Workbook

Sheet Negócios
A1: ANO | B1: MES | C1: ID_DO_CLIENTE | D1: CLIENTE | E1: ID_NEGOCIO | F1: CONTRATO | G1: ID_ITEM_DE_LINHA | H1: CATEGORIA_DO_ITEM | I1: BOOKING | J1: ARR | K1: RESTANTE_ARR | L1: MRR | M1: NMRR | N1: MRR_EXPANSAO | O1: MRR_RENOVACAO | P1: CONSULTOR | Q1: EQUIPE | R1: VERTICAL | S1: FECHAMENTO_NEGOCIO | T1: FECHAMENTO_AJUSTADO | U1: DATA_DE_INICIO | V1: DATA_DE_RENOVACAO | W1: VIGENCIA | X1: DURACAO | Y1: TIPO_DO_CONTRATO | Z1: TIPO_DA_VENDA | AA1: FORMA_DE_PAGAMENTO | AB1: PARCELAS | AC1: PIPELINE | AD1: ITEM_DE_LINHA | AE1: FAMILIA_DO_ITEM_DE_LINHA | AF1: APLICACAO_DO_ITEM_DE_LINHA | AG1: Acel Form Pag | AH1: Pago >400k
A2: 2026 | B2: 1 | C2: 19435599785 | D2: Prefeitura do Município de Cianorte | E2: 21648281648 | F2: 635639 | G2: 49516753480 | H2: Software | I2: 7432 | J2: 7432 | K2: 0 | L2: 619.33333 | M2: 0 | N2: 0 | O2: 0 | P2: deize.rudek@altoqi.com.br | Q2: B2G | R2: B2G | S2: 46041 | T2: 46041 | U2: 45982 | W2: 12 meses | X2: 12 | Y2: Vitalício | AA2: Transferência bancária | AB2: 1 | AC2: Comercial B2G | AD2: SSA 1 ano para AltoQi Builder Premium Governo | AE2: Builder | AF2: Premium | AG2: =IF(IFERROR(SEARCH("Recorrente",AA2),0)>0,"Recorrente",IF(AB2=1,"À Vista",IF(AB2<=3,"CC 3x",IF(AB2<=12,"CC 12x",IF(AB2>12,"Recorrente",""))))) -> À Vista | AH2: =IF(AND(SUMIF(E:E,E2,I:I)>=400000,Q2="B2G"),"n","")
A3: 2026 | B3: 1 | C3: 19435599785 | D3: Prefeitura do Município de Cianorte | E3: 21648281648 | F3: 635639 | G3: 49516753481 | H3: Software | I3: 10695 | J3: 10695 | K3: 0 | L3: 891.25 | M3: 0 | N3: 0 | O3: 0 | P3: deize.rudek@altoqi.com.br | Q3: B2G | R3: B2G | S3: 46041 | T3: 46041 | U3: 45982 | W3: 12 meses | X3: 12 | Y3: Vitalício | AA3: Transferência bancária | AB3: 1 | AC3: Comercial B2G | AD3: SSA 1 ano para AltoQi Eberick Infinity Governo | AE3: Eberick | AF3: Infinity | AG3: =IF(IFERROR(SEARCH("Recorrente",AA3),0)>0,"Recorrente",IF(AB3=1,"À Vista",IF(AB3<=3,"CC 3x",IF(AB3<=12,"CC 12x",IF(AB3>12,"Recorrente",""))))) -> À Vista | AH3: =IF(AND(SUMIF(E:E,E3,I:I)>=400000,Q3="B2G"),"n","")
A4: 2026 | B4: 1 | C4: 19435599785 | D4: Prefeitura do Município de Cianorte | E4: 21648281648 | F4: 635639 | G4: 49516753482 | H4: Software | I4: 5799 | J4: 5799 | K4: 0 | L4: 483.25 | M4: 0 | N4: 0 | O4: 0 | P4: deize.rudek@altoqi.com.br | Q4: B2G | R4: B2G | S4: 46041 | T4: 46041 | U4: 45982 | W4: 12 meses | X4: 12 | Y4: Vitalício | AA4: Transferência bancária | AB4: 1 | AC4: Comercial B2G | AD4: SSA 1 ano para AltoQi Builder Infinity Governo | AE4: Builder | AF4: Infinity | AG4: =IF(IFERROR(SEARCH("Recorrente",AA4),0)>0,"Recorrente",IF(AB4=1,"À Vista",IF(AB4<=3,"CC 3x",IF(AB4<=12,"CC 12x",IF(AB4>12,"Recorrente",""))))) -> À Vista | AH4: =IF(AND(SUMIF(E:E,E4,I:I)>=400000,Q4="B2G"),"n","")
A5: 2026 | B5: 1 | C5: 19435599785 | D5: Prefeitura do Município de Cianorte | E5: 21817048369 | F5: 635661 | G5: 49669089590 | H5: Software | I5: 15980.16 | J5: 15980.16 | K5: 0 | L5: 1331.68 | M5: 1331.68 | N5: 0 | O5: 0 | P5: deize.rudek@altoqi.com.br | Q5: B2G | R5: B2G | S5: 46043 | T5: 46043 | V5: 46408 | W5: 12 meses | X5: 12 | Y5: Assinatura | AA5: Transferência bancária | AB5: 1 | AC5: Comercial B2G | AD5: Plano Visus Obras Públicas Premium Governo | AE5: Visus Obras Públicas | AF5: Premium | AG5: =IF(IFERROR(SEARCH("Recorrente",AA5),0)>0,"Recorrente",IF(AB5=1,"À Vista",IF(AB5<=3,"CC 3x",IF(AB5<=12,"CC 12x",IF(AB5>12,"Recorrente",""))))) -> À Vista | AH5: =IF(AND(SUMIF(E:E,E5,I:I)>=400000,Q5="B2G"),"n","")
A6: 2026 | B6: 1 | C6: 19435640354 | D6: FUNDACAO UNIVERSIDADE FEDERAL DA GRANDE DOURADOS | E6: 29857451798 | F6: 635750 | G6: 49949823822 | H6: Software | I6: 13932 | J6: 13932 | K6: 0 | L6: 1161 | M6: 1161 | N6: 0 | O6: 0 | P6: deize.rudek@altoqi.com.br | Q6: B2G | R6: B2G | S6: 46049 | T6: 46049 | V6: 46414 | W6: 12 meses | X6: 12 | Y6: Assinatura | AA6: Transferência bancária | AB6: 1 | AC6: Comercial B2G | AD6: Plano AltoQi Builder Premium Governo | AE6: Builder | AF6: Premium | AG6: =IF(IFERROR(SEARCH("Recorrente",AA6),0)>0,"Recorrente",IF(AB6=1,"À Vista",IF(AB6<=3,"CC 3x",IF(AB6<=12,"CC 12x",IF(AB6>12,"Recorrente",""))))) -> À Vista | AH6: =IF(AND(SUMIF(E:E,E6,I:I)>=400000,Q6="B2G"),"n","")
A7: 2026 | B7: 1 | C7: 19435640354 | D7: FUNDACAO UNIVERSIDADE FEDERAL DA GRANDE DOURADOS | E7: 29857451798 | F7: 635750 | G7: 49949823823 | H7: Software | I7: 5436 | J7: 5436 | K7: 0 | L7: 453 | M7: 453 | N7: 0 | O7: 0 | P7: deize.rudek@altoqi.com.br | Q7: B2G | R7: B2G | S7: 46049 | T7: 46049 | V7: 46414 | W7: 12 meses | X7: 12 | Y7: Assinatura | AA7: Transferência bancária | AB7: 1 | AC7: Comercial B2G | AD7: Plano AltoQi Eberick Premium Governo | AE7: Eberick | AF7: Premium | AG7: =IF(IFERROR(SEARCH("Recorrente",AA7),0)>0,"Recorrente",IF(AB7=1,"À Vista",IF(AB7<=3,"CC 3x",IF(AB7<=12,"CC 12x",IF(AB7>12,"Recorrente",""))))) -> À Vista | AH7: =IF(AND(SUMIF(E:E,E7,I:I)>=400000,Q7="B2G"),"n","")
A8: 2026 | B8: 1 | C8: 19435564728 | D8: Prefeitura Municipal de Imbe | E8: 29861060658 | F8: 635812 | G8: 50425912479 | H8: Software | I8: 105560.16 | J8: 52780.08 | K8: 52780.08 | L8: 4398.34 | M8: 4398.34 | N8: 0 | O8: 0 | P8: deize.rudek@altoqi.com.br | Q8: B2G | R8: B2G | S8: 46052 | T8: 46052 | V8: 46782 | W8: 24 meses | X8: 24 | Y8: Assinatura | AA8: Transferência bancária | AB8: 1 | AC8: Comercial B2G | AD8: Plataforma BIM - AltoQi Gestão Pública – Projetos, Gestão e Controle de Custos | AE8: Visus Control Tower | AF8: Sem Aplicação | AG8: =IF(IFERROR(SEARCH("Recorrente",AA8),0)>0,"Recorrente",IF(AB8=1,"À Vista",IF(AB8<=3,"CC 3x",IF(AB8<=12,"CC 12x",IF(AB8>12,"Recorrente",""))))) -> À Vista | AH8: =IF(AND(SUMIF(E:E,E8,I:I)>=400000,Q8="B2G"),"n","")
A9: 2026 | B9: 1 | C9: 19540695847 | D9: MUNICIPIO DE REALEZA | E9: 30153859675 | F9: 635747 | G9: 49949879727 | H9: Software | I9: 7432 | J9: 3716 | K9: 3716 | L9: 309.66667 | M9: 0 | N9: 0 | O9: 0 | P9: deize.rudek@altoqi.com.br | Q9: B2G | R9: B2G | S9: 46049 | T9: 46049 | W9: 24 meses | X9: 24 | Y9: Vitalício | AA9: Transferência bancária | AB9: 1 | AC9: Comercial B2G | AD9: SSA 2 anos para AltoQi Builder Premium Governo | AE9: Builder | AF9: Premium | AG9: =IF(IFERROR(SEARCH("Recorrente",AA9),0)>0,"Recorrente",IF(AB9=1,"À Vista",IF(AB9<=3,"CC 3x",IF(AB9<=12,"CC 12x",IF(AB9>12,"Recorrente",""))))) -> À Vista | AH9: =IF(AND(SUMIF(E:E,E9,I:I)>=400000,Q9="B2G"),"n","")
A10: 2026 | B10: 1 | C10: 19540695847 | D10: MUNICIPIO DE REALEZA | E10: 30153859675 | F10: 635747 | G10: 49949879728 | H10: Software | I10: 18576 | J10: 0 | K10: 0 | L10: 0 | M10: 0 | N10: 0 | O10: 0 | P10: deize.rudek@altoqi.com.br | Q10: B2G | R10: B2G | S10: 46049 | T10: 46049 | W10: Vitalício | Y10: Vitalício | AA10: Transferência bancária | AB10: 1 | AC10: Comercial B2G | AD10: Plano Builder 2025 Premium Governo | AE10: Builder | AF10: Premium | AG10: =IF(IFERROR(SEARCH("Recorrente",AA10),0)>0,"Recorrente",IF(AB10=1,"À Vista",IF(AB10<=3,"CC 3x",IF(AB10<=12,"CC 12x",IF(AB10>12,"Recorrente",""))))) -> À Vista | AH10: =IF(AND(SUMIF(E:E,E10,I:I)>=400000,Q10="B2G"),"n","")
A11: 2026 | B11: 1 | C11: 19540695847 | D11: MUNICIPIO DE REALEZA | E11: 30153859675 | F11: 635747 | G11: 49949879729 | H11: Software | I11: 21744 | J11: 0 | K11: 0 | L11: 0 | M11: 0 | N11: 0 | O11: 0 | P11: deize.rudek@altoqi.com.br | Q11: B2G | R11: B2G | S11: 46049 | T11: 46049 | W11: Vitalício | Y11: Vitalício | AA11: Transferência bancária | AB11: 1 | AC11: Comercial B2G | AD11: Plano Eberick 2025 Premium Governo | AE11: Eberick | AF11: Premium | AG11: =IF(IFERROR(SEARCH("Recorrente",AA11),0)>0,"Recorrente",IF(AB11=1,"À Vista",IF(AB11<=3,"CC 3x",IF(AB11<=12,"CC 12x",IF(AB11>12,"Recorrente",""))))) -> À Vista | AH11: =IF(AND(SUMIF(E:E,E11,I:I)>=400000,Q11="B2G"),"n","")
A12: 2026 | B12: 1 | C12: 19540695847 | D12: MUNICIPIO DE REALEZA | E12: 30153859675 | F12: 635747 | G12: 49949879730 | H12: Software | I12: 8698 | J12: 4349 | K12: 4349 | L12: 362.41667 | M12: 0 | N12: 0 | O12: 0 | P12: deize.rudek@altoqi.com.br | Q12: B2G | R12: B2G | S12: 46049 | T12: 46049 | W12: 24 meses | X12: 24 | Y12: Vitalício | AA12: Transferência bancária | AB12: 1 | AC12: Comercial B2G | AD12: SSA 2 anos para AltoQi Eberick Premium Governo | AE12: Eberick | AF12: Premium | AG12: =IF(IFERROR(SEARCH("Recorrente",AA12),0)>0,"Recorrente",IF(AB12=1,"À Vista",IF(AB12<=3,"CC 3x",IF(AB12<=12,"CC 12x",IF(AB12>12,"Recorrente",""))))) -> À Vista | AH12: =IF(AND(SUMIF(E:E,E12,I:I)>=400000,Q12="B2G"),"n","")
A13: 2026 | B13: 1 | C13: 30176499367 | D13: UNIVERSIDADE FEDERAL DE UBERLANDIA | E13: 33917004397 | F13: 635688 | G13: 49708158237 | H13: Software | I13: 57984 | J13: 0 | K13: 0 | L13: 0 | M13: 0 | N13: 0 | O13: 0 | P13: soraia@altoqi.com.br | Q13: B2G | R13: B2G | S13: 46044 | T13: 46044 | W13: Vitalício | Y13: Vitalício | AA13: Transferência bancária | AB13: 1 | AC13: Comercial B2G | AD13: Plano AltoQi Builder 2025 Infinity Governo - Upgrade | AE13: Builder | AF13: Infinity | AG13: =IF(IFERROR(SEARCH("Recorrente",AA13),0)>0,"Recorrente",IF(AB13=1,"À Vista",IF(AB13<=3,"CC 3x",IF(AB13<=12,"CC 12x",IF(AB13>12,"Recorrente",""))))) -> À Vista | AH13: =IF(AND(SUMIF(E:E,E13,I:I)>=400000,Q13="B2G"),"n","")
A14: 2026 | B14: 1 | C14: 35907319569 | D14: ORGANIZACAO BRASILEIRA PARA O DESENVOLVIMENTO CIENTIFICO E TECNOLOGICO DO CONTROLE DO ESPACO AEREO-CTCEA | E14: 38789220430 | F14: 635786 | G14: 50274464379 | H14: Software | I14: 21744 | J14: 21744 | K14: 0 | L14: 1812 | M14: 0 | N14: 1812 | O14: 0 | P14: jordayn.almeida@altoqi.com.br | Q14: B2G | R14: B2G | S14: 46051 | T14: 46051 | U14: 46000 | V14: 46416 | W14: 12 meses | X14: 12 | Y14: Assinatura | AA14: Transferência bancária | AB14: 1 | AC14: Comercial B2G | AD14: Plano AltoQi Builder Infinity Governo | AE14: Builder | AF14: Infinity | AG14: =IF(IFERROR(SEARCH("Recorrente",AA14),0)>0,"Recorrente",IF(AB14=1,"À Vista",IF(AB14<=3,"CC 3x",IF(AB14<=12,"CC 12x",IF(AB14>12,"Recorrente",""))))) -> À Vista | AH14: =IF(AND(SUMIF(E:E,E14,I:I)>=400000,Q14="B2G"),"n","")
A15: 2026 | B15: 1 | C15: 35907319569 | D15: ORGANIZACAO BRASILEIRA PARA O DESENVOLVIMENTO CIENTIFICO E TECNOLOGICO DO CONTROLE DO ESPACO AEREO-CTCEA | E15: 38789220430 | F15: 635786 | G15: 50274464379 | H15: Software | I15: 21744 | J15: 21744 | K15: 0 | L15: 1812 | M15: 0 | N15: 1812 | O15: 0 | P15: soraia@altoqi.com.br | Q15: B2G | R15: B2G | S15: 46051 | T15: 46051 | U15: 46000 | V15: 46416 | W15: 12 meses | X15: 12 | Y15: Assinatura | AA15: Transferência bancária | AB15: 1 | AC15: Comercial B2G | AD15: Plano AltoQi Builder Infinity Governo | AE15: Builder | AF15: Infinity | AG15: =IF(IFERROR(SEARCH("Recorrente",AA15),0)>0,"Recorrente",IF(AB15=1,"À Vista",IF(AB15<=3,"CC 3x",IF(AB15<=12,"CC 12x",IF(AB15>12,"Recorrente",""))))) -> À Vista | AH15: =IF(AND(SUMIF(E:E,E15,I:I)>=400000,Q15="B2G"),"n","")
A16: 2026 | B16: 1 | C16: 19485596080 | D16: MUNICÍPIO DE FOZ DO IGUAÇU | E16: 39962115145 | F16: 635520 | G16: 48560859043 | H16: Software | I16: 15990 | J16: 15990 | K16: 0 | L16: 1332.5 | M16: 1332.5 | N16: 0 | O16: 0 | P16: henry.petersen@altoqi.com.br | Q16: B2G | R16: B2G | S16: 46030 | T16: 46030 | V16: 46395 | W16: 12 meses | X16: 12 | Y16: Assinatura | AA16: Transferência bancária | AB16: 1 | AC16: Comercial B2G | AD16: Plano Visus Obras Públicas Infinity Governo | AE16: Visus Obras Públicas | AF16: Infinity | AG16: =IF(IFERROR(SEARCH("Recorrente",AA16),0)>0,"Recorrente",IF(AB16=1,"À Vista",IF(AB16<=3,"CC 3x",IF(AB16<=12,"CC 12x",IF(AB16>12,"Recorrente",""))))) -> À Vista | AH16: =IF(AND(SUMIF(E:E,E16,I:I)>=400000,Q16="B2G"),"n","")
A17: 2026 | B17: 1 | C17: 19435497254 | D17: FUNDACAO CULTURAL E DE FOMENTO A PESQUISA, ENSINO, EXTENSAO E INOVACAO - FADEX | E17: 40516172212 | F17: 625579 | G17: 49068412739 | H17: Software | I17: 5436 | J17: 5436 | K17: 0 | L17: 453 | M17: 0 | N17: 46 | O17: 407 | P17: tabata.couto@altoqi.com.br | Q17: B2G | R17: B2G | S17: 46036 | T17: 46036 | U17: 46038 | V17: 46403 | W17: 12 meses | X17: 12 | Y17: Assinatura | Z17: Renovação com Expansão | AA17: Transferência bancária | AB17: 1 | AC17: Comercial B2G | AD17: Plano AltoQi Eberick Premium Governo | AE17: Eberick | AF17: Premium | AG17: =IF(IFERROR(SEARCH("Recorrente",AA17),0)>0,"Recorrente",IF(AB17=1,"À Vista",IF(AB17<=3,"CC 3x",IF(AB17<=12,"CC 12x",IF(AB17>12,"Recorrente",""))))) -> À Vista | AH17: =IF(AND(SUMIF(E:E,E17,I:I)>=400000,Q17="B2G"),"n","")
A18: 2026 | B18: 1 | C18: 29124531791 | D18: ASSOCIACAO PAULISTA SUDOESTE DA IASD | E18: 41109232824 | F18: 625944 | G18: 48886123146 | H18: Software | I18: 5394 | J18: 5394 | K18: 0 | L18: 449.5 | M18: 0 | N18: 55.5 | O18: 394 | P18: jenifer.soares@altoqi.com.br | Q18: IES | R18: B2E | S18: 46035 | T18: 46035 | U18: 46050 | V18: 46415 | W18: 12 meses | X18: 12 | Y18: Assinatura | Z18: Renovação | AA18: Boleto | AB18: 1 | AC18: Comercial B2E - Instituição | AD18: Plano Builder Premium | AE18: Builder | AF18: Premium | AG18: =IF(IFERROR(SEARCH("Recorrente",AA18),0)>0,"Recorrente",IF(AB18=1,"À Vista",IF(AB18<=3,"CC 3x",IF(AB18<=12,"CC 12x",IF(AB18>12,"Recorrente",""))))) -> À Vista | AH18: =IF(AND(SUMIF(E:E,E18,I:I)>=400000,Q18="B2G"),"n","")
A19: 2026 | B19: 1 | C19: 29124531791 | D19: ASSOCIACAO PAULISTA SUDOESTE DA IASD | E19: 41109232824 | F19: 625944 | G19: 48886123147 | H19: Software | I19: 5394 | J19: 5394 | K19: 0 | L19: 449.5 | M19: 0 | N19: 55.5 | O19: 394 | P19: jenifer.soares@altoqi.com.br | Q19: IES | R19: B2E | S19: 46035 | T19: 46035 | U19: 46050 | V19: 46415 | W19: 12 meses | X19: 12 | Y19: Assinatura | Z19: Renovação | AA19: Boleto | AB19: 1 | AC19: Comercial B2E - Instituição | AD19: Plano Eberick Premium | AE19: Eberick | AF19: Premium | AG19: =IF(IFERROR(SEARCH("Recorrente",AA19),0)>0,"Recorrente",IF(AB19=1,"À Vista",IF(AB19<=3,"CC 3x",IF(AB19<=12,"CC 12x",IF(AB19>12,"Recorrente",""))))) -> À Vista | AH19: =IF(AND(SUMIF(E:E,E19,I:I)>=400000,Q19="B2G"),"n","")
A20: 2026 | B20: 1 | C20: 20534852467 | D20: MUNICIPIO DE EMBU DAS ARTES | E20: 41206575190 | F20: 625980 | G20: 50350997306 | H20: Software | I20: 4007.16 | J20: 4007.16 | K20: 0 | L20: 333.93 | M20: 0 | N20: 14.93 | O20: 319 | P20: angelica.steinbach@altoqi.com.br | Q20: B2G | R20: B2G | S20: 46051 | T20: 46051 | U20: 46051 | V20: 46416 | W20: 12 meses | X20: 12 | Y20: Assinatura | Z20: Renovação | AA20: Transferência bancária | AB20: 1 | AC20: Comercial B2G | AD20: Plano AltoQi Builder Premium Governo | AE20: Builder | AF20: Premium | AG20: =IF(IFERROR(SEARCH("Recorrente",AA20),0)>0,"Recorrente",IF(AB20=1,"À Vista",IF(AB20<=3,"CC 3x",IF(AB20<=12,"CC 12x",IF(AB20>12,"Recorrente",""))))) -> À Vista | AH20: =IF(AND(SUMIF(E:E,E20,I:I)>=400000,Q20="B2G"),"n","")
A21: 2026 | B21: 1 | C21: 19435452707 | D21: MUNICIPIO DE URUOCA | E21: 41255385229 | F21: 635553 | G21: 48885894405 | H21: Software | I21: 4644 | J21: 4644 | K21: 0 | L21: 387 | M21: 0 | N21: 52.52 | O21: 334.47857 | P21: deize.rudek@altoqi.com.br | Q21: B2G | R21: B2G | S21: 46035 | T21: 46035 | U21: 46052 | V21: 46400 | W21: 12 meses | X21: 12 | Y21: Assinatura | AA21: Transferência bancária | AB21: 1 | AC21: Comercial B2G | AD21: Plano AltoQi Builder Premium Governo | AE21: Builder | AF21: Premium | AG21: =IF(IFERROR(SEARCH("Recorrente",AA21),0)>0,"Recorrente",IF(AB21=1,"À Vista",IF(AB21<=3,"CC 3x",IF(AB21<=12,"CC 12x",IF(AB21>12,"Recorrente",""))))) -> À Vista | AH21: =IF(AND(SUMIF(E:E,E21,I:I)>=400000,Q21="B2G"),"n","")
A22: 2026 | B22: 1 | C22: 19435452707 | D22: MUNICIPIO DE URUOCA | E22: 41255385229 | F22: 635553 | G22: 48885894406 | H22: Software | I22: 5436 | J22: 5436 | K22: 0 | L22: 453 | M22: 0 | N22: 61.48 | O22: 391.52143 | P22: deize.rudek@altoqi.com.br | Q22: B2G | R22: B2G | S22: 46035 | T22: 46035 | U22: 46052 | V22: 46400 | W22: 12 meses | X22: 12 | Y22: Assinatura | AA22: Transferência bancária | AB22: 1 | AC22: Comercial B2G | AD22: Plano AltoQi Eberick Premium Governo | AE22: Eberick | AF22: Premium | AG22: =IF(IFERROR(SEARCH("Recorrente",AA22),0)>0,"Recorrente",IF(AB22=1,"À Vista",IF(AB22<=3,"CC 3x",IF(AB22<=12,"CC 12x",IF(AB22>12,"Recorrente",""))))) -> À Vista | AH22: =IF(AND(SUMIF(E:E,E22,I:I)>=400000,Q22="B2G"),"n","")
A23: 2026 | B23: 1 | C23: 19435709240 | D23: VICTA PARTICIPACOES LTDA | E23: 41513028145 | F23: 635488 | G23: 48457676122 | H23: Software | I23: 8394 | J23: 8394 | K23: 0 | L23: 699.5 | M23: 699.5 | N23: 0 | O23: 0 | P23: henrique.silva@altoqi.com.br | Q23: B2B Construtora | R23: B2B Construtora | S23: 46028 | T23: 46028 | V23: 46393 | W23: 12 meses | X23: 12 | Y23: Assinatura | AA23: Boleto Recorrente | AB23: 12 | AC23: Comercial B2B - Construtoras | AD23: Plano Visus Cost Management Enterprise | AE23: Visus Cost | AF23: Enterprise | AG23: =IF(IFERROR(SEARCH("Recorrente",AA23),0)>0,"Recorrente",IF(AB23=1,"À Vista",IF(AB23<=3,"CC 3x",IF(AB23<=12,"CC 12x",IF(AB23>12,"Recorrente",""))))) -> Recorrente | AH23: =IF(AND(SUMIF(E:E,E23,I:I)>=400000,Q23="B2G"),"n","")
A24: 2026 | B24: 1 | C24: 19435393801 | D24: UNIVERSIDADE TECNOLOGICA FEDERAL DO PARANA | E24: 43288784965 | F24: 635824 | G24: 50425093796 | H24: Software | I24: 23220 | J24: 23220 | K24: 0 | L24: 1935 | M24: 1935 | N24: 0 | O24: 0 | P24: fernanda.barbosa@altoqi.com.br | Q24: B2G | R24: B2G | S24: 46052 | T24: 46052 | V24: 46417 | W24: 12 meses | X24: 12 | Y24: Assinatura | AA24: Transferência bancária | AB24: 1 | AC24: Comercial B2G | AD24: Plano AltoQi Builder Premium Governo | AE24: Builder | AF24: Premium | AG24: =IF(IFERROR(SEARCH("Recorrente",AA24),0)>0,"Recorrente",IF(AB24=1,"À Vista",IF(AB24<=3,"CC 3x",IF(AB24<=12,"CC 12x",IF(AB24>12,"Recorrente",""))))) -> À Vista | AH24: =IF(AND(SUMIF(E:E,E24,I:I)>=400000,Q24="B2G"),"n","")
A25: 2026 | B25: 1 | C25: 19435393801 | D25: UNIVERSIDADE TECNOLOGICA FEDERAL DO PARANA | E25: 43288784965 | F25: 635824 | G25: 50425093798 | H25: Software | I25: 7990.08 | J25: 7990.08 | K25: 0 | L25: 665.84 | M25: 665.84 | N25: 0 | O25: 0 | P25: fernanda.barbosa@altoqi.com.br | Q25: B2G | R25: B2G | S25: 46052 | T25: 46052 | V25: 46417 | W25: 12 meses | X25: 12 | Y25: Assinatura | AA25: Transferência bancária | AB25: 1 | AC25: Comercial B2G | AD25: Plano Visus Obras Públicas Premium Governo | AE25: Visus Obras Públicas | AF25: Premium | AG25: =IF(IFERROR(SEARCH("Recorrente",AA25),0)>0,"Recorrente",IF(AB25=1,"À Vista",IF(AB25<=3,"CC 3x",IF(AB25<=12,"CC 12x",IF(AB25>12,"Recorrente",""))))) -> À Vista | AH25: =IF(AND(SUMIF(E:E,E25,I:I)>=400000,Q25="B2G"),"n","")
A26: 2026 | B26: 1 | C26: 19435393801 | D26: UNIVERSIDADE TECNOLOGICA FEDERAL DO PARANA | E26: 43288784965 | F26: 635824 | G26: 50425093799 | H26: Software | I26: 5436 | J26: 5436 | K26: 0 | L26: 453 | M26: 453 | N26: 0 | O26: 0 | P26: fernanda.barbosa@altoqi.com.br | Q26: B2G | R26: B2G | S26: 46052 | T26: 46052 | V26: 46417 | W26: 12 meses | X26: 12 | Y26: Assinatura | AA26: Transferência bancária | AB26: 1 | AC26: Comercial B2G | AD26: Plano AltoQi Eberick Premium Governo | AE26: Eberick | AF26: Premium | AG26: =IF(IFERROR(SEARCH("Recorrente",AA26),0)>0,"Recorrente",IF(AB26=1,"À Vista",IF(AB26<=3,"CC 3x",IF(AB26<=12,"CC 12x",IF(AB26>12,"Recorrente",""))))) -> À Vista | AH26: =IF(AND(SUMIF(E:E,E26,I:I)>=400000,Q26="B2G"),"n","")
A27: 2026 | B27: 1 | C27: 19435497254 | D27: FUNDACAO CULTURAL E DE FOMENTO A PESQUISA, ENSINO, EXTENSAO E INOVACAO - FADEX | E27: 44063859254 | F27: 627642 | G27: 49007574180 | H27: Software | I27: 14496 | J27: 14496 | K27: 0 | L27: 1208 | M27: 1208 | N27: 0 | O27: 0 | P27: tabata.couto@altoqi.com.br | Q27: B2G | R27: B2G | S27: 46037 | T27: 46037 | V27: 46467 | W27: 12 meses | X27: 14 | Y27: Assinatura | Z27: Renovação | AA27: Transferência bancária | AB27: 1 | AC27: Comercial B2G | AD27: Plano AltoQi Builder Infinity Governo | AE27: Builder | AF27: Infinity | AG27: =IF(IFERROR(SEARCH("Recorrente",AA27),0)>0,"Recorrente",IF(AB27=1,"À Vista",IF(AB27<=3,"CC 3x",IF(AB27<=12,"CC 12x",IF(AB27>12,"Recorrente",""))))) -> À Vista | AH27: =IF(AND(SUMIF(E:E,E27,I:I)>=400000,Q27="B2G"),"n","")
A28: 2026 | B28: 1 | C28: 29287902612 | D28: UNESPAR - UNIVERSIDADE ESTADUAL DO PARANA | E28: 44506492043 | F28: 635514 | G28: 48545432894 | H28: Software | I28: 13368 | J28: 13368 | K28: 0 | L28: 1114 | M28: 1114 | N28: 0 | O28: 0 | P28: fernanda.barbosa@altoqi.com.br | Q28: B2G | R28: B2G | S28: 46030 | T28: 46030 | V28: 46395 | W28: 12 meses | X28: 12 | Y28: Assinatura | AA28: Transferência bancária | AB28: 1 | AC28: Comercial B2G | AD28: Plano AltoQi Eberick Infinity Governo | AE28: Eberick | AF28: Infinity | AG28: =IF(IFERROR(SEARCH("Recorrente",AA28),0)>0,"Recorrente",IF(AB28=1,"À Vista",IF(AB28<=3,"CC 3x",IF(AB28<=12,"CC 12x",IF(AB28>12,"Recorrente",""))))) -> À Vista | AH28: =IF(AND(SUMIF(E:E,E28,I:I)>=400000,Q28="B2G"),"n","")
A29: 2026 | B29: 1 | C29: 19435447599 | D29: Prefeitura Municipal de Amambai-ms | E29: 45877912418 | F29: 635818 | G29: 50350906931 | H29: Software | I29: 32616 | J29: 10872 | K29: 21744 | L29: 906 | M29: 906 | N29: 0 | O29: 0 | P29: deize.rudek@altoqi.com.br | Q29: B2G | R29: B2G | S29: 46052 | T29: 46052 | V29: 47148 | W29: 36 meses | X29: 36 | Y29: Assinatura | AA29: Transferência bancária | AB29: 1 | AC29: Comercial B2G | AD29: Plano AltoQi Eberick Premium Governo | AE29: Eberick | AF29: Premium | AG29: =IF(IFERROR(SEARCH("Recorrente",AA29),0)>0,"Recorrente",IF(AB29=1,"À Vista",IF(AB29<=3,"CC 3x",IF(AB29<=12,"CC 12x",IF(AB29>12,"Recorrente",""))))) -> À Vista | AH29: =IF(AND(SUMIF(E:E,E29,I:I)>=400000,Q29="B2G"),"n","")
A30: 2026 | B30: 1 | C30: 19435447599 | D30: Prefeitura Municipal de Amambai-ms | E30: 45877912418 | F30: 635818 | G30: 50350906932 | H30: Software | I30: 27864 | J30: 9288 | K30: 18576 | L30: 774 | M30: 774 | N30: 0 | O30: 0 | P30: deize.rudek@altoqi.com.br | Q30: B2G | R30: B2G | S30: 46052 | T30: 46052 | V30: 47148 | W30: 36 meses | X30: 36 | Y30: Assinatura | AA30: Transferência bancária | AB30: 1 | AC30: Comercial B2G | AD30: Plano AltoQi Builder Premium Governo | AE30: Builder | AF30: Premium | AG30: =IF(IFERROR(SEARCH("Recorrente",AA30),0)>0,"Recorrente",IF(AB30=1,"À Vista",IF(AB30<=3,"CC 3x",IF(AB30<=12,"CC 12x",IF(AB30>12,"Recorrente",""))))) -> À Vista | AH30: =IF(AND(SUMIF(E:E,E30,I:I)>=400000,Q30="B2G"),"n","")
A31: 2026 | B31: 1 | C31: 19435567269 | D31: MUNICIPIO DE SAO BENTO DO SUL | E31: 46511646114 | F31: 635662 | G31: 49670317965 | H31: Curso | I31: 718.8 | J31: 718.8 | K31: 0 | L31: 59.9 | M31: 59.9 | N31: 0 | O31: 0 | P31: fernanda.barbosa@altoqi.com.br | Q31: B2G | R31: B2G | S31: 46043 | T31: 46043 | V31: 46408 | W31: 12 meses | X31: 12 | Y31: Curso | AA31: Transferência bancária | AB31: 1 | AC31: Comercial B2G | AD31: Plataforma AltoQi Education - Cursos de Software | AE31: Outros | AF31: Sem Aplicação | AG31: =IF(IFERROR(SEARCH("Recorrente",AA31),0)>0,"Recorrente",IF(AB31=1,"À Vista",IF(AB31<=3,"CC 3x",IF(AB31<=12,"CC 12x",IF(AB31>12,"Recorrente",""))))) -> À Vista | AH31: =IF(AND(SUMIF(E:E,E31,I:I)>=400000,Q31="B2G"),"n","")
A32: 2026 | B32: 1 | C32: 42179585166 | D32: MINISTERIO PUBLICO DO ESTADO DO ESPIRITO SANTO | E32: 46554281576 | F32: 635666 | G32: 49608453559 | H32: Software | I32: 10872 | J32: 5436 | K32: 5436 | L32: 453 | M32: 453 | N32: 0 | O32: 0 | P32: angelica.steinbach@altoqi.com.br | Q32: B2G | R32: B2G | S32: 46043 | T32: 46043 | V32: 46773 | W32: 24 meses | X32: 24 | Y32: Assinatura | AA32: Transferência bancária | AB32: 1 | AC32: Comercial B2G | AD32: Plano AltoQi Eberick Premium Governo | AE32: Eberick | AF32: Premium | AG32: =IF(IFERROR(SEARCH("Recorrente",AA32),0)>0,"Recorrente",IF(AB32=1,"À Vista",IF(AB32<=3,"CC 3x",IF(AB32<=12,"CC 12x",IF(AB32>12,"Recorrente",""))))) -> À Vista | AH32: =IF(AND(SUMIF(E:E,E32,I:I)>=400000,Q32="B2G"),"n","")
A33: 2026 | B33: 1 | C33: 42179585166 | D33: MINISTERIO PUBLICO DO ESTADO DO ESPIRITO SANTO | E33: 46554281576 | F33: 635666 | G33: 49608453560 | H33: Software | I33: 9288 | J33: 4644 | K33: 4644 | L33: 387 | M33: 387 | N33: 0 | O33: 0 | P33: angelica.steinbach@altoqi.com.br | Q33: B2G | R33: B2G | S33: 46043 | T33: 46043 | V33: 46773 | W33: 24 meses | X33: 24 | Y33: Assinatura | AA33: Transferência bancária | AB33: 1 | AC33: Comercial B2G | AD33: Plano AltoQi Builder Premium Governo | AE33: Builder | AF33: Premium | AG33: =IF(IFERROR(SEARCH("Recorrente",AA33),0)>0,"Recorrente",IF(AB33=1,"À Vista",IF(AB33<=3,"CC 3x",IF(AB33<=12,"CC 12x",IF(AB33>12,"Recorrente",""))))) -> À Vista | AH33: =IF(AND(SUMIF(E:E,E33,I:I)>=400000,Q33="B2G"),"n","")
A34: 2026 | B34: 1 | C34: 20535617041 | D34: MUNICIPIO DE ITAPECERICA DA SERRA | E34: 46559124409 | F34: 635778 | G34: 50273452422 | H34: Software | I34: 16308 | J34: 5436 | K34: 10872 | L34: 453 | M34: 453 | N34: 0 | O34: 0 | P34: deize.rudek@altoqi.com.br | Q34: B2G | R34: B2G | S34: 46050 | T34: 46050 | V34: 47146 | W34: 36 meses | X34: 36 | Y34: Assinatura | AA34: Transferência bancária | AB34: 1 | AC34: Comercial B2G | AD34: Plano AltoQi Eberick Premium Governo | AE34: Eberick | AF34: Premium | AG34: =IF(IFERROR(SEARCH("Recorrente",AA34),0)>0,"Recorrente",IF(AB34=1,"À Vista",IF(AB34<=3,"CC 3x",IF(AB34<=12,"CC 12x",IF(AB34>12,"Recorrente",""))))) -> À Vista | AH34: =IF(AND(SUMIF(E:E,E34,I:I)>=400000,Q34="B2G"),"n","")
A35: 2026 | B35: 1 | C35: 26512022954 | D35: RIBEIRO DO VALE ENGENHARIA LTDA | E35: 46588609583 | F35: 624533 | G35: 44801325474 | H35: Software | I35: 3299.88 | J35: 3299.88 | K35: 0 | L35: 274.99 | M35: 0 | N35: 25.16 | O35: 249.84 | P35: rubia.estipe@altoqi.com.br | Q35: Saving | R35: Saving | S35: 45979 | T35: 46023 | U35: 45994 | V35: 46359 | W35: 12 meses | X35: 12 | Y35: Assinatura | Z35: Renovação | AA35: Cartão de crédito | AB35: 12 | AC35: CS - Saving | AD35: Plano Builder Hidro Premium | AE35: Builder | AF35: Premium | AG35: =IF(IFERROR(SEARCH("Recorrente",AA35),0)>0,"Recorrente",IF(AB35=1,"À Vista",IF(AB35<=3,"CC 3x",IF(AB35<=12,"CC 12x",IF(AB35>12,"Recorrente",""))))) -> CC 12x | AH35: =IF(AND(SUMIF(E:E,E35,I:I)>=400000,Q35="B2G"),"n","")
A36: 2026 | B36: 1 | C36: 2075043 | D36: IGOR GUIMARAES MATIAS | E36: 46725753464 | F36: 503913 | G36: 45802403695 | H36: Software | I36: 2932.32 | J36: 2932.32 | K36: 0 | L36: 244.36 | M36: 0 | N36: 0 | O36: 244.36005 | P36: marcela@altoqi.com.br | Q36: Saving | R36: Saving | S36: 45992 | T36: 46023 | U36: 45996 | V36: 46361 | W36: 12 meses | X36: 12 | Y36: Assinatura | Z36: Renovação com Expansão | AA36: Pix | AB36: 1 | AC36: CS - Saving | AD36: Plano Builder Premium | AE36: Builder | AF36: Premium | AG36: =IF(IFERROR(SEARCH("Recorrente",AA36),0)>0,"Recorrente",IF(AB36=1,"À Vista",IF(AB36<=3,"CC 3x",IF(AB36<=12,"CC 12x",IF(AB36>12,"Recorrente",""))))) -> À Vista | AH36: =IF(AND(SUMIF(E:E,E36,I:I)>=400000,Q36="B2G"),"n","")
A37: 2026 | B37: 1 | C37: 2075043 | D37: IGOR GUIMARAES MATIAS | E37: 46725753464 | F37: 503913 | G37: 45802403697 | H37: Software | I37: 2932.32 | J37: 2932.32 | K37: 0 | L37: 244.36 | M37: 0 | N37: 0 | O37: 244.36005 | P37: marcela@altoqi.com.br | Q37: Saving | R37: Saving | S37: 45992 | T37: 46023 | U37: 45996 | V37: 46361 | W37: 12 meses | X37: 12 | Y37: Assinatura | Z37: Renovação com Expansão | AA37: Pix | AB37: 1 | AC37: CS - Saving | AD37: Plano Eberick Premium | AE37: Eberick | AF37: Premium | AG37: =IF(IFERROR(SEARCH("Recorrente",AA37),0)>0,"Recorrente",IF(AB37=1,"À Vista",IF(AB37<=3,"CC 3x",IF(AB37<=12,"CC 12x",IF(AB37>12,"Recorrente",""))))) -> À Vista | AH37: =IF(AND(SUMIF(E:E,E37,I:I)>=400000,Q37="B2G"),"n","")
A38: 2026 | B38: 1 | C38: 2075043 | D38: IGOR GUIMARAES MATIAS | E38: 46725753464 | F38: 503913 | G38: 45802403698 | H38: Software | I38: 2932.32 | J38: 2932.32 | K38: 0 | L38: 244.36 | M38: 0 | N38: 0 | O38: 244.36005 | P38: marcela@altoqi.com.br | Q38: Saving | R38: Saving | S38: 45992 | T38: 46023 | U38: 45996 | V38: 46361 | W38: 12 meses | X38: 12 | Y38: Assinatura | Z38: Renovação com Expansão | AA38: Pix | AB38: 1 | AC38: CS - Saving | AD38: Plano Builder Professional | AE38: Builder | AF38: Professional | AG38: =IF(IFERROR(SEARCH("Recorrente",AA38),0)>0,"Recorrente",IF(AB38=1,"À Vista",IF(AB38<=3,"CC 3x",IF(AB38<=12,"CC 12x",IF(AB38>12,"Recorrente",""))))) -> À Vista | AH38: =IF(AND(SUMIF(E:E,E38,I:I)>=400000,Q38="B2G"),"n","")
A39: 2026 | B39: 1 | C39: 20945228105 | D39: BMV ENGENHARIA LTDA | E39: 46813173130 | F39: 523210 | G39: 46407636880 | H39: Software | I39: 4278.84 | J39: 4278.84 | K39: 0 | L39: 356.57 | M39: 0 | N39: 0 | O39: 356.575 | P39: silvia.estipe@altoqi.com.br | Q39: Saving | R39: Saving | S39: 45995 | T39: 46023 | U39: 45999 | V39: 46364 | W39: 12 meses | X39: 12 | Y39: Assinatura | Z39: Renovação | AA39: Cartão de crédito - Recorrente | AB39: 12 | AC39: CS - Saving | AD39: Plano Builder Premium | AE39: Builder | AF39: Premium | AG39: =IF(IFERROR(SEARCH("Recorrente",AA39),0)>0,"Recorrente",IF(AB39=1,"À Vista",IF(AB39<=3,"CC 3x",IF(AB39<=12,"CC 12x",IF(AB39>12,"Recorrente",""))))) -> Recorrente | AH39: =IF(AND(SUMIF(E:E,E39,I:I)>=400000,Q39="B2G"),"n","")
A40: 2026 | B40: 1 | C40: 42326226253 | D40: ENERGIA CONSULT - ENGENHARIA, CONSULTORIA E GERENCIAMENTO DE PROJETOS LTDA | E40: 47253502621 | F40: 624563 | G40: 45846126405 | H40: Software | I40: 5754 | J40: 5754 | K40: 0 | L40: 479.5 | M40: 0 | N40: 30.5 | O40: 449 | P40: rubia.estipe@altoqi.com.br | Q40: Saving | R40: Saving | S40: 45992 | T40: 46023 | U40: 45995 | V40: 46360 | W40: 12 meses | X40: 12 | Y40: Assinatura | Z40: Renovação | AA40: Cartão de crédito | AB40: 12 | AC40: CS - Saving | AD40: Plano Eberick Premium | AE40: Eberick | AF40: Premium | AG40: =IF(IFERROR(SEARCH("Recorrente",AA40),0)>0,"Recorrente",IF(AB40=1,"À Vista",IF(AB40<=3,"CC 3x",IF(AB40<=12,"CC 12x",IF(AB40>12,"Recorrente",""))))) -> CC 12x | AH40: =IF(AND(SUMIF(E:E,E40,I:I)>=400000,Q40="B2G"),"n","")
A41: 2026 | B41: 1 | C41: 19435398462 | D41: RIBEIRO LOPES CONSULTORIA E SERVIÇOS | E41: 47292692739 | F41: 605501 | G41: 44212418208 | H41: Software | I41: 5923.44 | J41: 5923.44 | K41: 0 | L41: 493.62 | M41: 0 | N41: 7.17 | O41: 486.45 | P41: marcela@altoqi.com.br | Q41: Saving | R41: Saving | S41: 45973 | T41: 46023 | U41: 46003 | V41: 46368 | W41: 12 meses | X41: 12 | Y41: Assinatura | Z41: Renovação com Expansão | AA41: Cartão de crédito - Recorrente | AB41: 12 | AC41: CS - Saving | AD41: Plano Builder Infinity | AE41: Builder | AF41: Infinity | AG41: =IF(IFERROR(SEARCH("Recorrente",AA41),0)>0,"Recorrente",IF(AB41=1,"À Vista",IF(AB41<=3,"CC 3x",IF(AB41<=12,"CC 12x",IF(AB41>12,"Recorrente",""))))) -> Recorrente | AH41: =IF(AND(SUMIF(E:E,E41,I:I)>=400000,Q41="B2G"),"n","")
A42: 2026 | B42: 1 | C42: 2128769 | D42: Inaldo Almeida Dias | E42: 47476939324 | F42: 504233 | G42: 44167681699 | H42: Software | I42: 3669 | J42: 3669 | K42: 0 | L42: 305.75 | M42: 0 | N42: 36.36 | O42: 269.39 | P42: jaqueline.correa@altoqi.com.br | Q42: Saving | R42: Saving | S42: 45985 | T42: 46023 | U42: 46004 | V42: 46369 | W42: 12 meses | X42: 12 | Y42: Assinatura | Z42: Renovação | AA42: Pix | AB42: 1 | AC42: CS - Saving | AD42: Plano Eberick Premium | AE42: Eberick | AF42: Premium | AG42: =IF(IFERROR(SEARCH("Recorrente",AA42),0)>0,"Recorrente",IF(AB42=1,"À Vista",IF(AB42<=3,"CC 3x",IF(AB42<=12,"CC 12x",IF(AB42>12,"Recorrente",""))))) -> À Vista | AH42: =IF(AND(SUMIF(E:E,E42,I:I)>=400000,Q42="B2G"),"n","")
A43: 2026 | B43: 1 | C43: 19435374438 | D43: JUNKES EMPREENDIMENTOS IMOBILIARIOS LTDA | E43: 47479106969 | F43: 635737 | G43: 49944656906 | H43: Software | I43: 2586.6 | J43: 2586.6 | K43: 0 | L43: 215.55 | M43: 215.55 | N43: 0 | O43: 0 | P43: eloyse.silveira@altoqi.com.br | Q43: B2B Construtora | R43: B2B Construtora | S43: 46048 | T43: 46048 | V43: 46413 | W43: 12 meses | X43: 12 | Y43: Assinatura | AA43: Pix | AB43: 1 | AC43: Comercial B2B - Construtoras | AD43: Plano Builder Professional | AE43: Builder | AF43: Professional | AG43: =IF(IFERROR(SEARCH("Recorrente",AA43),0)>0,"Recorrente",IF(AB43=1,"À Vista",IF(AB43<=3,"CC 3x",IF(AB43<=12,"CC 12x",IF(AB43>12,"Recorrente",""))))) -> À Vista | AH43: =IF(AND(SUMIF(E:E,E43,I:I)>=400000,Q43="B2G"),"n","")
A44: 2026 | B44: 1 | C44: 21692459068 | D44: Atenas | E44: 47622206131 | F44: 504206 | G44: 46565614233 | H44: Software | I44: 7747.2 | J44: 7747.2 | K44: 0 | L44: 645.6 | M44: 0 | N44: 35.47 | O44: 610.13 | P44: jaqueline.correa@altoqi.com.br | Q44: Saving | R44: Saving | S44: 45996 | T44: 46023 | U44: 46002 | V44: 46367 | W44: 12 meses | X44: 12 | Y44: Assinatura | Z44: Renovação | AA44: Cartão de crédito | AB44: 12 | AC44: CS - Saving | AD44: Plano Eberick Enterprise | AE44: Eberick | AF44: Enterprise | AG44: =IF(IFERROR(SEARCH("Recorrente",AA44),0)>0,"Recorrente",IF(AB44=1,"À Vista",IF(AB44<=3,"CC 3x",IF(AB44<=12,"CC 12x",IF(AB44>12,"Recorrente",""))))) -> CC 12x | AH44: =IF(AND(SUMIF(E:E,E44,I:I)>=400000,Q44="B2G"),"n","")
A45: 2026 | B45: 1 | C45: 19435586210 | D45: Assessoria e Consultoria Miotto | E45: 47648038175 | F45: 504309 | G45: 46927421719 | H45: Software | I45: 5752.68 | J45: 5752.68 | K45: 0 | L45: 479.39 | M45: 0 | N45: 12.05 | O45: 467.34 | P45: rosana@altoqi.com.br | Q45: Saving | R45: Saving | S45: 46004 | T45: 46023 | U45: 46004 | V45: 46369 | W45: 12 meses | X45: 12 | Y45: Assinatura | Z45: Renovação | AA45: Pix | AB45: 1 | AC45: CS - Saving | AD45: Plano InBIM Premium | AE45: InBIM | AF45: Premium | AG45: =IF(IFERROR(SEARCH("Recorrente",AA45),0)>0,"Recorrente",IF(AB45=1,"À Vista",IF(AB45<=3,"CC 3x",IF(AB45<=12,"CC 12x",IF(AB45>12,"Recorrente",""))))) -> À Vista | AH45: =IF(AND(SUMIF(E:E,E45,I:I)>=400000,Q45="B2G"),"n","")
A46: 2026 | B46: 1 | C46: 2087895 | D46: Fernando Oliveira | E46: 47666004314 | F46: 624886 | G46: 46761103535 | H46: Software | I46: 4452.6 | J46: 4452.6 | K46: 0 | L46: 371.05 | M46: 0 | N46: 31.9 | O46: 339.15 | P46: francyellen@altoqi.com.br | Q46: Saving | R46: Saving | S46: 46001 | T46: 46023 | U46: 46004 | V46: 46369 | W46: 12 meses | X46: 12 | Y46: Assinatura | Z46: Renovação com Expansão | AA46: Cartão de crédito - Recorrente | AB46: 12 | AC46: CS - Saving | AD46: Plano InBIM Professional | AE46: InBIM | AF46: Professional | AG46: =IF(IFERROR(SEARCH("Recorrente",AA46),0)>0,"Recorrente",IF(AB46=1,"À Vista",IF(AB46<=3,"CC 3x",IF(AB46<=12,"CC 12x",IF(AB46>12,"Recorrente",""))))) -> Recorrente | AH46: =IF(AND(SUMIF(E:E,E46,I:I)>=400000,Q46="B2G"),"n","")
A47: 2026 | B47: 1 | C47: 19485924166 | D47: Alfa Mk Construtora | E47: 47668184094 | F47: 624870 | G47: 47127695970 | H47: Software | I47: 2586.6 | J47: 2586.6 | K47: 0 | L47: 215.55 | M47: 0 | N47: 0.45 | O47: 215.1 | P47: jaqueline.correa@altoqi.com.br | Q47: Saving | R47: Saving | S47: 46007 | T47: 46023 | U47: 46003 | V47: 46368 | W47: 12 meses | X47: 12 | Y47: Assinatura | Z47: Renovação | AA47: Cartão de crédito | AB47: 12 | AC47: CS - Saving | AD47: Plano Eberick Professional | AE47: Eberick | AF47: Professional | AG47: =IF(IFERROR(SEARCH("Recorrente",AA47),0)>0,"Recorrente",IF(AB47=1,"À Vista",IF(AB47<=3,"CC 3x",IF(AB47<=12,"CC 12x",IF(AB47>12,"Recorrente",""))))) -> CC 12x | AH47: =IF(AND(SUMIF(E:E,E47,I:I)>=400000,Q47="B2G"),"n","")
A48: 2026 | B48: 1 | C48: 2247230 | D48: Kleber Melo Ferreira | E48: 47669558104 | F48: 504380 | G48: 45824610850 | H48: Software | I48: 5275.2 | J48: 5275.2 | K48: 0 | L48: 439.6 | M48: 0 | N48: 109.85 | O48: 329.755 | P48: silvia.estipe@altoqi.com.br | Q48: Saving | R48: Saving | S48: 45989 | T48: 46023 | U48: 46005 | V48: 46370 | W48: 12 meses | X48: 12 | Y48: Assinatura | Z48: Renovação | AA48: Cartão de crédito - Recorrente | AB48: 12 | AC48: CS - Saving | AD48: Plano InBIM Premium | AE48: InBIM | AF48: Premium | AG48: =IF(IFERROR(SEARCH("Recorrente",AA48),0)>0,"Recorrente",IF(AB48=1,"À Vista",IF(AB48<=3,"CC 3x",IF(AB48<=12,"CC 12x",IF(AB48>12,"Recorrente",""))))) -> Recorrente | AH48: =IF(AND(SUMIF(E:E,E48,I:I)>=400000,Q48="B2G"),"n","")
A49: 2026 | B49: 1 | C49: 2247230 | D49: Kleber Melo Ferreira | E49: 47669558104 | F49: 504380 | G49: 45824610851 | H49: Software | I49: 5275.2 | J49: 5275.2 | K49: 0 | L49: 439.6 | M49: 0 | N49: 109.85 | O49: 329.755 | P49: silvia.estipe@altoqi.com.br | Q49: Saving | R49: Saving | S49: 45989 | T49: 46023 | U49: 46005 | V49: 46370 | W49: 12 meses | X49: 12 | Y49: Assinatura | Z49: Renovação | AA49: Cartão de crédito - Recorrente | AB49: 12 | AC49: CS - Saving | AD49: Plano Visus Cost Management Premium | AE49: Visus Cost | AF49: Premium | AG49: =IF(IFERROR(SEARCH("Recorrente",AA49),0)>0,"Recorrente",IF(AB49=1,"À Vista",IF(AB49<=3,"CC 3x",IF(AB49<=12,"CC 12x",IF(AB49>12,"Recorrente",""))))) -> Recorrente | AH49: =IF(AND(SUMIF(E:E,E49,I:I)>=400000,Q49="B2G"),"n","")
A50: 2026 | B50: 1 | C50: 2076224 | D50: David Dantas de Lima | E50: 47675789409 | F50: 523118 | G50: 45831558460 | H50: Software | I50: 3914.88 | J50: 3914.88 | K50: 0 | L50: 326.24 | M50: 0 | N50: 10.16 | O50: 316.09 | P50: jaqueline.correa@altoqi.com.br | Q50: Saving | R50: Saving | S50: 45989 | T50: 46023 | U50: 46000 | V50: 46365 | W50: 12 meses | X50: 12 | Y50: Assinatura | Z50: Renovação com Expansão | AA50: Pix | AB50: 1 | AC50: CS - Saving | AD50: Plano InBIM Professional | AE50: InBIM | AF50: Professional | AG50: =IF(IFERROR(SEARCH("Recorrente",AA50),0)>0,"Recorrente",IF(AB50=1,"À Vista",IF(AB50<=3,"CC 3x",IF(AB50<=12,"CC 12x",IF(AB50>12,"Recorrente",""))))) -> À Vista | AH50: =IF(AND(SUMIF(E:E,E50,I:I)>=400000,Q50="B2G"),"n","")
A51: 2026 | B51: 1 | C51: 117958536056 | D51: Mayara Galdino Dias | E51: 47678171505 | F51: 605634 | G51: 46884876908 | H51: Software | I51: 4660.68 | J51: 4660.68 | K51: 0 | L51: 388.39 | M51: 0 | N51: 1.6 | O51: 386.8 | P51: francyellen@altoqi.com.br | Q51: Saving | R51: Saving | S51: 46003 | T51: 46023 | U51: 46004 | V51: 46369 | W51: 12 meses | X51: 12 | Y51: Assinatura | Z51: Renovação | AA51: Pix | AB51: 1 | AC51: CS - Saving | AD51: Plano Eberick Premium | AE51: Eberick | AF51: Premium | AG51: =IF(IFERROR(SEARCH("Recorrente",AA51),0)>0,"Recorrente",IF(AB51=1,"À Vista",IF(AB51<=3,"CC 3x",IF(AB51<=12,"CC 12x",IF(AB51>12,"Recorrente",""))))) -> À Vista | AH51: =IF(AND(SUMIF(E:E,E51,I:I)>=400000,Q51="B2G"),"n","")
A52: 2026 | B52: 1 | C52: 129005008134 | D52: Naiara Cristina de Souza Carvalho | E52: 47680922476 | F52: 326920 | G52: 44721743490 | H52: Software | I52: 16750.08 | J52: 8375.04 | K52: 8375.04 | L52: 697.92 | M52: 0 | N52: 326.82 | O52: 371.1 | P52: rubia.estipe@altoqi.com.br | Q52: Saving | R52: Saving | S52: 46003 | T52: 46023 | U52: 46006 | V52: 46736 | W52: 24 meses | X52: 24 | Y52: Assinatura | Z52: Renovação com Expansão | AA52: Cartão de crédito - Recorrente | AB52: 24 | AC52: CS - Saving | AD52: Plano InBIM Enterprise | AE52: InBIM | AF52: Enterprise | AG52: =IF(IFERROR(SEARCH("Recorrente",AA52),0)>0,"Recorrente",IF(AB52=1,"À Vista",IF(AB52<=3,"CC 3x",IF(AB52<=12,"CC 12x",IF(AB52>12,"Recorrente",""))))) -> Recorrente | AH52: =IF(AND(SUMIF(E:E,E52,I:I)>=400000,Q52="B2G"),"n","")
A53: 2026 | B53: 1 | C53: 195024457615 | D53: Marina Roque | E53: 47682679108 | F53: 327644 | G53: 46529985849 | H53: Software | I53: 4315.44 | J53: 4315.44 | K53: 0 | L53: 359.62 | M53: 0 | N53: 67.78 | O53: 291.85 | P53: silvia.estipe@altoqi.com.br | Q53: Saving | R53: Saving | S53: 45995 | T53: 46023 | U53: 46002 | V53: 46367 | W53: 12 meses | X53: 12 | Y53: Assinatura | Z53: Renovação | AA53: Cartão de crédito - Recorrente | AB53: 12 | AC53: CS - Saving | AD53: Plano Eberick Premium | AE53: Eberick | AF53: Premium | AG53: =IF(IFERROR(SEARCH("Recorrente",AA53),0)>0,"Recorrente",IF(AB53=1,"À Vista",IF(AB53<=3,"CC 3x",IF(AB53<=12,"CC 12x",IF(AB53>12,"Recorrente",""))))) -> Recorrente | AH53: =IF(AND(SUMIF(E:E,E53,I:I)>=400000,Q53="B2G"),"n","")
A54: 2026 | B54: 1 | C54: 2095325 | D54: Gabriel Pires | E54: 47744281985 | F54: 605553 | G54: 44337662602 | H54: Software | I54: 9953.76 | J54: 4976.88 | K54: 4976.88 | L54: 414.74 | M54: 0 | N54: 18.49 | O54: 396.25 | P54: marcela@altoqi.com.br | Q54: Saving | R54: Saving | S54: 45999 | T54: 46023 | U54: 46004 | V54: 46734 | W54: 24 meses | X54: 24 | Y54: Assinatura | Z54: Renovação com Expansão | AA54: Cartão de crédito - Recorrente | AB54: 24 | AC54: CS - Saving | AD54: Plano Builder Enterprise | AE54: Builder | AF54: Enterprise | AG54: =IF(IFERROR(SEARCH("Recorrente",AA54),0)>0,"Recorrente",IF(AB54=1,"À Vista",IF(AB54<=3,"CC 3x",IF(AB54<=12,"CC 12x",IF(AB54>12,"Recorrente",""))))) -> Recorrente | AH54: =IF(AND(SUMIF(E:E,E54,I:I)>=400000,Q54="B2G"),"n","")
A55: 2026 | B55: 1 | C55: 19435653671 | D55: Padilha & Ribeiro - Engenharia e Projetos Associados | E55: 47757949775 | F55: 624746 | G55: 46700562560 | H55: Software | I55: 2529.12 | J55: 2529.12 | K55: 0 | L55: 210.76 | M55: 0 | N55: 0.44 | O55: 210.32 | P55: jaqueline.correa@altoqi.com.br | Q55: Saving | R55: Saving | S55: 46000 | T55: 46023 | U55: 46001 | V55: 46366 | W55: 12 meses | X55: 12 | Y55: Assinatura | Z55: Renovação | AA55: Cartão de crédito | AB55: 12 | AC55: CS - Saving | AD55: Plano Eberick Professional | AE55: Eberick | AF55: Professional | AG55: =IF(IFERROR(SEARCH("Recorrente",AA55),0)>0,"Recorrente",IF(AB55=1,"À Vista",IF(AB55<=3,"CC 3x",IF(AB55<=12,"CC 12x",IF(AB55>12,"Recorrente",""))))) -> CC 12x | AH55: =IF(AND(SUMIF(E:E,E55,I:I)>=400000,Q55="B2G"),"n","")
... A77: 2026 | B77: 1 | C77: 119295005269 | D77: Thiago SDSA | E77: 48848678066 | F77: 624828 | G77: 47029948294 | H77: Software | I77: 5612.4 | J77: 5612.4 | K77: 0 | L77: 467.7 | M77: 467.7 | N77: 0 | O77: 0 | P77: cintia@altoqi.com.br | Q77: Saving | R77: Saving | S77: 46003 | T77: 46023 | U77: 46002 | V77: 46368 | W77: 12 meses | X77: 12 | Y77: Assinatura | Z77: Renovação | AA77: Cartão de crédito | AB77: 12 | AC77: CS - Saving | AD77: Plano InBIM Premium | AE77: InBIM | AF77: Premium | AG77: =IF(IFERROR(SEARCH("Recorrente",AA77),0)>0,"Recorrente",IF(AB77=1,"À Vista",IF(AB77<=3,"CC 3x",IF(AB77<=12,"CC 12x",IF(AB77>12,"Recorrente",""))))) -> CC 12x | AH77: =IF(AND(SUMIF(E:E,E77,I:I)>=400000,Q77="B2G"),"n","")
A78: 2026 | B78: 1 | C78: 30934616757 | D78: ASSOCIACAO DOS MUNICIPIOS DA REGIAO SERRANA | E78: 48886938383 | F78: 635690 | G78: 49714856457 | H78: Software | I78: 4644 | J78: 4644 | K78: 0 | L78: 387 | M78: 387 | N78: 0 | O78: 0 | P78: fernanda.barbosa@altoqi.com.br | Q78: B2G | R78: B2G | S78: 46044 | T78: 46044 | V78: 46409 | W78: 12 meses | X78: 12 | Y78: Assinatura | AA78: Transferência bancária | AB78: 1 | AC78: Comercial B2G | AD78: Plano AltoQi Builder Premium Governo | AE78: Builder | AF78: Premium | AG78: =IF(IFERROR(SEARCH("Recorrente",AA78),0)>0,"Recorrente",IF(AB78=1,"À Vista",IF(AB78<=3,"CC 3x",IF(AB78<=12,"CC 12x",IF(AB78>12,"Recorrente",""))))) -> À Vista | AH78: =IF(AND(SUMIF(E:E,E78,I:I)>=400000,Q78="B2G"),"n","")
A79: 2026 | B79: 1 | C79: 133327953510 | D79: marcelo matos | E79: 48941137811 | F79: 602833 | G79: 48825764902 | H79: Software | I79: 7553.4 | J79: 7553.4 | K79: 0 | L79: 629.45 | M79: 0 | N79: 12.9 | O79: 616.55 | P79: cintia@altoqi.com.br | Q79: Saving | R79: Saving | S79: 46034 | T79: 46034 | U79: 46004 | V79: 46399 | W79: 12 meses | X79: 13 | Y79: Assinatura | Z79: Renovação | AA79: Cartão de crédito - Recorrente | AB79: 12 | AC79: CS - Saving | AD79: Plano InBIM Premium | AE79: InBIM | AF79: Premium | AG79: =IF(IFERROR(SEARCH("Recorrente",AA79),0)>0,"Recorrente",IF(AB79=1,"À Vista",IF(AB79<=3,"CC 3x",IF(AB79<=12,"CC 12x",IF(AB79>12,"Recorrente",""))))) -> Recorrente | AH79: =IF(AND(SUMIF(E:E,E79,I:I)>=400000,Q79="B2G"),"n","")
A80: 2026 | B80: 1 | C80: 121449636265 | D80: Cintia Sganzerla | E80: 48977924635 | F80: 522751 | G80: 46760338222 | H80: Software | I80: 2457.24 | J80: 2457.24 | K80: 0 | L80: 204.77 | M80: 0 | N80: 0 | O80: 204.7725 | P80: francyellen@altoqi.com.br | Q80: Saving | R80: Saving | S80: 46001 | T80: 46023 | U80: 46019 | V80: 46384 | W80: 12 meses | X80: 12 | Y80: Assinatura | Z80: Renovação | AA80: Cartão de crédito - Recorrente | AB80: 12 | AC80: CS - Saving | AD80: Plano Builder Professional | AE80: Builder | AF80: Professional | AG80: =IF(IFERROR(SEARCH("Recorrente",AA80),0)>0,"Recorrente",IF(AB80=1,"À Vista",IF(AB80<=3,"CC 3x",IF(AB80<=12,"CC 12x",IF(AB80>12,"Recorrente",""))))) -> Recorrente | AH80: =IF(AND(SUMIF(E:E,E80,I:I)>=400000,Q80="B2G"),"n","")
A81: 2026 | B81: 1 | C81: 121449636265 | D81: Cintia Sganzerla | E81: 48977924635 | F81: 522751 | G81: 46760338223 | H81: Software | I81: 2457.24 | J81: 2457.24 | K81: 0 | L81: 204.77 | M81: 0 | N81: 0 | O81: 204.7725 | P81: francyellen@altoqi.com.br | Q81: Saving | R81: Saving | S81: 46001 | T81: 46023 | U81: 46019 | V81: 46384 | W81: 12 meses | X81: 12 | Y81: Assinatura | Z81: Renovação | AA81: Cartão de crédito - Recorrente | AB81: 12 | AC81: CS - Saving | AD81: Plano Eberick Professional | AE81: Eberick | AF81: Professional | AG81: =IF(IFERROR(SEARCH("Recorrente",AA81),0)>0,"Recorrente",IF(AB81=1,"À Vista",IF(AB81<=3,"CC 3x",IF(AB81<=12,"CC 12x",IF(AB81>12,"Recorrente",""))))) -> Recorrente | AH81: =IF(AND(SUMIF(E:E,E81,I:I)>=400000,Q81="B2G"),"n","")
A82: 2026 | B82: 1 | C82: 136154984229 | D82: Eduardo Deitos | E82: 49040847389 | F82: 605671 | G82: 46345970180 | H82: Software | I82: 3948 | J82: 3948 | K82: 0 | L82: 329 | M82: 0 | N82: 20.26 | O82: 308.74 | P82: jaqueline.correa@altoqi.com.br | Q82: Saving | R82: Saving | S82: 45994 | T82: 46023 | U82: 46010 | V82: 46375 | W82: 12 meses | X82: 12 | Y82: Assinatura | Z82: Renovação | AA82: Cartão de crédito | AB82: 12 | AC82: CS - Saving | AD82: Plano Builder Elétrica Enterprise | AE82: Builder | AF82: Enterprise | AG82: =IF(IFERROR(SEARCH("Recorrente",AA82),0)>0,"Recorrente",IF(AB82=1,"À Vista",IF(AB82<=3,"CC 3x",IF(AB82<=12,"CC 12x",IF(AB82>12,"Recorrente",""))))) -> CC 12x | AH82: =IF(AND(SUMIF(E:E,E82,I:I)>=400000,Q82="B2G"),"n","")
A83: 2026 | B83: 1 | C83: 19435566940 | D83: OXFORD ENGENHARIA | E83: 49040907923 | F83: 523604 | G83: 47279014577 | H83: Software | I83: 3707.28 | J83: 3707.28 | K83: 0 | L83: 308.94 | M83: 0 | N83: 0 | O83: 308.94185 | P83: francyellen@altoqi.com.br | Q83: Saving | R83: Saving | S83: 46010 | T83: 46023 | U83: 46007 | V83: 46375 | W83: 12 meses | X83: 12 | Y83: Assinatura | Z83: Renovação | AA83: Pix | AB83: 1 | AC83: CS - Saving | AD83: Plano Eberick Premium | AE83: Eberick | AF83: Premium | AG83: =IF(IFERROR(SEARCH("Recorrente",AA83),0)>0,"Recorrente",IF(AB83=1,"À Vista",IF(AB83<=3,"CC 3x",IF(AB83<=12,"CC 12x",IF(AB83>12,"Recorrente",""))))) -> À Vista | AH83: =IF(AND(SUMIF(E:E,E83,I:I)>=400000,Q83="B2G"),"n","")
A84: 2026 | B84: 1 | C84: 19435617053 | D84: SEHT ENGENHARIA | E84: 49090943072 | F84: 326742 | G84: 44720891285 | H84: Software | I84: 4527.24 | J84: 4527.24 | K84: 0 | L84: 377.27 | M84: 0 | N84: 0 | O84: 377.26875 | P84: rubia.estipe@altoqi.com.br | Q84: Saving | R84: Saving | S84: 45978 | T84: 46023 | U84: 46006 | V84: 46371 | W84: 12 meses | X84: 12 | Y84: Assinatura | Z84: Renovação | AA84: Cartão de crédito - Recorrente | AB84: 12 | AC84: CS - Saving | AD84: Plano Builder Enterprise | AE84: Builder | AF84: Enterprise | AG84: =IF(IFERROR(SEARCH("Recorrente",AA84),0)>0,"Recorrente",IF(AB84=1,"À Vista",IF(AB84<=3,"CC 3x",IF(AB84<=12,"CC 12x",IF(AB84>12,"Recorrente",""))))) -> Recorrente | AH84: =IF(AND(SUMIF(E:E,E84,I:I)>=400000,Q84="B2G"),"n","")
A85: 2026 | B85: 1 | C85: 123423171206 | D85: Guylherme Rezende Rosário | E85: 49135849291 | F85: 301960 | G85: 46529928882 | H85: Software | I85: 2356.68 | J85: 2356.68 | K85: 0 | L85: 196.39 | M85: 0 | N85: 11.39 | O85: 185 | P85: rubia.estipe@altoqi.com.br | Q85: Saving | R85: Saving | S85: 45995 | T85: 46023 | U85: 46017 | V85: 46382 | W85: 12 meses | X85: 12 | Y85: Assinatura | Z85: Renovação com Expansão | AA85: Cartão de crédito | AB85: 12 | AC85: CS - Saving | AD85: Plano Builder Professional | AE85: Builder | AF85: Professional | AG85: =IF(IFERROR(SEARCH("Recorrente",AA85),0)>0,"Recorrente",IF(AB85=1,"À Vista",IF(AB85<=3,"CC 3x",IF(AB85<=12,"CC 12x",IF(AB85>12,"Recorrente",""))))) -> CC 12x | AH85: =IF(AND(SUMIF(E:E,E85,I:I)>=400000,Q85="B2G"),"n","")
A86: 2026 | B86: 1 | C86: 32670691707 | D86: Município de Divinopolis | E86: 49141755828 | F86: 635749 | G86: 49949978893 | H86: Software | I86: 4644 | J86: 4644 | K86: 0 | L86: 387 | M86: 387 | N86: 0 | O86: 0 | P86: tabata.couto@altoqi.com.br | Q86: B2G | R86: B2G | S86: 46049 | T86: 46049 | V86: 46414 | W86: 12 meses | X86: 12 | Y86: Assinatura | AA86: Transferência bancária | AB86: 1 | AC86: Comercial B2G | AD86: Plano AltoQi Builder Premium Governo | AE86: Builder | AF86: Premium | AG86: =IF(IFERROR(SEARCH("Recorrente",AA86),0)>0,"Recorrente",IF(AB86=1,"À Vista",IF(AB86<=3,"CC 3x",IF(AB86<=12,"CC 12x",IF(AB86>12,"Recorrente",""))))) -> À Vista | AH86: =IF(AND(SUMIF(E:E,E86,I:I)>=400000,Q86="B2G"),"n","")
A87: 2026 | B87: 1 | C87: 91623146910 | D87: Leonardo Bianconi Welchek | E87: 49206469521 | F87: 503490 | G87: 44435182774 | H87: Software | I87: 4315.44 | J87: 4315.44 | K87: 0 | L87: 359.62 | M87: 0 | N87: 56.55 | O87: 303.08 | P87: thiago.oliveira@altoqi.com.br | Q87: Renovação Automática | R87: Renovação Automática | S87: 46034 | T87: 46034 | U87: 46023 | V87: 46388 | W87: 12 meses | X87: 12 | Y87: Assinatura | Z87: Renovação | AA87: Cartão de crédito | AB87: 5 | AC87: Renovação Automática | AD87: Plano Eberick Premium | AE87: Eberick | AF87: Premium | AG87: =IF(IFERROR(SEARCH("Recorrente",AA87),0)>0,"Recorrente",IF(AB87=1,"À Vista",IF(AB87<=3,"CC 3x",IF(AB87<=12,"CC 12x",IF(AB87>12,"Recorrente",""))))) -> CC 12x | AH87: =IF(AND(SUMIF(E:E,E87,I:I)>=400000,Q87="B2G"),"n","")
A88: 2026 | B88: 1 | C88: 2131194 | D88: Joao Henrique Zangaro Dos Santos | E88: 49210120197 | F88: 504696 | G88: 44419552438 | H88: Software | I88: 5178.6 | J88: 5178.6 | K88: 0 | L88: 431.55 | M88: 0 | N88: 117.29 | O88: 314.26 | P88: thiago.oliveira@altoqi.com.br | Q88: Renovação Automática | R88: Renovação Automática | S88: 46023 | T88: 46023 | U88: 46023 | V88: 46388 | W88: 12 meses | X88: 12 | Y88: Assinatura | Z88: Renovação | AA88: Cartão de crédito - Recorrente | AB88: 12 | AC88: Renovação Automática | AD88: Plano Eberick Premium | AE88: Eberick | AF88: Premium | AG88: =IF(IFERROR(SEARCH("Recorrente",AA88),0)>0,"Recorrente",IF(AB88=1,"À Vista",IF(AB88<=3,"CC 3x",IF(AB88<=12,"CC 12x",IF(AB88>12,"Recorrente",""))))) -> Recorrente | AH88: =IF(AND(SUMIF(E:E,E88,I:I)>=400000,Q88="B2G"),"n","")
A89: 2026 | B89: 1 | C89: 19485990822 | D89: GE PROJETOS & CONSTRUCAO LTDA | E89: 49218873256 | F89: 635798 | G89: 50350991438 | H89: Software | I89: 3120.12 | J89: 3120.11 | K89: 0.01 | L89: 260.01 | M89: 0 | N89: 260.01 | O89: 0 | P89: aline.pureza@altoqi.com.br | Q89: Farmer | R89: Farmer | S89: 46051 | T89: 46051 | V89: 46416 | W89: 12 meses | X89: 12 | Y89: Assinatura | AA89: Cartão de crédito | AB89: 12 | AC89: Farmer - Deméter | AD89: Plano Visus Cost Management Premium | AE89: Visus Cost | AF89: Premium | AG89: =IF(IFERROR(SEARCH("Recorrente",AA89),0)>0,"Recorrente",IF(AB89=1,"À Vista",IF(AB89<=3,"CC 3x",IF(AB89<=12,"CC 12x",IF(AB89>12,"Recorrente",""))))) -> CC 12x | AH89: =IF(AND(SUMIF(E:E,E89,I:I)>=400000,Q89="B2G"),"n","")
A90: 2026 | B90: 1 | C90: 2096449 | D90: Lucca Caselli | E90: 49242220118 | F90: 605457 | G90: 47224568410 | H90: Software | I90: 8937.24 | J90: 8937.24 | K90: 0 | L90: 744.77 | M90: 0 | N90: 53.95 | O90: 690.82 | P90: jaqueline.correa@altoqi.com.br | Q90: Saving | R90: Saving | S90: 46010 | T90: 46023 | U90: 46011 | V90: 46376 | W90: 12 meses | X90: 12 | Y90: Assinatura | Z90: Renovação | AA90: Cartão de crédito - Recorrente | AB90: 12 | AC90: CS - Saving | AD90: Plano InBIM Enterprise | AE90: InBIM | AF90: Enterprise | AG90: =IF(IFERROR(SEARCH("Recorrente",AA90),0)>0,"Recorrente",IF(AB90=1,"À Vista",IF(AB90<=3,"CC 3x",IF(AB90<=12,"CC 12x",IF(AB90>12,"Recorrente",""))))) -> Recorrente | AH90: =IF(AND(SUMIF(E:E,E90,I:I)>=400000,Q90="B2G"),"n","")
A91: 2026 | B91: 1 | C91: 124900305416 | D91: Leandro Brenes Burque | E91: 49245441880 | F91: 327927 | G91: 47441443891 | H91: Software | I91: 4130.16 | J91: 4130.16 | K91: 0 | L91: 344.18 | M91: 0 | N91: 50.88 | O91: 293.3 | P91: rosana@altoqi.com.br | Q91: Saving | R91: Saving | S91: 46014 | T91: 46023 | U91: 46016 | V91: 46381 | W91: 12 meses | X91: 12 | Y91: Assinatura | Z91: Renovação | AA91: Cartão de crédito | AB91: 12 | AC91: CS - Saving | AD91: Plano Builder Elétrica Infinity | AE91: Builder | AF91: Infinity | AG91: =IF(IFERROR(SEARCH("Recorrente",AA91),0)>0,"Recorrente",IF(AB91=1,"À Vista",IF(AB91<=3,"CC 3x",IF(AB91<=12,"CC 12x",IF(AB91>12,"Recorrente",""))))) -> CC 12x | AH91: =IF(AND(SUMIF(E:E,E91,I:I)>=400000,Q91="B2G"),"n","")
A92: 2026 | B92: 1 | C92: 19435513456 | D92: PROJETARY | E92: 49300130605 | F92: 302281 | G92: 46066383414 | H92: Software | I92: 7488.36 | J92: 7488.36 | K92: 0 | L92: 624.03 | M92: 0 | N92: 124.2 | O92: 499.835 | P92: jaqueline.correa@altoqi.com.br | Q92: Saving | R92: Saving | S92: 45992 | T92: 46023 | U92: 46007 | V92: 46372 | W92: 12 meses | X92: 12 | Y92: Assinatura | Z92: Renovação | AA92: Cartão de crédito | AB92: 12 | AC92: CS - Saving | AD92: Plano Builder Infinity | AE92: Builder | AF92: Infinity | AG92: =IF(IFERROR(SEARCH("Recorrente",AA92),0)>0,"Recorrente",IF(AB92=1,"À Vista",IF(AB92<=3,"CC 3x",IF(AB92<=12,"CC 12x",IF(AB92>12,"Recorrente",""))))) -> CC 12x | AH92: =IF(AND(SUMIF(E:E,E92,I:I)>=400000,Q92="B2G"),"n","")
A93: 2026 | B93: 1 | C93: 19435513456 | D93: PROJETARY | E93: 49300130605 | F93: 302281 | G93: 46066383415 | H93: Software | I93: 7488.36 | J93: 7488.36 | K93: 0 | L93: 624.03 | M93: 0 | N93: 124.2 | O93: 499.835 | P93: jaqueline.correa@altoqi.com.br | Q93: Saving | R93: Saving | S93: 45992 | T93: 46023 | U93: 46007 | V93: 46372 | W93: 12 meses | X93: 12 | Y93: Assinatura | Z93: Renovação | AA93: Cartão de crédito | AB93: 12 | AC93: CS - Saving | AD93: Plano Eberick Infinity | AE93: Eberick | AF93: Infinity | AG93: =IF(IFERROR(SEARCH("Recorrente",AA93),0)>0,"Recorrente",IF(AB93=1,"À Vista",IF(AB93<=3,"CC 3x",IF(AB93<=12,"CC 12x",IF(AB93>12,"Recorrente",""))))) -> CC 12x | AH93: =IF(AND(SUMIF(E:E,E93,I:I)>=400000,Q93="B2G"),"n","")
A94: 2026 | B94: 1 | C94: 179742877269 | D94: André Rodrigo Neuhauser | E94: 49420767314 | F94: 503652 | G94: 45835228596 | H94: Software | I94: 3883.92 | J94: 3883.92 | K94: 0 | L94: 323.66 | M94: 0 | N94: 54.25 | O94: 269.41 | P94: francyellen@altoqi.com.br | Q94: Saving | R94: Saving | S94: 45988 | T94: 46023 | U94: 45992 | V94: 46357 | W94: 12 meses | X94: 12 | Y94: Assinatura | Z94: Renovação | AA94: Pix | AB94: 1 | AC94: CS - Saving | AD94: Plano Eberick Premium | AE94: Eberick | AF94: Premium | AG94: =IF(IFERROR(SEARCH("Recorrente",AA94),0)>0,"Recorrente",IF(AB94=1,"À Vista",IF(AB94<=3,"CC 3x",IF(AB94<=12,"CC 12x",IF(AB94>12,"Recorrente",""))))) -> À Vista | AH94: =IF(AND(SUMIF(E:E,E94,I:I)>=400000,Q94="B2G"),"n","")
A95: 2026 | B95: 1 | C95: 19435672491 | D95: Servcon-servicos de Construcoes | E95: 49470339849 | F95: 606799 | G95: 44748072560 | H95: Software | I95: 4962.6 | J95: 0 | K95: 4962.6 | L95: 0 | M95: 0 | N95: 0 | O95: 0 | P95: beatriz@altoqi.com.br | Q95: Renovação Automática | R95: Renovação Automática | S95: 46024 | T95: 46024 | U95: 46024 | V95: 46389 | W95: 12 meses | X95: 12 | Y95: Assinatura | Z95: Renovação | AA95: Cartão de crédito - Recorrente | AB95: 12 | AC95: Renovação Automática | AD95: Plano InBIM Professional | AE95: InBIM | AF95: Professional | AG95: =IF(IFERROR(SEARCH("Recorrente",AA95),0)>0,"Recorrente",IF(AB95=1,"À Vista",IF(AB95<=3,"CC 3x",IF(AB95<=12,"CC 12x",IF(AB95>12,"Recorrente",""))))) -> Recorrente | AH95: =IF(AND(SUMIF(E:E,E95,I:I)>=400000,Q95="B2G"),"n","")
A96: 2026 | B96: 1 | C96: 2085460 | D96: Robert Alex Nogueira da Silva | E96: 49471270441 | F96: 328111 | G96: 44804494186 | H96: Software | I96: 7015.44 | J96: 7015.44 | K96: 0 | L96: 584.62 | M96: 0 | N96: 143.38 | O96: 441.25 | P96: thiago.oliveira@altoqi.com.br | Q96: Renovação Automática | R96: Renovação Automática | S96: 46024 | T96: 46024 | U96: 46024 | V96: 46389 | W96: 12 meses | X96: 12 | Y96: Assinatura | Z96: Renovação | AA96: Cartão de crédito | AB96: 12 | AC96: Renovação Automática | AD96: Plano InBIM Premium | AE96: InBIM | AF96: Premium | AG96: =IF(IFERROR(SEARCH("Recorrente",AA96),0)>0,"Recorrente",IF(AB96=1,"À Vista",IF(AB96<=3,"CC 3x",IF(AB96<=12,"CC 12x",IF(AB96>12,"Recorrente",""))))) -> CC 12x | AH96: =IF(AND(SUMIF(E:E,E96,I:I)>=400000,Q96="B2G"),"n","")
A97: 2026 | B97: 1 | C97: 139487682306 | D97: Cicero Nataniel Lima De Pinho | E97: 49473514881 | F97: 625250 | G97: 44739285516 | H97: Software | I97: 4962.6 | J97: 4962.6 | K97: 0 | L97: 413.55 | M97: 0 | N97: 48.47 | O97: 365.08 | P97: thiago.oliveira@altoqi.com.br | Q97: Renovação Automática | R97: Renovação Automática | S97: 46025 | T97: 46025 | U97: 46025 | V97: 46390 | W97: 12 meses | X97: 12 | Y97: Assinatura | Z97: Renovação | AA97: Cartão de crédito - Recorrente | AB97: 12 | AC97: Renovação Automática | AD97: Plano InBIM Professional | AE97: InBIM | AF97: Professional | AG97: =IF(IFERROR(SEARCH("Recorrente",AA97),0)>0,"Recorrente",IF(AB97=1,"À Vista",IF(AB97<=3,"CC 3x",IF(AB97<=12,"CC 12x",IF(AB97>12,"Recorrente",""))))) -> Recorrente | AH97: =IF(AND(SUMIF(E:E,E97,I:I)>=400000,Q97="B2G"),"n","")
A98: 2026 | B98: 1 | C98: 2139371 | D98: Thaisa Trento | E98: 49474676482 | F98: 625232 | G98: 44811378517 | H98: Software | I98: 2874 | J98: 2874 | K98: 0 | L98: 239.5 | M98: 0 | N98: 36.35 | O98: 203.15 | P98: thiago.oliveira@altoqi.com.br | Q98: Renovação Automática | R98: Renovação Automática | S98: 46024 | T98: 46024 | U98: 46024 | V98: 46389 | W98: 12 meses | X98: 12 | Y98: Assinatura | Z98: Renovação | AA98: Cartão de crédito - Recorrente | AB98: 12 | AC98: Renovação Automática | AD98: Plano Eberick Professional | AE98: Eberick | AF98: Professional | AG98: =IF(IFERROR(SEARCH("Recorrente",AA98),0)>0,"Recorrente",IF(AB98=1,"À Vista",IF(AB98<=3,"CC 3x",IF(AB98<=12,"CC 12x",IF(AB98>12,"Recorrente",""))))) -> Recorrente | AH98: =IF(AND(SUMIF(E:E,E98,I:I)>=400000,Q98="B2G"),"n","")
A99: 2026 | B99: 1 | C99: 2078240 | D99: Luis Piccoli | E99: 49481946676 | F99: 625231 | G99: 44753333607 | H99: Software | I99: 5754 | J99: 5754 | K99: 0 | L99: 479.5 | M99: 0 | N99: 30.5 | O99: 449 | P99: thiago.oliveira@altoqi.com.br | Q99: Renovação Automática | R99: Renovação Automática | S99: 46024 | T99: 46024 | U99: 46024 | V99: 46389 | W99: 12 meses | X99: 12 | Y99: Assinatura | Z99: Renovação | AA99: Cartão de crédito - Recorrente | AB99: 12 | AC99: Renovação Automática | AD99: Plano Eberick Premium | AE99: Eberick | AF99: Premium | AG99: =IF(IFERROR(SEARCH("Recorrente",AA99),0)>0,"Recorrente",IF(AB99=1,"À Vista",IF(AB99<=3,"CC 3x",IF(AB99<=12,"CC 12x",IF(AB99>12,"Recorrente",""))))) -> Recorrente | AH99: =IF(AND(SUMIF(E:E,E99,I:I)>=400000,Q99="B2G"),"n","")
A100: 2026 | B100: 1 | C100: 179716889471 | D100: Luana Soares Nogueira | E100: 49541964809 | F100: 274113 | G100: 45846618224 | H100: Software | I100: 4190.64 | J100: 4190.64 | K100: 0 | L100: 349.22 | M100: 0 | N100: 94.22 | O100: 255 | P100: rosana@altoqi.com.br | Q100: Saving | R100: Saving | S100: 45990 | T100: 46023 | U100: 46021 | V100: 46386 | W100: 12 meses | X100: 12 | Y100: Assinatura | Z100: Renovação com Expansão | AA100: Cartão de crédito - Recorrente | AB100: 12 | AC100: CS - Saving | AD100: Plano InBIM Professional | AE100: InBIM | AF100: Professional | AG100: =IF(IFERROR(SEARCH("Recorrente",AA100),0)>0,"Recorrente",IF(AB100=1,"À Vista",IF(AB100<=3,"CC 3x",IF(AB100<=12,"CC 12x",IF(AB100>12,"Recorrente",""))))) -> Recorrente | AH100: =IF(AND(SUMIF(E:E,E100,I:I)>=400000,Q100="B2G"),"n","")
A101: 2026 | B101: 1 | C101: 19485978015 | D101: TERRES DOS SANTOS ARQUITETURA E ENGENHARIA LTDA | E101: 49595233908 | F101: 624976 | G101: 44916512907 | H101: Software | I101: 14043.24 | J101: 4681.08 | K101: 9362.16 | L101: 390.09 | M101: 0 | N101: 227.52 | O101: 162.57 | P101: marcela@altoqi.com.br | Q101: Saving | R101: Saving | S101: 45980 | T101: 46023 | U101: 46008 | V101: 47104 | W101: 36 meses | X101: 36 | Y101: Assinatura | Z101: Renovação | AA101: Cartão de crédito - Recorrente | AB101: 36 | AC101: CS - Saving | AD101: Plano Builder Elétrica Infinity | AE101: Builder | AF101: Infinity | AG101: =IF(IFERROR(SEARCH("Recorrente",AA101),0)>0,"Recorrente",IF(AB101=1,"À Vista",IF(AB101<=3,"CC 3x",IF(AB101<=12,"CC 12x",IF(AB101>12,"Recorrente",""))))) -> Recorrente | AH101: =IF(AND(SUMIF(E:E,E101,I:I)>=400000,Q101="B2G"),"n","")
... A121: 2026 | B121: 1 | C121: 2107686 | D121: Valson Do Carmo Moraes Junior | E121: 50095794963 | F121: 303317 | G121: 45382288705 | H121: Software | I121: 8418.6 | J121: 8418.6 | K121: 0 | L121: 701.55 | M121: 0 | N121: 247.25 | O121: 454.3 | P121: thiago.oliveira@altoqi.com.br | Q121: Renovação Automática | R121: Renovação Automática | S121: 46029 | T121: 46029 | U121: 46029 | V121: 46394 | W121: 12 meses | X121: 12 | Y121: Assinatura | Z121: Renovação | AA121: Cartão de crédito - Recorrente | AB121: 12 | AC121: Renovação Automática | AD121: Plano InBIM Premium | AE121: InBIM | AF121: Premium | AG121: =IF(IFERROR(SEARCH("Recorrente",AA121),0)>0,"Recorrente",IF(AB121=1,"À Vista",IF(AB121<=3,"CC 3x",IF(AB121<=12,"CC 12x",IF(AB121>12,"Recorrente",""))))) -> Recorrente | AH121: =IF(AND(SUMIF(E:E,E121,I:I)>=400000,Q121="B2G"),"n","")
A122: 2026 | B122: 1 | C122: 45761739299 | D122: NORDESTE LOGISTICA S.A | E122: 50097766779 | F122: 635497 | G122: 48464651276 | H122: Software | I122: 5034 | J122: 5034 | K122: 0 | L122: 419.5 | M122: 419.5 | N122: 0 | O122: 0 | P122: henrique.silva@altoqi.com.br | Q122: B2B Construtora | R122: B2B Construtora | S122: 46028 | T122: 46028 | V122: 46393 | W122: 12 meses | X122: 12 | Y122: Assinatura | AA122: Boleto | AB122: 1 | AC122: Comercial B2B - Construtoras | AD122: Plano Builder Premium | AE122: Builder | AF122: Premium | AG122: =IF(IFERROR(SEARCH("Recorrente",AA122),0)>0,"Recorrente",IF(AB122=1,"À Vista",IF(AB122<=3,"CC 3x",IF(AB122<=12,"CC 12x",IF(AB122>12,"Recorrente",""))))) -> À Vista | AH122: =IF(AND(SUMIF(E:E,E122,I:I)>=400000,Q122="B2G"),"n","")
A123: 2026 | B123: 1 | C123: 2088656 | D123: Juliano Roberto Pierezan | E123: 50100814472 | F123: 328201 | G123: 45371310607 | H123: Software | I123: 2874 | J123: 2874 | K123: 0 | L123: 239.5 | M123: 0 | N123: 24.4 | O123: 215.1 | P123: thiago.oliveira@altoqi.com.br | Q123: Renovação Automática | R123: Renovação Automática | S123: 45985 | T123: 46023 | U123: 46030 | V123: 46395 | W123: 12 meses | X123: 12 | Y123: Assinatura | Z123: Renovação | AA123: Cartão de crédito | AB123: 12 | AC123: Renovação Automática | AD123: Plano Eberick Professional | AE123: Eberick | AF123: Professional | AG123: =IF(IFERROR(SEARCH("Recorrente",AA123),0)>0,"Recorrente",IF(AB123=1,"À Vista",IF(AB123<=3,"CC 3x",IF(AB123<=12,"CC 12x",IF(AB123>12,"Recorrente",""))))) -> CC 12x | AH123: =IF(AND(SUMIF(E:E,E123,I:I)>=400000,Q123="B2G"),"n","")
A124: 2026 | B124: 1 | C124: 129169628527 | D124: Guilherme Schmitz | E124: 50109456966 | F124: 625279 | G124: 45377063248 | H124: Software | I124: 2874 | J124: 2874 | K124: 0 | L124: 239.5 | M124: 0 | N124: 0.5 | O124: 239 | P124: thiago.oliveira@altoqi.com.br | Q124: Renovação Automática | R124: Renovação Automática | S124: 46029 | T124: 46029 | U124: 46029 | V124: 46394 | W124: 12 meses | X124: 12 | Y124: Assinatura | Z124: Renovação | AA124: Cartão de crédito - Recorrente | AB124: 12 | AC124: Renovação Automática | AD124: Plano Eberick Professional | AE124: Eberick | AF124: Professional | AG124: =IF(IFERROR(SEARCH("Recorrente",AA124),0)>0,"Recorrente",IF(AB124=1,"À Vista",IF(AB124<=3,"CC 3x",IF(AB124<=12,"CC 12x",IF(AB124>12,"Recorrente",""))))) -> Recorrente | AH124: =IF(AND(SUMIF(E:E,E124,I:I)>=400000,Q124="B2G"),"n","")
A125: 2026 | B125: 1 | C125: 22171278257 | D125: Marcelo Corrêa Merlo Pantuzza | E125: 50109921636 | F125: 625287 | G125: 45370196918 | H125: Software | I125: 2874 | J125: 2874 | K125: 0 | L125: 239.5 | M125: 0 | N125: 20.41 | O125: 219.09 | P125: thiago.oliveira@altoqi.com.br | Q125: Renovação Automática | R125: Renovação Automática | S125: 46032 | T125: 46032 | U125: 46029 | V125: 46394 | W125: 12 meses | X125: 12 | Y125: Assinatura | Z125: Renovação | AA125: Cartão de crédito - Recorrente | AB125: 12 | AC125: Renovação Automática | AD125: Plano Eberick Professional | AE125: Eberick | AF125: Professional | AG125: =IF(IFERROR(SEARCH("Recorrente",AA125),0)>0,"Recorrente",IF(AB125=1,"À Vista",IF(AB125<=3,"CC 3x",IF(AB125<=12,"CC 12x",IF(AB125>12,"Recorrente",""))))) -> Recorrente | AH125: =IF(AND(SUMIF(E:E,E125,I:I)>=400000,Q125="B2G"),"n","")
A126: 2026 | B126: 1 | C126: 19435529526 | D126: W R Engenharia e Consultoria LTDA W R ENGENHARIA | E126: 50116911240 | F126: 606978 | G126: 45530074513 | H126: Software | I126: 5034 | J126: 5034 | K126: 0 | L126: 419.5 | M126: 0 | N126: 139.82 | O126: 279.68 | P126: thiago.oliveira@altoqi.com.br | Q126: Renovação Automática | R126: Renovação Automática | S126: 46030 | T126: 46030 | U126: 46030 | V126: 46395 | W126: 12 meses | X126: 12 | Y126: Assinatura | Z126: Renovação | AA126: Cartão de crédito | AB126: 12 | AC126: Renovação Automática | AD126: Plano Builder Premium | AE126: Builder | AF126: Premium | AG126: =IF(IFERROR(SEARCH("Recorrente",AA126),0)>0,"Recorrente",IF(AB126=1,"À Vista",IF(AB126<=3,"CC 3x",IF(AB126<=12,"CC 12x",IF(AB126>12,"Recorrente",""))))) -> CC 12x | AH126: =IF(AND(SUMIF(E:E,E126,I:I)>=400000,Q126="B2G"),"n","")
A127: 2026 | B127: 1 | C127: 2100387 | D127: Fagner Junior Fernandes | E127: 50164726384 | F127: 503814 | G127: 45368833054 | H127: Software | I127: 4638.6 | J127: 4638.6 | K127: 0 | L127: 386.55 | M127: 0 | N127: 113.7 | O127: 272.85 | P127: thiago.oliveira@altoqi.com.br | Q127: Renovação Automática | R127: Renovação Automática | S127: 46030 | T127: 46030 | U127: 46030 | V127: 46395 | W127: 12 meses | X127: 12 | Y127: Assinatura | Z127: Renovação | AA127: Cartão de crédito - Recorrente | AB127: 12 | AC127: Renovação Automática | AD127: Plano Builder Hidro Enterprise | AE127: Builder | AF127: Enterprise | AG127: =IF(IFERROR(SEARCH("Recorrente",AA127),0)>0,"Recorrente",IF(AB127=1,"À Vista",IF(AB127<=3,"CC 3x",IF(AB127<=12,"CC 12x",IF(AB127>12,"Recorrente",""))))) -> Recorrente | AH127: =IF(AND(SUMIF(E:E,E127,I:I)>=400000,Q127="B2G"),"n","")
A128: 2026 | B128: 1 | C128: 19435564614 | D128: UNION ARQUITETURA E ENGENHARIA | E128: 50229057058 | F128: 606164 | G128: 45397296173 | H128: Software | I128: 5334 | J128: 5334 | K128: 0 | L128: 444.5 | M128: 0 | N128: 74.95 | O128: 369.55 | P128: thiago.oliveira@altoqi.com.br | Q128: Renovação Automática | R128: Renovação Automática | S128: 46030 | T128: 46030 | U128: 46030 | V128: 46395 | W128: 12 meses | X128: 12 | Y128: Assinatura | Z128: Renovação | AA128: Cartão de crédito - Recorrente | AB128: 12 | AC128: Renovação Automática | AD128: Plano Builder Infinity | AE128: Builder | AF128: Infinity | AG128: =IF(IFERROR(SEARCH("Recorrente",AA128),0)>0,"Recorrente",IF(AB128=1,"À Vista",IF(AB128<=3,"CC 3x",IF(AB128<=12,"CC 12x",IF(AB128>12,"Recorrente",""))))) -> Recorrente | AH128: =IF(AND(SUMIF(E:E,E128,I:I)>=400000,Q128="B2G"),"n","")
A129: 2026 | B129: 1 | C129: 19435564614 | D129: UNION ARQUITETURA E ENGENHARIA | E129: 50229057058 | F129: 606164 | G129: 45449219750 | H129: Software | I129: 5334 | J129: 5334 | K129: 0 | L129: 444.5 | M129: 0 | N129: 74.95 | O129: 369.55 | P129: thiago.oliveira@altoqi.com.br | Q129: Renovação Automática | R129: Renovação Automática | S129: 46030 | T129: 46030 | U129: 46030 | V129: 46395 | W129: 12 meses | X129: 12 | Y129: Assinatura | Z129: Renovação | AA129: Cartão de crédito - Recorrente | AB129: 12 | AC129: Renovação Automática | AD129: Plano Eberick Professional | AE129: Eberick | AF129: Professional | AG129: =IF(IFERROR(SEARCH("Recorrente",AA129),0)>0,"Recorrente",IF(AB129=1,"À Vista",IF(AB129<=3,"CC 3x",IF(AB129<=12,"CC 12x",IF(AB129>12,"Recorrente",""))))) -> Recorrente | AH129: =IF(AND(SUMIF(E:E,E129,I:I)>=400000,Q129="B2G"),"n","")
A130: 2026 | B130: 1 | C130: 93004671635 | D130: Juan Duarte Silva | E130: 50243571854 | F130: 625327 | G130: 45385103874 | H130: Software | I130: 5514 | J130: 5514 | K130: 0 | L130: 459.5 | M130: 0 | N130: 93.74 | O130: 365.76 | P130: thiago.oliveira@altoqi.com.br | Q130: Renovação Automática | R130: Renovação Automática | S130: 46030 | T130: 46030 | U130: 46030 | V130: 46395 | W130: 12 meses | X130: 12 | Y130: Assinatura | Z130: Renovação | AA130: Cartão de crédito - Recorrente | AB130: 12 | AC130: Renovação Automática | AD130: Plano InBIM Professional | AE130: InBIM | AF130: Professional | AG130: =IF(IFERROR(SEARCH("Recorrente",AA130),0)>0,"Recorrente",IF(AB130=1,"À Vista",IF(AB130<=3,"CC 3x",IF(AB130<=12,"CC 12x",IF(AB130>12,"Recorrente",""))))) -> Recorrente | AH130: =IF(AND(SUMIF(E:E,E130,I:I)>=400000,Q130="B2G"),"n","")
A131: 2026 | B131: 1 | C131: 2094938 | D131: Douglas De Miranda Kons | E131: 50275057922 | F131: 624209 | G131: 46353584302 | H131: Software | I131: 4413 | J131: 4413 | K131: 0 | L131: 367.75 | M131: 0 | N131: 0 | O131: 367.75 | P131: rubia.estipe@altoqi.com.br | Q131: Saving | R131: Saving | S131: 45995 | T131: 46023 | U131: 45995 | V131: 46360 | W131: 12 meses | X131: 12 | Y131: Assinatura | Z131: Renovação | AA131: Cartão de crédito | AB131: 12 | AC131: CS - Saving | AD131: Plano InBIM Professional | AE131: InBIM | AF131: Professional | AG131: =IF(IFERROR(SEARCH("Recorrente",AA131),0)>0,"Recorrente",IF(AB131=1,"À Vista",IF(AB131<=3,"CC 3x",IF(AB131<=12,"CC 12x",IF(AB131>12,"Recorrente",""))))) -> CC 12x | AH131: =IF(AND(SUMIF(E:E,E131,I:I)>=400000,Q131="B2G"),"n","")
A132: 2026 | B132: 1 | C132: 2081652 | D132: Rafael Perius | E132: 50353531321 | F132: 606694 | G132: 47234980901 | H132: Software | I132: 2047.68 | J132: 2047.68 | K132: 0 | L132: 170.64 | M132: 0 | N132: 104.2 | O132: 66.4375 | P132: marcela@altoqi.com.br | Q132: Saving | R132: Saving | S132: 46007 | T132: 46023 | U132: 46020 | V132: 46385 | W132: 12 meses | X132: 12 | Y132: Assinatura | Z132: Renovação | AA132: Cartão de crédito - Recorrente | AB132: 12 | AC132: CS - Saving | AD132: Plano Eberick Professional | AE132: Eberick | AF132: Professional | AG132: =IF(IFERROR(SEARCH("Recorrente",AA132),0)>0,"Recorrente",IF(AB132=1,"À Vista",IF(AB132<=3,"CC 3x",IF(AB132<=12,"CC 12x",IF(AB132>12,"Recorrente",""))))) -> Recorrente | AH132: =IF(AND(SUMIF(E:E,E132,I:I)>=400000,Q132="B2G"),"n","")
A133: 2026 | B133: 1 | C133: 2096843 | D133: Carlos Alberto Lago Honaiser | E133: 50367232565 | F133: 504825 | G133: 45657962833 | H133: Software | I133: 2874 | J133: 2874 | K133: 0 | L133: 239.5 | M133: 0 | N133: 59.5 | O133: 180 | P133: thiago.oliveira@altoqi.com.br | Q133: Renovação Automática | R133: Renovação Automática | S133: 46031 | T133: 46031 | U133: 46031 | V133: 46396 | W133: 12 meses | X133: 12 | Y133: Assinatura | Z133: Renovação | AA133: Cartão de crédito | AB133: 12 | AC133: Renovação Automática | AD133: Plano Builder Professional | AE133: Builder | AF133: Professional | AG133: =IF(IFERROR(SEARCH("Recorrente",AA133),0)>0,"Recorrente",IF(AB133=1,"À Vista",IF(AB133<=3,"CC 3x",IF(AB133<=12,"CC 12x",IF(AB133>12,"Recorrente",""))))) -> CC 12x | AH133: =IF(AND(SUMIF(E:E,E133,I:I)>=400000,Q133="B2G"),"n","")
A134: 2026 | B134: 1 | C134: 59669144212 | D134: Joao Henrique Sampaio Oliveira | E134: 50370522024 | F134: 625344 | G134: 45643665817 | H134: Software | I134: 2874 | J134: 2874 | K134: 0 | L134: 239.5 | M134: 0 | N134: 38.74 | O134: 200.76 | P134: thiago.oliveira@altoqi.com.br | Q134: Renovação Automática | R134: Renovação Automática | S134: 46031 | T134: 46031 | U134: 46031 | V134: 46396 | W134: 12 meses | X134: 12 | Y134: Assinatura | Z134: Renovação | AA134: Cartão de crédito | AB134: 12 | AC134: Renovação Automática | AD134: Plano Builder Professional | AE134: Builder | AF134: Professional | AG134: =IF(IFERROR(SEARCH("Recorrente",AA134),0)>0,"Recorrente",IF(AB134=1,"À Vista",IF(AB134<=3,"CC 3x",IF(AB134<=12,"CC 12x",IF(AB134>12,"Recorrente",""))))) -> CC 12x | AH134: =IF(AND(SUMIF(E:E,E134,I:I)>=400000,Q134="B2G"),"n","")
... A142: 2026 | B142: 1 | C142: 2091759 | D142: Tiago Silva Lopes | E142: 50456341869 | F142: 328132 | G142: 45803119658 | H142: Software | I142: 5127 | J142: 5127 | K142: 0 | L142: 427.25 | M142: 0 | N142: 169.13 | O142: 258.125 | P142: thiago.oliveira@altoqi.com.br | Q142: Renovação Automática | R142: Renovação Automática | S142: 46033 | T142: 46033 | U142: 46033 | V142: 46398 | W142: 12 meses | X142: 12 | Y142: Assinatura | Z142: Renovação | AA142: Cartão de crédito - Recorrente | AB142: 12 | AC142: Renovação Automática | AD142: Plano Visus Cost Management Projetista | AE142: Visus Cost | AF142: Projetista | AG142: =IF(IFERROR(SEARCH("Recorrente",AA142),0)>0,"Recorrente",IF(AB142=1,"À Vista",IF(AB142<=3,"CC 3x",IF(AB142<=12,"CC 12x",IF(AB142>12,"Recorrente",""))))) -> Recorrente | AH142: =IF(AND(SUMIF(E:E,E142,I:I)>=400000,Q142="B2G"),"n","")
A143: 2026 | B143: 1 | C143: 44331693112 | D143: BOM PRINCIPIO ALIMENTOS | E143: 50457686673 | F143: 635808 | G143: 50350678669 | H143: Software | I143: 5718.6 | J143: 5718.6 | K143: 0 | L143: 476.55 | M143: 476.55 | N143: 0 | O143: 0 | P143: eloyse.silveira@altoqi.com.br | Q143: B2B Construtora | R143: B2B Construtora | S143: 46051 | T143: 46051 | V143: 46416 | W143: 12 meses | X143: 12 | Y143: Assinatura | AA143: Pix | AB143: 1 | AC143: Comercial B2B - Construtoras | AD143: Plano Builder Enterprise | AE143: Builder | AF143: Enterprise | AG143: =IF(IFERROR(SEARCH("Recorrente",AA143),0)>0,"Recorrente",IF(AB143=1,"À Vista",IF(AB143<=3,"CC 3x",IF(AB143<=12,"CC 12x",IF(AB143>12,"Recorrente",""))))) -> À Vista | AH143: =IF(AND(SUMIF(E:E,E143,I:I)>=400000,Q143="B2G"),"n","")
A144: 2026 | B144: 1 | C144: 19435418455 | D144: SPIES BESSLER ENGENHARIA E CONSTRUCOES LTDA | E144: 50459489295 | F144: 607190 | G144: 45736117510 | H144: Software | I144: 2874 | J144: 2874 | K144: 0 | L144: 239.5 | M144: 0 | N144: 69.99 | O144: 169.51 | P144: thiago.oliveira@altoqi.com.br | Q144: Renovação Automática | R144: Renovação Automática | S144: 46032 | T144: 46032 | U144: 46032 | V144: 46397 | W144: 12 meses | X144: 12 | Y144: Assinatura | Z144: Renovação | AA144: Cartão de crédito | AB144: 12 | AC144: Renovação Automática | AD144: Plano Eberick Professional | AE144: Eberick | AF144: Professional | AG144: =IF(IFERROR(SEARCH("Recorrente",AA144),0)>0,"Recorrente",IF(AB144=1,"À Vista",IF(AB144<=3,"CC 3x",IF(AB144<=12,"CC 12x",IF(AB144>12,"Recorrente",""))))) -> CC 12x | AH144: =IF(AND(SUMIF(E:E,E144,I:I)>=400000,Q144="B2G"),"n","")
A145: 2026 | B145: 1 | C145: 45934453807 | D145: FAJ NEGOCIOS IMOBILIARIOS LTDA | E145: 50462023435 | F145: 635627 | G145: 49362998813 | H145: Software | I145: 6900 | J145: 6900.03 | K145: 0 | L145: 575 | M145: 575 | N145: 0 | O145: 0 | P145: henrique.silva@altoqi.com.br | Q145: B2B Construtora | R145: B2B Construtora | S145: 46038 | T145: 46038 | V145: 46403 | W145: 12 meses | X145: 12 | Y145: Assinatura | AA145: Cartão de crédito | AB145: 12 | AC145: Comercial B2B - Construtoras | AD145: Plano Builder Infinity | AE145: Builder | AF145: Infinity | AG145: =IF(IFERROR(SEARCH("Recorrente",AA145),0)>0,"Recorrente",IF(AB145=1,"À Vista",IF(AB145<=3,"CC 3x",IF(AB145<=12,"CC 12x",IF(AB145>12,"Recorrente",""))))) -> CC 12x | AH145: =IF(AND(SUMIF(E:E,E145,I:I)>=400000,Q145="B2G"),"n","")
A146: 2026 | B146: 1 | C146: 91588270673 | D146: Fernanda Mostardeiro | E146: 50464082971 | F146: 605893 | G146: 45711598227 | H146: Software | I146: 4027.8 | J146: 4027.8 | K146: 0 | L146: 335.65 | M146: 0 | N146: 166.18 | O146: 169.47 | P146: rubia.estipe@altoqi.com.br | Q146: Saving | R146: Saving | S146: 45987 | T146: 46023 | U146: 46011 | V146: 46376 | W146: 12 meses | X146: 12 | Y146: Assinatura | Z146: Renovação com Expansão | AA146: Cartão de crédito | AB146: 1 | AC146: CS - Saving | AD146: Plano Eberick Premium | AE146: Eberick | AF146: Premium | AG146: =IF(IFERROR(SEARCH("Recorrente",AA146),0)>0,"Recorrente",IF(AB146=1,"À Vista",IF(AB146<=3,"CC 3x",IF(AB146<=12,"CC 12x",IF(AB146>12,"Recorrente",""))))) -> À Vista | AH146: =IF(AND(SUMIF(E:E,E146,I:I)>=400000,Q146="B2G"),"n","")
A147: 2026 | B147: 1 | C147: 30774127123 | D147: MGR PROJETTAR ENGENHARIA DE PROJETOS LTDA | E147: 50464329226 | F147: 521342 | G147: 45842356834 | H147: Software | I147: 10197.36 | J147: 10197.36 | K147: 0 | L147: 849.78 | M147: 0 | N147: 33.69 | O147: 816.09 | P147: rosana@altoqi.com.br | Q147: Saving | R147: Saving | S147: 45992 | T147: 46023 | U147: 46006 | V147: 46371 | W147: 12 meses | X147: 12 | Y147: Assinatura | Z147: Renovação | AA147: Cartão de crédito - Recorrente | AB147: 12 | AC147: CS - Saving | AD147: Plano InBIM Enterprise | AE147: InBIM | AF147: Enterprise | AG147: =IF(IFERROR(SEARCH("Recorrente",AA147),0)>0,"Recorrente",IF(AB147=1,"À Vista",IF(AB147<=3,"CC 3x",IF(AB147<=12,"CC 12x",IF(AB147>12,"Recorrente",""))))) -> Recorrente | AH147: =IF(AND(SUMIF(E:E,E147,I:I)>=400000,Q147="B2G"),"n","")
...

Sheet Realizado GD
A1: Ano | B1: Mês | C1: Email | D1: Realizado
A2: 2026 | B2: 1 | C2: ana.camargo@altoqi.com.br | D2: 96
A3: 2026 | B3: 1 | C3: anand.figueiredo@altoqi.com.br | D3: 43
A4: 2026 | B4: 1 | C4: arthur.trevisiol@altoqi.com.br | D4: 106
A5: 2026 | B5: 1 | C5: eliane.guinther@altoqi.com.br | D5: 1
A6: 2026 | B6: 1 | C6: elisa.costa@altoqi.com.br | D6: 124
A7: 2026 | B7: 1 | C7: luiz.senna@altoqi.com.br | D7: 61
A8: 2026 | B8: 1 | C8: maria.eduarda@altoqi.com.br | D8: 2
A9: 2026 | B9: 1 | C9: matheus.lima@altoqi.com.br | D9: 113
A10: 2026 | B10: 1 | C10: renata.scheffer@altoqi.com.br | D10: 41
A11: 2026 | B11: 2 | C11: amanda.bernardez@altoqi.com.br | D11: 1
A12: 2026 | B12: 2 | C12: ana.camargo@altoqi.com.br | D12: 95
A13: 2026 | B13: 2 | C13: anand.figueiredo@altoqi.com.br | D13: 46
... A47: 2026 | B47: 5 | C47: vanessa.sousa@altoqi.com.br | D47: 62

Sheet Cargos e OTEs
A1: Ano | B1: Mês | C1: Cargo | D1: OTE
A2: 2026 | B2: 4 | C2: Account Executive Jr | D2: 3661.2
A3: 2026 | B3: 4 | C3: Account Executive Pl | D3: 4593.6
A4: 2026 | B4: 4 | C4: Account Executive Sr | D4: 5402.94
A5: 2026 | B5: 4 | C5: Inside Sales Jr | D5: 3742.2
A6: 2026 | B6: 4 | C6: Inside Sales Pl | D6: 4356
A7: 2026 | B7: 4 | C7: Inside Sales Sr | D7: 5016
A8: 2026 | B8: 4 | C8: Farmer Jr | D8: 3746.2
A9: 2026 | B9: 4 | C9: Farmer Pl | D9: 4677.12
A10: 2026 | B10: 4 | C10: Farmer Sr | D10: 6011.88
A11: 2026 | B11: 4 | C11: Sales Development Representative (SDR) I | D11: 1650
A12: 2026 | B12: 4 | C12: Sales Development Representative (SDR) II | D12: 1980
A13: 2026 | B13: 4 | C13: Inside Sales B2G Jr | D13: 5880
... A18: 2026 | B18: 4 | C18: Key Account Corporate B2G Sr | D18: 10500
A19: 2026 | B19: 4 | C19: Account Executive B2G Jr
A20: 2026 | B20: 4 | C20: Account Executive B2G Pl
A21: 2026 | B21: 4 | C21: Account Executive B2G Sr | D21: 9660
A22: 2026 | B22: 4 | C22: Technical Pre-Sales Engineer | D22: 3960
A23: 2026 | B23: 4 | C23: Customer Success Saver Analyst Jr | D23: 3750
A24: 2026 | B24: 4 | C24: Customer Success Saver Analyst Pl | D24: 5400
A25: 2026 | B25: 4 | C25: Customer Success Saver Analyst Sr | D25: 8100
A26: 2026 | B26: 4 | C26: Customer Success Saver Specialist | D26: 11500
A27: 2026 | B27: 4 | C27: Customer Success Renewals Coordinator | D27: 12000
A28: 2026 | B28: 4 | C28: Sales Manager B2g | D28: 12075
A29: 2026 | B29: 4 | C29: Demand Generation Coordinator | D29: 3360
A30: 2026 | B30: 4 | C30: Sales Coordinator B2B | D30: 6600
A31: 2026 | B31: 4 | C31: Sales Coordinator Fsb | D31: 5122.95
A32: 2026 | B32: 4 | C32: Sales Manager Fsb | D32: 9424.8
... A49: 2026 | B49: 5 | C49: Key Account Corporate B2G Sr | D49: 10500
A50: 2026 | B50: 5 | C50: Account Executive B2G Jr
A51: 2026 | B51: 5 | C51: Account Executive B2G Pl
A52: 2026 | B52: 5 | C52: Account Executive B2G Sr | D52: 9660
A53: 2026 | B53: 5 | C53: Technical Pre-Sales Engineer | D53: 3960
A54: 2026 | B54: 5 | C54: Customer Success Saver Analyst Jr | D54: 3750
A55: 2026 | B55: 5 | C55: Customer Success Saver Analyst Pl | D55: 5400
A56: 2026 | B56: 5 | C56: Customer Success Saver Analyst Sr | D56: 8100
A57: 2026 | B57: 5 | C57: Customer Success Saver Specialist | D57: 11500
A58: 2026 | B58: 5 | C58: Customer Success Renewals Coordinator | D58: 12000
A59: 2026 | B59: 5 | C59: Sales Manager B2g | D59: 12075
A60: 2026 | B60: 5 | C60: Demand Generation Coordinator | D60: 3360
A61: 2026 | B61: 5 | C61: Sales Coordinator B2B - E | D61: 6600
A62: 2026 | B62: 5 | C62: Sales Coordinator Fsb | D62: 5122.95
A63: 2026 | B63: 5 | C63: Sales Manager Fsb | D63: 9424.8
... A66: 2026 | B66: 5 | C66: Key Account II | D66: 9660

Sheet Metas
A1: Ano | B1: Mês | C1: Consultor | D1: Email | E1: Equipe | F1: Cargo | G1: Gestor | H1: Tipo | I1: Meta Cheia | J1: Desconto na Meta | K1: Meta Proporcional | L1: Ponderação | M1: % Proteção | N1: Adicional na Meta
A2: 2026 | B2: 1 | C2: Anderson Ortiz | D2: anderson.ortiz@altoqi.com.br | E2: Ares | F2: Consultor | G2: sonia.zielinski@altoqi.com.br | H2: MRR | I2: 10000 | J2: 0.5 | K2: =I2*IF(J2="",1,1-J2) -> 5000 | L2: 1
A3: 2026 | B3: 1 | C3: Francisco Guilherme Junior | D3: francisco.junior@altoqi.com.br | E3: Ares | F3: Consultor | G3: sonia.zielinski@altoqi.com.br | H3: MRR | I3: 10000 | K3: =I3*IF(J3="",1,1-J3) -> 10000 | L3: 1
A4: 2026 | B4: 1 | C4: Rodrigo da Rosa Lima | D4: rodrigo.lima@altoqi.com.br | E4: Ares | F4: Consultor | G4: sonia.zielinski@altoqi.com.br | H4: MRR | I4: 0 | K4: =I4*IF(J4="",1,1-J4) -> 0 | L4: 1
A5: 2026 | B5: 1 | C5: Denis Melo Silva | D5: denis.silva@altoqi.com.br | E5: B2B Construtora | F5: Consultor | H5: MRR | I5: 7500 | J5: 0.75 | K5: =I5*IF(J5="",1,1-J5) -> 1875 | L5: 1
A6: 2026 | B6: 1 | C6: Eloyse Silveira | D6: eloyse.silveira@altoqi.com.br | E6: B2B Construtora | F6: Consultor | H6: MRR | I6: 7500 | J6: 0.5 | K6: =I6*IF(J6="",1,1-J6) -> 3750 | L6: 1
A7: 2026 | B7: 1 | C7: Henrique Teixeira Silva | D7: henrique.silva@altoqi.com.br | E7: B2B Construtora | F7: Consultor | H7: MRR | I7: 7500 | J7: 0.33 | K7: =I7*IF(J7="",1,1-J7) -> 5025 | L7: 1
A8: 2026 | B8: 1 | C8: Rafael Acencio | D8: rafael.acencio@altoqi.com.br | E8: B2B Construtora | F8: Consultor | H8: MRR | I8: 7500 | J8: 0.0952 | K8: =I8*IF(J8="",1,1-J8) -> 6786 | L8: 1
A9: 2026 | B9: 1 | C9: Fernanda da Silva Fertonani | D9: fernanda.fertonani@altoqi.com.br | E9: B2B Escritório | F9: Consultor | H9: MRR | I9: 8500 | J9: 0.5 | K9: =I9*IF(J9="",1,1-J9) -> 4250 | L9: 1
A10: 2026 | B10: 1 | C10: Paola Oliveira | D10: paola.oliveira@altoqi.com.br | E10: B2B Escritório | F10: Consultor | H10: MRR | I10: 8500 | K10: =I10*IF(J10="",1,1-J10) -> 8500 | L10: 1
A11: 2026 | B11: 1 | C11: Aline Castilho Pureza | D11: aline.pureza@altoqi.com.br | E11: Farmer | F11: Consultor | G11: sonia.zielinski@altoqi.com.br | H11: MRR | I11: 5000 | K11: =I11*IF(J11="",1,1-J11) -> 5000 | L11: 1
A12: 2026 | B12: 1 | C12: Clidiani Costa | D12: clidiani@altoqi.com.br | E12: Farmer | F12: Consultor | G12: sonia.zielinski@altoqi.com.br | H12: MRR | I12: 8325 | K12: =I12*IF(J12="",1,1-J12) -> 8325 | L12: 1
A13: 2026 | B13: 1 | C13: Debora Vieira | D13: debora.vieira@altoqi.com.br | E13: Farmer | F13: Consultor | G13: sonia.zielinski@altoqi.com.br | H13: MRR | I13: 7120 | J13: 0.5 | K13: =I13*IF(J13="",1,1-J13) -> 3560 | L13: 1
A14: 2026 | B14: 1 | C14: Mariana Rachadel | D14: mariana@altoqi.com.br | E14: Farmer | F14: Consultor | G14: sonia.zielinski@altoqi.com.br | H14: MRR | I14: 10300 | K14: =I14*IF(J14="",1,1-J14) -> 10300 | L14: 1
A15: 2026 | B15: 1 | C15: Renata Parizotto | D15: renata.parizotto@altoqi.com.br | E15: Farmer | F15: Consultor | G15: sonia.zielinski@altoqi.com.br | H15: MRR | I15: 8700 | K15: =I15*IF(J15="",1,1-J15) -> 8700 | L15: 1
A16: 2026 | B16: 1 | C16: Thales Mariante De Sá | D16: thales.sa@altoqi.com.br | E16: Farmer | F16: Consultor | G16: sonia.zielinski@altoqi.com.br | H16: MRR | I16: 7120 | K16: =I16*IF(J16="",1,1-J16) -> 7120 | L16: 1
A17: 2026 | B17: 1 | C17: Artur Machado | D17: artur.francisco@altoqi.com.br | E17: FSB | F17: Consultor | G17: sonia.zielinski@altoqi.com.br | H17: MRR | I17: 8600 | K17: =I17*IF(J17="",1,1-J17) -> 8600 | L17: 1
A18: 2026 | B18: 1 | C18: Eliane Guinther | D18: eliane.guinther@altoqi.com.br | E18: FSB | F18: Consultor | G18: sonia.zielinski@altoqi.com.br | H18: MRR | I18: 8600 | K18: =I18*IF(J18="",1,1-J18) -> 8600 | L18: 1
A19: 2026 | B19: 1 | C19: Renata Scheffer | D19: renata.scheffer@altoqi.com.br | E19: FSB | F19: Consultor | G19: sonia.zielinski@altoqi.com.br | H19: MRR | I19: 8600 | J19: 0.36 | K19: =IF(M19>0,SUMIFS(Negócios!L:L,Negócios!A:A,A19,Negócios!B:B,B19,Negócios!P:P,D19),I19*IF(J19="",1,1-J19)) -> 1386.11 | L19: 1 | M19: 1
A20: 2026 | B20: 1 | C20: Susana Alves Becker | D20: susana.becker@altoqi.com.br | E20: FSB | F20: Consultor | G20: sonia.zielinski@altoqi.com.br | H20: MRR | I20: 9300 | K20: =I20*IF(J20="",1,1-J20) -> 9300 | L20: 1
A21: 2026 | B21: 1 | C21: Ana Camargo | D21: ana.camargo@altoqi.com.br | E21: GD | F21: Consultor | G21: andre.cardoso@altoqi.com.br | H21: Opps | I21: 96 | J21: 0.25 | K21: =I21*IF(J21="",1,1-J21) -> 72 | L21: 1
A22: 2026 | B22: 1 | C22: Anand Freitas Figueiredo | D22: anand.figueiredo@altoqi.com.br | E22: GD | F22: Consultor | H22: Opps | I22: 40 | K22: =I22*IF(J22="",1,1-J22) -> 40 | L22: 1
A23: 2026 | B23: 1 | C23: André Cardoso | D23: andre.cardoso@altoqi.com.br | E23: GD | F23: Gestor | H23: Opps | I23: 442 | K23: =I23*IF(J23="",1,1-J23) -> 442 | L23: 1
A24: 2026 | B24: 1 | C24: Arthur Treivisol | D24: arthur.trevisiol@altoqi.com.br | E24: GD | F24: Consultor | G24: andre.cardoso@altoqi.com.br | H24: Opps | I24: 96 | K24: =I24*IF(J24="",1,1-J24) -> 96 | L24: 1
A25: 2026 | B25: 1 | C25: Elisa Nickel Costa | D25: elisa.costa@altoqi.com.br | E25: GD | F25: Consultor | G25: andre.cardoso@altoqi.com.br | H25: Opps | I25: 96 | K25: =I25*IF(J25="",1,1-J25) -> 96 | L25: 1
A26: 2026 | B26: 1 | C26: Luiz Arthur Falcão Senna | D26: luiz.senna@altoqi.com.br | E26: GD | F26: Consultor | G26: andre.cardoso@altoqi.com.br | H26: Opps | I26: 47 | K26: =I26*IF(J26="",1,1-J26) -> 47 | L26: 1
A27: 2026 | B27: 1 | C27: Maria Eduarda Barbosa | D27: maria.eduarda@altoqi.com.br | E27: GD | F27: Consultor | G27: andre.cardoso@altoqi.com.br
A28: 2026 | B28: 1 | C28: Matheus Fiebig | D28: matheus.lima@altoqi.com.br | E28: GD | F28: Consultor | G28: andre.cardoso@altoqi.com.br | H28: Opps | I28: 96 | K28: =I28*IF(J28="",1,1-J28) -> 96 | L28: 1
A29: 2026 | B29: 1 | C29: Renata Scheffer | D29: renata.scheffer@altoqi.com.br | E29: GD | F29: Consultor | G29: andre.cardoso@altoqi.com.br | H29: Opps | I29: 96 | J29: 0.58 | K29: =I29*IF(J29="",1,1-J29) -> 40.32 | L29: 1
A30: 2026 | B30: 1 | C30: Sarai Daniela | D30: daniela.cabrera@altoqi.com.br | E30: GD | F30: Consultor | H30: Opps | K30: =I30*IF(J30="",1,1-J30) -> 0 | L30: 1
A31: 2026 | B31: 1 | C31: Angélica da Silva Steinbach | D31: angelica.steinbach@altoqi.com.br | E31: Governo | F31: Consultor | G31: marcelo.maestro@altoqi.com.br | H31: ARR | I31: 114309 | K31: =I31*IF(J31="",1,1-J31) -> 114309 | L31: 0.4
A32: 2026 | B32: 1 | C32: Angélica da Silva Steinbach | D32: angelica.steinbach@altoqi.com.br | E32: Governo | F32: Consultor | G32: marcelo.maestro@altoqi.com.br | H32: Booking | I32: 228618 | K32: =I32*IF(J32="",1,1-J32) -> 228618 | L32: 0.6
A33: 2026 | B33: 1 | C33: Carla Araujo | D33: carla.araujo@altoqi.com.br | E33: Governo | F33: Consultor | G33: marcelo.maestro@altoqi.com.br | H33: ARR | I33: 83126 | K33: =I33*IF(J33="",1,1-J33) -> 83126 | L33: 0.4
A34: 2026 | B34: 1 | C34: Carla Araujo | D34: carla.araujo@altoqi.com.br | E34: Governo | F34: Consultor | G34: marcelo.maestro@altoqi.com.br | H34: Booking | I34: 166252 | K34: =I34*IF(J34="",1,1-J34) -> 166252 | L34: 0.6
A35: 2026 | B35: 1 | C35: Deize Marla Rudek | D35: deize.rudek@altoqi.com.br | E35: Governo | F35: Consultor | G35: marcelo.maestro@altoqi.com.br | H35: ARR | I35: 92681.25 | K35: =I35*IF(J35="",1,1-J35) -> 92681.25 | L35: 0.4
A36: 2026 | B36: 1 | C36: Deize Marla Rudek | D36: deize.rudek@altoqi.com.br | E36: Governo | F36: Consultor | G36: marcelo.maestro@altoqi.com.br | H36: Booking | I36: 185362.49 | K36: =I36*IF(J36="",1,1-J36) -> 185362.49 | L36: 0.6
A37: 2026 | B37: 1 | C37: Fernanda Cristina Barbosa | D37: fernanda.barbosa@altoqi.com.br | E37: Governo | F37: Consultor | G37: marcelo.maestro@altoqi.com.br | H37: ARR | I37: 92683.7 | K37: =I37*IF(J37="",1,1-J37) -> 92683.7 | L37: 0.4
A38: 2026 | B38: 1 | C38: Fernanda Cristina Barbosa | D38: fernanda.barbosa@altoqi.com.br | E38: Governo | F38: Consultor | G38: marcelo.maestro@altoqi.com.br | H38: Booking | I38: 185367.4 | K38: =I38*IF(J38="",1,1-J38) -> 185367.4 | L38: 0.6
A39: 2026 | B39: 1 | C39: Henry Carlos Petersen | D39: henry.petersen@altoqi.com.br | E39: Governo | F39: Consultor | G39: marcelo.maestro@altoqi.com.br | H39: ARR | I39: 198811.3 | K39: =I39*IF(J39="",1,1-J39) -> 198811.3 | L39: 0.4
A40: 2026 | B40: 1 | C40: Henry Carlos Petersen | D40: henry.petersen@altoqi.com.br | E40: Governo | F40: Consultor | G40: marcelo.maestro@altoqi.com.br | H40: Booking | I40: 397622.6 | K40: =I40*IF(J40="",1,1-J40) -> 397622.6 | L40: 0.6
A41: 2026 | B41: 1 | C41: Jenifer das Dores Soares | D41: jenifer.soares@altoqi.com.br | E41: Governo | F41: Consultor | G41: marcelo.maestro@altoqi.com.br | H41: ARR | I41: 53512.5 | K41: =I41*IF(J41="",1,1-J41) -> 53512.5 | L41: 0.4
A42: 2026 | B42: 1 | C42: Jenifer das Dores Soares | D42: jenifer.soares@altoqi.com.br | E42: Governo | F42: Consultor | G42: marcelo.maestro@altoqi.com.br | H42: Booking | I42: 107025 | K42: =I42*IF(J42="",1,1-J42) -> 107025 | L42: 0.6
... A46: 2026 | B46: 1 | C46: Leandro Fontana da Silva | D46: leandro.fontana@altoqi.com.br | E46: Governo | F46: Consultor | G46: marcelo.maestro@altoqi.com.br | H46: Booking | I46: 331869.72 | K46: =I46*IF(J46="",1,1-J46) -> 331869.72 | L46: 0.6
A47: 2026 | B47: 1 | C47: Marcelo Maestro | D47: marcelo.maestro@altoqi.com.br | E47: Governo | F47: Gestor | H47: Booking | I47: 1951064.7 | K47: =I47*IF(J47="",1,1-J47) -> 1951064.7 | L47: 0.8
A48: 2026 | B48: 1 | C48: Marcelo Maestro | D48: marcelo.maestro@altoqi.com.br | E48: Governo | F48: Gestor | H48: Meta Atingida | I48: 0.8 | K48: =I48*IF(J48="",1,1-J48) -> 0.8 | L48: 0.2
A49: 2026 | B49: 1 | C49: Nathan Alves | D49: nathan.alves@altoqi.com.br | E49: Governo | F49: Consultor | G49: marcelo.maestro@altoqi.com.br | H49: ARR | I49: 66667.5 | K49: =I49*IF(J49="",1,1-J49) -> 66667.5 | L49: 0.4
A50: 2026 | B50: 1 | C50: Nathan Alves | D50: nathan.alves@altoqi.com.br | E50: Governo | F50: Consultor | G50: marcelo.maestro@altoqi.com.br | H50: Booking | I50: 133335 | K50: =I50*IF(J50="",1,1-J50) -> 133335 | L50: 0.6
A51: 2026 | B51: 1 | C51: Soraia Fronchetti | D51: soraia@altoqi.com.br | E51: Governo | F51: Consultor | G51: marcelo.maestro@altoqi.com.br | H51: ARR | I51: 198760 | K51: =I51*IF(J51="",1,1-J51) -> 198760 | L51: 0.4
A52: 2026 | B52: 1 | C52: Soraia Fronchetti | D52: soraia@altoqi.com.br | E52: Governo | F52: Consultor | G52: marcelo.maestro@altoqi.com.br | H52: Booking | I52: 397520 | K52: =I52*IF(J52="",1,1-J52) -> 397520 | L52: 0.6
A53: 2026 | B53: 1 | C53: Tabata Couto | D53: tabata.couto@altoqi.com.br | E53: Governo | F53: Consultor | G53: marcelo.maestro@altoqi.com.br | H53: ARR | I53: 53442 | K53: =I53*IF(J53="",1,1-J53) -> 53442 | L53: 0.4
A54: 2026 | B54: 1 | C54: Tabata Couto | D54: tabata.couto@altoqi.com.br | E54: Governo | F54: Consultor | G54: marcelo.maestro@altoqi.com.br | H54: Booking | I54: 106884 | K54: =I54*IF(J54="",1,1-J54) -> 106884 | L54: 0.6
A55: 2026 | B55: 1 | C55: Beatriz Nau | D55: beatriz@altoqi.com.br | E55: Saving | F55: Gestor | H55: MRR | I55: 92366.1 | K55: =I55*IF(J55="",1,1-J55) -> 92366.1 | L55: 1
A56: 2026 | B56: 1 | C56: Cintia Faraco | D56: cintia@altoqi.com.br | E56: Saving | F56: Consultor | G56: beatriz@altoqi.com.br | H56: MRR | I56: 12389.69 | K56: =I56*IF(J56="",1,1-J56) -> 12389.69 | L56: 1
A57: 2026 | B57: 1 | C57: Francyellen Batista | D57: francyellen@altoqi.com.br | E57: Saving | F57: Consultor | G57: beatriz@altoqi.com.br | H57: MRR | I57: 11826.65 | K57: =I57*IF(J57="",1,1-J57) -> 11826.65 | L57: 1
A58: 2026 | B58: 1 | C58: Jaqueline Correa | D58: jaqueline.correa@altoqi.com.br | E58: Saving | F58: Consultor | G58: beatriz@altoqi.com.br | H58: MRR | I58: 13796.64 | K58: =I58*IF(J58="",1,1-J58) -> 13796.64 | L58: 1
A59: 2026 | B59: 1 | C59: Marcela Accacio | D59: marcela@altoqi.com.br | E59: Saving | F59: Consultor | G59: beatriz@altoqi.com.br | H59: MRR | I59: 12427.33 | K59: =I59*IF(J59="",1,1-J59) -> 12427.33 | L59: 1
A60: 2026 | B60: 1 | C60: Rosana Machado | D60: rosana@altoqi.com.br | E60: Saving | F60: Consultor | G60: beatriz@altoqi.com.br | H60: MRR | I60: 11424.3 | K60: =I60*IF(J60="",1,1-J60) -> 11424.3 | L60: 1
A61: 2026 | B61: 1 | C61: Rubia Estipe | D61: rubia.estipe@altoqi.com.br | E61: Saving | F61: Consultor | G61: beatriz@altoqi.com.br | H61: MRR | I61: 13955.9 | K61: =I61*IF(J61="",1,1-J61) -> 13955.9 | L61: 1
A62: 2026 | B62: 1 | C62: Silvia Estipe | D62: silvia.estipe@altoqi.com.br | E62: Saving | F62: Consultor | G62: beatriz@altoqi.com.br | H62: MRR | I62: 12485.74 | K62: =I62*IF(J62="",1,1-J62) -> 12485.74 | L62: 1
A63: 2026 | B63: 1 | C63: Sonia Maria Zielinski Pockszevnicki | D63: sonia.zielinski@altoqi.com.br | E63: Sonia | F63: Gestor | H63: MRR | I63: 84505 | K63: =I63*IF(J63="",1,1-J63) -> 84505 | L63: 1
A64: 2026 | B64: 2 | C64: Francisco Guilherme Junior | D64: francisco.junior@altoqi.com.br | E64: Ares | F64: Consultor | G64: sonia.zielinski@altoqi.com.br | H64: MRR | I64: 14300 | J64: 0.5 | K64: =I64*IF(J64="",1,1-J64) -> 7150 | L64: 1
A65: 2026 | B65: 2 | C65: Rodrigo da Rosa Lima | D65: rodrigo.lima@altoqi.com.br | E65: Ares | F65: Consultor | G65: sonia.zielinski@altoqi.com.br | H65: MRR | I65: 11750 | K65: =I65*IF(J65="",1,1-J65) -> 11750 | L65: 1
A66: 2026 | B66: 2 | C66: Denis Melo Silva | D66: denis.silva@altoqi.com.br | E66: B2B Construtora | F66: Consultor | H66: MRR | I66: 7626 | J66: 0.7 | K66: 2288 | L66: 1
A67: 2026 | B67: 2 | C67: Eloyse Silveira | D67: eloyse.silveira@altoqi.com.br | E67: B2B Construtora | F67: Consultor | H67: MRR | I67: 6100 | K67: =I67*IF(J67="",1,1-J67) -> 6100 | L67: 1
A68: 2026 | B68: 2 | C68: Henrique Teixeira Silva | D68: henrique.silva@altoqi.com.br | E68: B2B Construtora | F68: Consultor | H68: MRR | I68: 6100 | K68: =I68*IF(J68="",1,1-J68) -> 6100 | L68: 1
A69: 2026 | B69: 2 | C69: Rafael Acencio | D69: rafael.acencio@altoqi.com.br | E69: B2B Construtora | F69: Consultor | H69: MRR | I69: 7626 | J69: 0.34 | K69: 5033 | L69: 1
A70: 2026 | B70: 2 | C70: Fernanda da Silva Fertonani | D70: fernanda.fertonani@altoqi.com.br | E70: B2B Escritório | F70: Consultor | H70: MRR | I70: 9200 | K70: =I70*IF(J70="",1,1-J70) -> 9200 | L70: 1
A71: 2026 | B71: 2 | C71: Paola Oliveira | D71: paola.oliveira@altoqi.com.br | E71: B2B Escritório | F71: Consultor | H71: MRR | I71: 9200 | J71: 0.5 | K71: =I71*IF(J71="",1,1-J71) -> 4600 | L71: 1
A72: 2026 | B72: 2 | C72: Aline Castilho Pureza | D72: aline.pureza@altoqi.com.br | E72: Farmer | F72: Consultor | G72: sonia.zielinski@altoqi.com.br | H72: MRR | I72: 8000 | J72: 0.4 | K72: =I72*IF(J72="",1,1-J72) -> 4800 | L72: 1
A73: 2026 | B73: 2 | C73: Clidiani Costa | D73: clidiani@altoqi.com.br | E73: Farmer | F73: Consultor | G73: sonia.zielinski@altoqi.com.br | H73: MRR | I73: 9775.6417 | J73: 0.22 | K73: =I73*IF(J73="",1,1-J73) + 1216.308 -> 8841.3085 | L73: 1
A74: 2026 | B74: 2 | C74: Debora Vieira | D74: debora.vieira@altoqi.com.br | E74: Farmer | F74: Consultor | G74: sonia.zielinski@altoqi.com.br | H74: MRR | I74: 8964 | K74: =I74*IF(J74="",1,1-J74) -> 8964 | L74: 1
A75: 2026 | B75: 2 | C75: Mariana Rachadel | D75: mariana@altoqi.com.br | E75: Farmer | F75: Consultor | G75: sonia.zielinski@altoqi.com.br | H75: MRR | I75: 13888.89 | J75: 0.37 | K75: =I75*IF(J75="",1,1-J75) + 3004.188 -> 11754.189 | L75: 1
A76: 2026 | B76: 2 | C76: Renata Parizotto | D76: renata.parizotto@altoqi.com.br | E76: Farmer | F76: Consultor | G76: sonia.zielinski@altoqi.com.br | H76: MRR | I76: 11510.2 | J76: 0.51 | K76: =I76*IF(J76="",1,1-J76) + 921.888 -> 6561.886 | L76: 1
A77: 2026 | B77: 2 | C77: Thales Mariante De Sá | D77: thales.sa@altoqi.com.br | E77: Farmer | F77: Consultor | G77: sonia.zielinski@altoqi.com.br | H77: MRR | I77: 8512 | K77: =I77*IF(J77="",1,1-J77) -> 8512 | L77: 1
A78: 2026 | B78: 2 | C78: Anderson Ortiz | D78: anderson.ortiz@altoqi.com.br | E78: FSB | F78: Gestor | H78: MRR | I78: 28500 | K78: =I78*IF(J78="",1,1-J78) -> 28500 | L78: 1
A79: 2026 | B79: 2 | C79: Artur Machado | D79: artur.francisco@altoqi.com.br | E79: FSB | F79: Consultor | G79: anderson.ortiz@altoqi.com.br | H79: MRR | I79: 9200 | J79: 0.5 | K79: =I79*IF(J79="",1,1-J79) -> 4600 | L79: 1
A80: 2026 | B80: 2 | C80: Eliane Guinther | D80: eliane.guinther@altoqi.com.br | E80: FSB | F80: Consultor | G80: anderson.ortiz@altoqi.com.br | H80: MRR | I80: 9200 | K80: =I80*IF(J80="",1,1-J80) -> 9200 | L80: 1
A81: 2026 | B81: 2 | C81: Renata Scheffer | D81: renata.scheffer@altoqi.com.br | E81: FSB | F81: Consultor | G81: anderson.ortiz@altoqi.com.br | H81: MRR | I81: 9200 | J81: 0.5 | K81: =I81*IF(J81="",1,1-J81) -> 4600 | L81: 1
A82: 2026 | B82: 2 | C82: Susana Alves Becker | D82: susana.becker@altoqi.com.br | E82: FSB | F82: Consultor | G82: anderson.ortiz@altoqi.com.br | H82: MRR | I82: 10120 | K82: =I82*IF(J82="",1,1-J82) -> 10120 | L82: 1
A83: 2026 | B83: 2 | C83: Ana Camargo | D83: ana.camargo@altoqi.com.br | E83: GD | F83: Consultor | G83: andre.cardoso@altoqi.com.br | H83: Opps | I83: 98 | K83: =I83*IF(J83="",1,1-J83) -> 98 | L83: 1
A84: 2026 | B84: 2 | C84: Anand Freitas Figueiredo | D84: anand.figueiredo@altoqi.com.br | E84: GD | F84: Consultor | H84: Opps | I84: 40 | K84: =I84*IF(J84="",1,1-J84) -> 40 | L84: 1
A85: 2026 | B85: 2 | C85: André Cardoso | D85: andre.cardoso@altoqi.com.br | E85: GD | F85: Gestor | H85: Opps | I85: 499 | K85: =I85*IF(J85="",1,1-J85) -> 499 | L85: 1
A86: 2026 | B86: 2 | C86: Arthur Treivisol | D86: arthur.trevisiol@altoqi.com.br | E86: GD | F86: Consultor | G86: andre.cardoso@altoqi.com.br | H86: Opps | I86: 98 | K86: =I86*IF(J86="",1,1-J86) -> 98 | L86: 1
A87: 2026 | B87: 2 | C87: Elisa Nickel Costa | D87: elisa.costa@altoqi.com.br | E87: GD | F87: Consultor | G87: andre.cardoso@altoqi.com.br | H87: Opps | I87: 98 | K87: =I87*IF(J87="",1,1-J87) -> 98 | L87: 1
A88: 2026 | B88: 2 | C88: Luiz Arthur Falcão Senna | D88: luiz.senna@altoqi.com.br | E88: GD | F88: Consultor | G88: andre.cardoso@altoqi.com.br | H88: Opps | I88: 74 | K88: =I88*IF(J88="",1,1-J88) -> 74 | L88: 1
A89: 2026 | B89: 2 | C89: Maria Eduarda Barbosa | D89: maria.eduarda@altoqi.com.br | E89: GD | F89: Consultor | G89: andre.cardoso@altoqi.com.br | H89: Opps | I89: 100 | J89: 0.67 | K89: =I89*IF(J89="",1,1-J89) -> 33 | L89: 1
A90: 2026 | B90: 2 | C90: Matheus Fiebig | D90: matheus.lima@altoqi.com.br | E90: GD | F90: Consultor | G90: andre.cardoso@altoqi.com.br | H90: Opps | I90: 98 | K90: =I90*IF(J90="",1,1-J90) -> 98 | L90: 1
A91: 2026 | B91: 2 | C91: Sarai Daniela | D91: daniela.cabrera@altoqi.com.br | E91: GD | F91: Consultor | K91: =I91*IF(J91="",1,1-J91) -> 0 | L91: 1
A92: 2026 | B92: 2 | C92: Angélica da Silva Steinbach | D92: angelica.steinbach@altoqi.com.br | E92: Governo | F92: Consultor | G92: marcelo.maestro@altoqi.com.br | H92: ARR | I92: 114309 | K92: =I92*IF(J92="",1,1-J92) -> 114309 | L92: 0.4
A93: 2026 | B93: 2 | C93: Angélica da Silva Steinbach | D93: angelica.steinbach@altoqi.com.br | E93: Governo | F93: Consultor | G93: marcelo.maestro@altoqi.com.br | H93: Booking | I93: 228618 | K93: =I93*IF(J93="",1,1-J93) -> 228618 | L93: 0.6
A94: 2026 | B94: 2 | C94: Carla Araujo | D94: carla.araujo@altoqi.com.br | E94: Governo | F94: Consultor | G94: marcelo.maestro@altoqi.com.br | H94: ARR | I94: 83126 | K94: =I94*IF(J94="",1,1-J94) -> 83126 | L94: 0.4
A95: 2026 | B95: 2 | C95: Carla Araujo | D95: carla.araujo@altoqi.com.br | E95: Governo | F95: Consultor | G95: marcelo.maestro@altoqi.com.br | H95: Booking | I95: 166252 | K95: =I95*IF(J95="",1,1-J95) -> 166252 | L95: 0.6
A96: 2026 | B96: 2 | C96: Deize Marla Rudek | D96: deize.rudek@altoqi.com.br | E96: Governo | F96: Consultor | G96: marcelo.maestro@altoqi.com.br | H96: ARR | I96: 92681.245 | K96: =I96*IF(J96="",1,1-J96) -> 92681.245 | L96: 0.4
A97: 2026 | B97: 2 | C97: Deize Marla Rudek | D97: deize.rudek@altoqi.com.br | E97: Governo | F97: Consultor | G97: marcelo.maestro@altoqi.com.br | H97: Booking | I97: 185362.49 | K97: =I97*IF(J97="",1,1-J97) -> 185362.49 | L97: 0.6
A98: 2026 | B98: 2 | C98: Fernanda Cristina Barbosa | D98: fernanda.barbosa@altoqi.com.br | E98: Governo | F98: Consultor | G98: marcelo.maestro@altoqi.com.br | H98: ARR | I98: 92683.7 | K98: =I98*IF(J98="",1,1-J98) -> 92683.7 | L98: 0.4
A99: 2026 | B99: 2 | C99: Fernanda Cristina Barbosa | D99: fernanda.barbosa@altoqi.com.br | E99: Governo | F99: Consultor | G99: marcelo.maestro@altoqi.com.br | H99: Booking | I99: 185367.4 | K99: =I99*IF(J99="",1,1-J99) -> 185367.4 | L99: 0.6
A100: 2026 | B100: 2 | C100: Henry Carlos Petersen | D100: henry.petersen@altoqi.com.br | E100: Governo | F100: Consultor | G100: marcelo.maestro@altoqi.com.br | H100: ARR | I100: 198811.3 | K100: =I100*IF(J100="",1,1-J100) -> 198811.3 | L100: 0.4
A101: 2026 | B101: 2 | C101: Henry Carlos Petersen | D101: henry.petersen@altoqi.com.br | E101: Governo | F101: Consultor | G101: marcelo.maestro@altoqi.com.br | H101: Booking | I101: 397622.6 | K101: =I101*IF(J101="",1,1-J101) -> 397622.6 | L101: 0.6
A102: 2026 | B102: 2 | C102: Jenifer das Dores Soares | D102: jenifer.soares@altoqi.com.br | E102: Governo | F102: Consultor | G102: marcelo.maestro@altoqi.com.br | H102: ARR | I102: 72618 | J102: 0.36842105 | K102: =I102*IF(J102="",1,1-J102) -> 45864 | L102: 0.4
A103: 2026 | B103: 2 | C103: Jenifer das Dores Soares | D103: jenifer.soares@altoqi.com.br | E103: Governo | F103: Consultor | G103: marcelo.maestro@altoqi.com.br | H103: Booking | I103: 145236 | J103: 0.36842105 | K103: =I103*IF(J103="",1,1-J103) -> 91728 | L103: 0.6
...

Sheet Parâmetros
A1: Ano | B1: Mês | C1: Consultor | D1: Email | E1: Equipe | F1: Cargo | G1: Cliff OTE 01 | H1: OTE 01 Cheio | I1: OTE 01 Proporcional | J1: Cliff OTE 02 | K1: OTE 02 Cheio | L1: OTE 02 Proporcional | M1: Cliff OTE 03 | N1: OTE 03 Cheio | O1: OTE 03 Proporcional | P1: Cliff Acelerador 01 | Q1: Acelerador OTE 01 | R1: Cliff Acelerador 02 | S1: Val Acelerador OTE 02 | T1: Cliff Acelerador 03 | U1: Acelerador OTE 03 | V1: Cliff Booking Extra | W1: % Booking Extra
A2: 2026 | B2: 1 | C2: Anderson Ortiz | D2: anderson.ortiz@altoqi.com.br | E2: Ares | F2: Consultor | G2: 0.55 | H2: 3960 | I2: =IF(_xlfn.MAXIFS(Metas!J:J,Metas!A:A,A2,Metas!B:B,B2,Metas!D:D,D2) = 0,H2,H2 * (1-_xlfn.MAXIFS(Metas!J:J,Metas!A:A,A2,Metas!B:B,B2,Metas!D:D,D2))) -> 1980 | L2: =IF(_xlfn.MAXIFS(Metas!J:J,Metas!A:A,A2,Metas!B:B,B2,Metas!D:D,D2) = 0,K2,K2 * (1-_xlfn.MAXIFS(Metas!J:J,Metas!A:A,A2,Metas!B:B,B2,Metas!D:D,D2))) -> 0 | O2: =IF(_xlfn.MAXIFS(Metas!J:J,Metas!A:A,A2,Metas!B:B,B2,Metas!D:D,D2) = 0,N2,N2 * (1-_xlfn.MAXIFS(Metas!J:J,Metas!A:A,A2,Metas!B:B,B2,Metas!D:D,D2))) -> 0 | P2: 0.95 | Q2: 1.15 | R2: 1.05 | S2: 1.25 | V2: =G2 -> 0.55 | W2: 0.02
A3: 2026 | B3: 1 | C3: Francisco Guilherme Junior | D3: francisco.junior@altoqi.com.br | E3: Ares | F3: Consultor | G3: 0.55 | H3: 4176 | I3: =IF(_xlfn.MAXIFS(Metas!J:J,Metas!A:A,A3,Metas!B:B,B3,Metas!D:D,D3) = 0,H3,H3 * (1-_xlfn.MAXIFS(Metas!J:J,Metas!A:A,A3,Metas!B:B,B3,Metas!D:D,D3))) -> 4176 | L3: =IF(_xlfn.MAXIFS(Metas!J:J,Metas!A:A,A3,Metas!B:B,B3,Metas!D:D,D3) = 0,K3,K3 * (1-_xlfn.MAXIFS(Metas!J:J,Metas!A:A,A3,Metas!B:B,B3,Metas!D:D,D3))) -> 0 | O3: =IF(_xlfn.MAXIFS(Metas!J:J,Metas!A:A,A3,Metas!B:B,B3,Metas!D:D,D3) = 0,N3,N3 * (1-_xlfn.MAXIFS(Metas!J:J,Metas!A:A,A3,Metas!B:B,B3,Metas!D:D,D3))) -> 0 | P3: 0.95 | Q3: 1.15 | R3: 1.05 | S3: 1.25 | V3: =G3 -> 0.55 | W3: 0.02
A4: 2026 | B4: 1 | C4: Rodrigo da Rosa Lima | D4: rodrigo.lima@altoqi.com.br | E4: Ares | F4: Consultor | G4: 0.55 | H4: 3564 | I4: =IF(_xlfn.MAXIFS(Metas!J:J,Metas!A:A,A4,Metas!B:B,B4,Metas!D:D,D4) = 0,H4,H4 * (1-_xlfn.MAXIFS(Metas!J:J,Metas!A:A,A4,Metas!B:B,B4,Metas!D:D,D4))) -> 3564 | L4: =IF(_xlfn.MAXIFS(Metas!J:J,Metas!A:A,A4,Metas!B:B,B4,Metas!D:D,D4) = 0,K4,K4 * (1-_xlfn.MAXIFS(Metas!J:J,Metas!A:A,A4,Metas!B:B,B4,Metas!D:D,D4))) -> 0 | O4: =IF(_xlfn.MAXIFS(Metas!J:J,Metas!A:A,A4,Metas!B:B,B4,Metas!D:D,D4) = 0,N4,N4 * (1-_xlfn.MAXIFS(Metas!J:J,Metas!A:A,A4,Metas!B:B,B4,Metas!D:D,D4))) -> 0 | P4: 0.95 | Q4: 1.15 | R4: 1.05 | S4: 1.25 | V4: =G4 -> 0.55 | W4: 0.02
A5: 2026 | B5: 1 | C5: Denis Melo Silva | D5: denis.silva@altoqi.com.br | E5: B2B Construtora | F5: Consultor | G5: 0.55 | H5: 4176 | I5: =IF(_xlfn.MAXIFS(Metas!J:J,Metas!A:A,A5,Metas!B:B,B5,Metas!D:D,D5) = 0,H5,H5 * (1-_xlfn.MAXIFS(Metas!J:J,Metas!A:A,A5,Metas!B:B,B5,Metas!D:D,D5))) -> 1044 | L5: =IF(_xlfn.MAXIFS(Metas!J:J,Metas!A:A,A5,Metas!B:B,B5,Metas!D:D,D5) = 0,K5,K5 * (1-_xlfn.MAXIFS(Metas!J:J,Metas!A:A,A5,Metas!B:B,B5,Metas!D:D,D5))) -> 0 | O5: =IF(_xlfn.MAXIFS(Metas!J:J,Metas!A:A,A5,Metas!B:B,B5,Metas!D:D,D5) = 0,N5,N5 * (1-_xlfn.MAXIFS(Metas!J:J,Metas!A:A,A5,Metas!B:B,B5,Metas!D:D,D5))) -> 0 | P5: 0.95 | Q5: 1.15 | R5: 1.05 | S5: 1.25 | V5: =G5 -> 0.55 | W5: 0.02
A6: 2026 | B6: 1 | C6: Eloyse Silveira | D6: eloyse.silveira@altoqi.com.br | E6: B2B Construtora | F6: Consultor | G6: 0.55 | H6: 4176 | I6: =IF(_xlfn.MAXIFS(Metas!J:J,Metas!A:A,A6,Metas!B:B,B6,Metas!D:D,D6) = 0,H6,H6 * (1-_xlfn.MAXIFS(Metas!J:J,Metas!A:A,A6,Metas!B:B,B6,Metas!D:D,D6))) -> 2088 | L6: =IF(_xlfn.MAXIFS(Metas!J:J,Metas!A:A,A6,Metas!B:B,B6,Metas!D:D,D6) = 0,K6,K6 * (1-_xlfn.MAXIFS(Metas!J:J,Metas!A:A,A6,Metas!B:B,B6,Metas!D:D,D6))) -> 0 | O6: =IF(_xlfn.MAXIFS(Metas!J:J,Metas!A:A,A6,Metas!B:B,B6,Metas!D:D,D6) = 0,N6,N6 * (1-_xlfn.MAXIFS(Metas!J:J,Metas!A:A,A6,Metas!B:B,B6,Metas!D:D,D6))) -> 0 | P6: 0.95 | Q6: 1.15 | R6: 1.05 | S6: 1.25 | V6: =G6 -> 0.55 | W6: 0.02
A7: 2026 | B7: 1 | C7: Henrique Teixeira Silva | D7: henrique.silva@altoqi.com.br | E7: B2B Construtora | F7: Consultor | G7: 0.55 | H7: 4176 | I7: =IF(_xlfn.MAXIFS(Metas!J:J,Metas!A:A,A7,Metas!B:B,B7,Metas!D:D,D7) = 0,H7,H7 * (1-_xlfn.MAXIFS(Metas!J:J,Metas!A:A,A7,Metas!B:B,B7,Metas!D:D,D7))) -> 2797.92 | L7: =IF(_xlfn.MAXIFS(Metas!J:J,Metas!A:A,A7,Metas!B:B,B7,Metas!D:D,D7) = 0,K7,K7 * (1-_xlfn.MAXIFS(Metas!J:J,Metas!A:A,A7,Metas!B:B,B7,Metas!D:D,D7))) -> 0 | O7: =IF(_xlfn.MAXIFS(Metas!J:J,Metas!A:A,A7,Metas!B:B,B7,Metas!D:D,D7) = 0,N7,N7 * (1-_xlfn.MAXIFS(Metas!J:J,Metas!A:A,A7,Metas!B:B,B7,Metas!D:D,D7))) -> 0 | P7: 0.95 | Q7: 1.15 | R7: 1.05 | S7: 1.25 | V7: =G7 -> 0.55 | W7: 0.02
A8: 2026 | B8: 1 | C8: Rafael Acencio | D8: rafael.acencio@altoqi.com.br | E8: B2B Construtora | F8: Consultor | G8: 0.55 | H8: 4176 | I8: =IF(_xlfn.MAXIFS(Metas!J:J,Metas!A:A,A8,Metas!B:B,B8,Metas!D:D,D8) = 0,H8,H8 * (1-_xlfn.MAXIFS(Metas!J:J,Metas!A:A,A8,Metas!B:B,B8,Metas!D:D,D8))) -> 3778.4448 | L8: =IF(_xlfn.MAXIFS(Metas!J:J,Metas!A:A,A8,Metas!B:B,B8,Metas!D:D,D8) = 0,K8,K8 * (1-_xlfn.MAXIFS(Metas!J:J,Metas!A:A,A8,Metas!B:B,B8,Metas!D:D,D8))) -> 0 | O8: =IF(_xlfn.MAXIFS(Metas!J:J,Metas!A:A,A8,Metas!B:B,B8,Metas!D:D,D8) = 0,N8,N8 * (1-_xlfn.MAXIFS(Metas!J:J,Metas!A:A,A8,Metas!B:B,B8,Metas!D:D,D8))) -> 0 | P8: 0.95 | Q8: 1.15 | R8: 1.05 | S8: 1.25 | V8: =G8 -> 0.55 | W8: 0.02
A9: 2026 | B9: 1 | C9: Fernanda da Silva Fertonani | D9: fernanda.fertonani@altoqi.com.br | E9: B2B Escritório | F9: Consultor | G9: 0.55 | H9: 4176 | I9: =IF(_xlfn.MAXIFS(Metas!J:J,Metas!A:A,A9,Metas!B:B,B9,Metas!D:D,D9) = 0,H9,H9 * (1-_xlfn.MAXIFS(Metas!J:J,Metas!A:A,A9,Metas!B:B,B9,Metas!D:D,D9))) -> 2088 | L9: =IF(_xlfn.MAXIFS(Metas!J:J,Metas!A:A,A9,Metas!B:B,B9,Metas!D:D,D9) = 0,K9,K9 * (1-_xlfn.MAXIFS(Metas!J:J,Metas!A:A,A9,Metas!B:B,B9,Metas!D:D,D9))) -> 0 | O9: =IF(_xlfn.MAXIFS(Metas!J:J,Metas!A:A,A9,Metas!B:B,B9,Metas!D:D,D9) = 0,N9,N9 * (1-_xlfn.MAXIFS(Metas!J:J,Metas!A:A,A9,Metas!B:B,B9,Metas!D:D,D9))) -> 0 | P9: 0.95 | Q9: 1.15 | R9: 1.05 | S9: 1.25 | V9: =G9 -> 0.55 | W9: 0.02
A10: 2026 | B10: 1 | C10: Paola Oliveira | D10: paola.oliveira@altoqi.com.br | E10: B2B Escritório | F10: Consultor | G10: 0.55 | H10: 4176 | I10: =IF(_xlfn.MAXIFS(Metas!J:J,Metas!A:A,A10,Metas!B:B,B10,Metas!D:D,D10) = 0,H10,H10 * (1-_xlfn.MAXIFS(Metas!J:J,Metas!A:A,A10,Metas!B:B,B10,Metas!D:D,D10))) -> 4176 | L10: =IF(_xlfn.MAXIFS(Metas!J:J,Metas!A:A,A10,Metas!B:B,B10,Metas!D:D,D10) = 0,K10,K10 * (1-_xlfn.MAXIFS(Metas!J:J,Metas!A:A,A10,Metas!B:B,B10,Metas!D:D,D10))) -> 0 | O10: =IF(_xlfn.MAXIFS(Metas!J:J,Metas!A:A,A10,Metas!B:B,B10,Metas!D:D,D10) = 0,N10,N10 * (1-_xlfn.MAXIFS(Metas!J:J,Metas!A:A,A10,Metas!B:B,B10,Metas!D:D,D10))) -> 0 | P10: 0.95 | Q10: 1.15 | R10: 1.05 | S10: 1.25 | V10: =G10 -> 0.55 | W10: 0.02
A11: 2026 | B11: 1 | C11: Aline Castilho Pureza | D11: aline.pureza@altoqi.com.br | E11: Farmer | F11: Consultor | G11: 0.55 | H11: 3240 | I11: =IF(_xlfn.MAXIFS(Metas!J:J,Metas!A:A,A11,Metas!B:B,B11,Metas!D:D,D11) = 0,H11,H11 * (1-_xlfn.MAXIFS(Metas!J:J,Metas!A:A,A11,Metas!B:B,B11,Metas!D:D,D11))) -> 3240 | L11: =IF(_xlfn.MAXIFS(Metas!J:J,Metas!A:A,A11,Metas!B:B,B11,Metas!D:D,D11) = 0,K11,K11 * (1-_xlfn.MAXIFS(Metas!J:J,Metas!A:A,A11,Metas!B:B,B11,Metas!D:D,D11))) -> 0 | O11: =IF(_xlfn.MAXIFS(Metas!J:J,Metas!A:A,A11,Metas!B:B,B11,Metas!D:D,D11) = 0,N11,N11 * (1-_xlfn.MAXIFS(Metas!J:J,Metas!A:A,A11,Metas!B:B,B11,Metas!D:D,D11))) -> 0 | P11: 0.95 | Q11: 1.15 | R11: 1.05 | S11: 1.25 | V11: =G11 -> 0.55 | W11: 0.02
A12: 2026 | B12: 1 | C12: Clidiani Costa | D12: clidiani@altoqi.com.br | E12: Farmer | F12: Consultor | G12: 0.55 | H12: 6480 | I12: =IF(_xlfn.MAXIFS(Metas!J:J,Metas!A:A,A12,Metas!B:B,B12,Metas!D:D,D12) = 0,H12,H12 * (1-_xlfn.MAXIFS(Metas!J:J,Metas!A:A,A12,Metas!B:B,B12,Metas!D:D,D12))) -> 6480 | J12: 1 | K12: 8100 | L12: =IF(_xlfn.MAXIFS(Metas!J:J,Metas!A:A,A12,Metas!B:B,B12,Metas!D:D,D12) = 0,K12,K12 * (1-_xlfn.MAXIFS(Metas!J:J,Metas!A:A,A12,Metas!B:B,B12,Metas!D:D,D12))) -> 8100 | O12: =IF(_xlfn.MAXIFS(Metas!J:J,Metas!A:A,A12,Metas!B:B,B12,Metas!D:D,D12) = 0,N12,N12 * (1-_xlfn.MAXIFS(Metas!J:J,Metas!A:A,A12,Metas!B:B,B12,Metas!D:D,D12))) -> 0 | P12: 0.95 | Q12: 1.15 | R12: 1.05 | S12: 1.25 | V12: =G12 -> 0.55 | W12: 0.02
A13: 2026 | B13: 1 | C13: Debora Vieira | D13: debora.vieira@altoqi.com.br | E13: Farmer | F13: Consultor | G13: 0.55 | H13: 3240 | I13: =IF(_xlfn.MAXIFS(Metas!J:J,Metas!A:A,A13,Metas!B:B,B13,Metas!D:D,D13) = 0,H13,H13 * (1-_xlfn.MAXIFS(Metas!J:J,Metas!A:A,A13,Metas!B:B,B13,Metas!D:D,D13))) -> 1620 | L13: =IF(_xlfn.MAXIFS(Metas!J:J,Metas!A:A,A13,Metas!B:B,B13,Metas!D:D,D13) = 0,K13,K13 * (1-_xlfn.MAXIFS(Metas!J:J,Metas!A:A,A13,Metas!B:B,B13,Metas!D:D,D13))) -> 0 | O13: =IF(_xlfn.MAXIFS(Metas!J:J,Metas!A:A,A13,Metas!B:B,B13,Metas!D:D,D13) = 0,N13,N13 * (1-_xlfn.MAXIFS(Metas!J:J,Metas!A:A,A13,Metas!B:B,B13,Metas!D:D,D13))) -> 0 | P13: 0.95 | Q13: 1.15 | R13: 1.05 | S13: 1.25 | V13: =G13 -> 0.55 | W13: 0.02
A14: 2026 | B14: 1 | C14: Mariana Rachadel | D14: mariana@altoqi.com.br | E14: Farmer | F14: Consultor | G14: 0.55 | H14: 9200 | I14: =IF(_xlfn.MAXIFS(Metas!J:J,Metas!A:A,A14,Metas!B:B,B14,Metas!D:D,D14) = 0,H14,H14 * (1-_xlfn.MAXIFS(Metas!J:J,Metas!A:A,A14,Metas!B:B,B14,Metas!D:D,D14))) -> 9200 | J14: 1 | K14: 11500 | L14: =IF(_xlfn.MAXIFS(Metas!J:J,Metas!A:A,A14,Metas!B:B,B14,Metas!D:D,D14) = 0,K14,K14 * (1-_xlfn.MAXIFS(Metas!J:J,Metas!A:A,A14,Metas!B:B,B14,Metas!D:D,D14))) -> 11500 | O14: =IF(_xlfn.MAXIFS(Metas!J:J,Metas!A:A,A14,Metas!B:B,B14,Metas!D:D,D14) = 0,N14,N14 * (1-_xlfn.MAXIFS(Metas!J:J,Metas!A:A,A14,Metas!B:B,B14,Metas!D:D,D14))) -> 0 | P14: 0.95 | Q14: 1.15 | R14: 1.05 | S14: 1.25 | V14: =G14 -> 0.55 | W14: 0.02
A15: 2026 | B15: 1 | C15: Renata Parizotto | D15: renata.parizotto@altoqi.com.br | E15: Farmer | F15: Consultor | G15: 0.55 | H15: 4176 | I15: =IF(_xlfn.MAXIFS(Metas!J:J,Metas!A:A,A15,Metas!B:B,B15,Metas!D:D,D15) = 0,H15,H15 * (1-_xlfn.MAXIFS(Metas!J:J,Metas!A:A,A15,Metas!B:B,B15,Metas!D:D,D15))) -> 4176 | L15: =IF(_xlfn.MAXIFS(Metas!J:J,Metas!A:A,A15,Metas!B:B,B15,Metas!D:D,D15) = 0,K15,K15 * (1-_xlfn.MAXIFS(Metas!J:J,Metas!A:A,A15,Metas!B:B,B15,Metas!D:D,D15))) -> 0 | O15: =IF(_xlfn.MAXIFS(Metas!J:J,Metas!A:A,A15,Metas!B:B,B15,Metas!D:D,D15) = 0,N15,N15 * (1-_xlfn.MAXIFS(Metas!J:J,Metas!A:A,A15,Metas!B:B,B15,Metas!D:D,D15))) -> 0 | P15: 0.95 | Q15: 1.15 | R15: 1.05 | S15: 1.25 | V15: =G15 -> 0.55 | W15: 0.02
A16: 2026 | B16: 1 | C16: Thales Mariante De Sá | D16: thales.sa@altoqi.com.br | E16: Farmer | F16: Consultor | G16: 0.55 | H16: 3240 | I16: =IF(_xlfn.MAXIFS(Metas!J:J,Metas!A:A,A16,Metas!B:B,B16,Metas!D:D,D16) = 0,H16,H16 * (1-_xlfn.MAXIFS(Metas!J:J,Metas!A:A,A16,Metas!B:B,B16,Metas!D:D,D16))) -> 3240 | L16: =IF(_xlfn.MAXIFS(Metas!J:J,Metas!A:A,A16,Metas!B:B,B16,Metas!D:D,D16) = 0,K16,K16 * (1-_xlfn.MAXIFS(Metas!J:J,Metas!A:A,A16,Metas!B:B,B16,Metas!D:D,D16))) -> 0 | O16: =IF(_xlfn.MAXIFS(Metas!J:J,Metas!A:A,A16,Metas!B:B,B16,Metas!D:D,D16) = 0,N16,N16 * (1-_xlfn.MAXIFS(Metas!J:J,Metas!A:A,A16,Metas!B:B,B16,Metas!D:D,D16))) -> 0 | P16: 0.95 | Q16: 1.15 | R16: 1.05 | S16: 1.25 | V16: =G16 -> 0.55 | W16: 0.02
A17: 2026 | B17: 1 | C17: Artur Machado | D17: artur.francisco@altoqi.com.br | E17: FSB | F17: Consultor | G17: 0.6 | H17: 3240 | I17: =IF(_xlfn.MAXIFS(Metas!J:J,Metas!A:A,A17,Metas!B:B,B17,Metas!D:D,D17) = 0,H17,H17 * (1-_xlfn.MAXIFS(Metas!J:J,Metas!A:A,A17,Metas!B:B,B17,Metas!D:D,D17))) -> 3240 | L17: =IF(_xlfn.MAXIFS(Metas!J:J,Metas!A:A,A17,Metas!B:B,B17,Metas!D:D,D17) = 0,K17,K17 * (1-_xlfn.MAXIFS(Metas!J:J,Metas!A:A,A17,Metas!B:B,B17,Metas!D:D,D17))) -> 0 | O17: =IF(_xlfn.MAXIFS(Metas!J:J,Metas!A:A,A17,Metas!B:B,B17,Metas!D:D,D17) = 0,N17,N17 * (1-_xlfn.MAXIFS(Metas!J:J,Metas!A:A,A17,Metas!B:B,B17,Metas!D:D,D17))) -> 0 | P17: 0.95 | Q17: 1.15 | R17: 1.05 | S17: 1.25 | V17: =G17 -> 0.6 | W17: 0.02
A18: 2026 | B18: 1 | C18: Eliane Guinther | D18: eliane.guinther@altoqi.com.br | E18: FSB | F18: Consultor | G18: 0.6 | H18: 3240 | I18: =IF(_xlfn.MAXIFS(Metas!J:J,Metas!A:A,A18,Metas!B:B,B18,Metas!D:D,D18) = 0,H18,H18 * (1-_xlfn.MAXIFS(Metas!J:J,Metas!A:A,A18,Metas!B:B,B18,Metas!D:D,D18))) -> 3240 | L18: =IF(_xlfn.MAXIFS(Metas!J:J,Metas!A:A,A18,Metas!B:B,B18,Metas!D:D,D18) = 0,K18,K18 * (1-_xlfn.MAXIFS(Metas!J:J,Metas!A:A,A18,Metas!B:B,B18,Metas!D:D,D18))) -> 0 | O18: =IF(_xlfn.MAXIFS(Metas!J:J,Metas!A:A,A18,Metas!B:B,B18,Metas!D:D,D18) = 0,N18,N18 * (1-_xlfn.MAXIFS(Metas!J:J,Metas!A:A,A18,Metas!B:B,B18,Metas!D:D,D18))) -> 0 | P18: 0.95 | Q18: 1.15 | R18: 1.05 | S18: 1.25 | V18: =G18 -> 0.6 | W18: 0.02
A19: 2026 | B19: 1 | C19: Renata Scheffer | D19: renata.scheffer@altoqi.com.br | E19: FSB | F19: Consultor | G19: 0.6 | H19: 3240 | I19: =IF(_xlfn.MAXIFS(Metas!J:J,Metas!A:A,A19,Metas!B:B,B19,Metas!D:D,D19,Metas!E:E,E19) = 0,H19,H19 * (1-_xlfn.MAXIFS(Metas!J:J,Metas!A:A,A19,Metas!B:B,B19,Metas!D:D,D19,Metas!E:E,E19))) -> 2073.6 | L19: =IF(_xlfn.MAXIFS(Metas!J:J,Metas!A:A,A19,Metas!B:B,B19,Metas!D:D,D19) = 0,K19,K19 * (1-_xlfn.MAXIFS(Metas!J:J,Metas!A:A,A19,Metas!B:B,B19,Metas!D:D,D19))) -> 0 | O19: =IF(_xlfn.MAXIFS(Metas!J:J,Metas!A:A,A19,Metas!B:B,B19,Metas!D:D,D19) = 0,N19,N19 * (1-_xlfn.MAXIFS(Metas!J:J,Metas!A:A,A19,Metas!B:B,B19,Metas!D:D,D19))) -> 0 | P19: 0.95 | Q19: 1.15 | R19: 1.05 | S19: 1.25 | V19: =G19 -> 0.6 | W19: 0.02
A20: 2026 | B20: 1 | C20: Susana Alves Becker | D20: susana.becker@altoqi.com.br | E20: FSB | F20: Consultor | G20: 0.6 | H20: 3960 | I20: =IF(_xlfn.MAXIFS(Metas!J:J,Metas!A:A,A20,Metas!B:B,B20,Metas!D:D,D20) = 0,H20,H20 * (1-_xlfn.MAXIFS(Metas!J:J,Metas!A:A,A20,Metas!B:B,B20,Metas!D:D,D20))) -> 3960 | L20: =IF(_xlfn.MAXIFS(Metas!J:J,Metas!A:A,A20,Metas!B:B,B20,Metas!D:D,D20) = 0,K20,K20 * (1-_xlfn.MAXIFS(Metas!J:J,Metas!A:A,A20,Metas!B:B,B20,Metas!D:D,D20))) -> 0 | O20: =IF(_xlfn.MAXIFS(Metas!J:J,Metas!A:A,A20,Metas!B:B,B20,Metas!D:D,D20) = 0,N20,N20 * (1-_xlfn.MAXIFS(Metas!J:J,Metas!A:A,A20,Metas!B:B,B20,Metas!D:D,D20))) -> 0 | P20: 0.95 | Q20: 1.15 | R20: 1.05 | S20: 1.25 | V20: =G20 -> 0.6 | W20: 0.02
A21: 2026 | B21: 1 | C21: Ana Camargo | D21: ana.camargo@altoqi.com.br | E21: GD | F21: Consultor | G21: 0.7 | H21: 1500 | I21: =IF(_xlfn.MAXIFS(Metas!J:J,Metas!A:A,A21,Metas!B:B,B21,Metas!D:D,D21) = 0,H21,H21 * (1-_xlfn.MAXIFS(Metas!J:J,Metas!A:A,A21,Metas!B:B,B21,Metas!D:D,D21))) -> 1125 | L21: =IF(_xlfn.MAXIFS(Metas!J:J,Metas!A:A,A21,Metas!B:B,B21,Metas!D:D,D21) = 0,K21,K21 * (1-_xlfn.MAXIFS(Metas!J:J,Metas!A:A,A21,Metas!B:B,B21,Metas!D:D,D21))) -> 0 | O21: =IF(_xlfn.MAXIFS(Metas!J:J,Metas!A:A,A21,Metas!B:B,B21,Metas!D:D,D21) = 0,N21,N21 * (1-_xlfn.MAXIFS(Metas!J:J,Metas!A:A,A21,Metas!B:B,B21,Metas!D:D,D21))) -> 0 | P21: 0.9 | Q21: 1.15 | R21: 1 | S21: 1.25
A22: 2026 | B22: 1 | C22: Anand Freitas Figueiredo | D22: anand.figueiredo@altoqi.com.br | E22: GD | F22: Consultor | G22: 0.5 | H22: 1800 | I22: =IF(_xlfn.MAXIFS(Metas!J:J,Metas!A:A,A22,Metas!B:B,B22,Metas!D:D,D22) = 0,H22,H22 * (1-_xlfn.MAXIFS(Metas!J:J,Metas!A:A,A22,Metas!B:B,B22,Metas!D:D,D22))) -> 1800 | L22: =IF(_xlfn.MAXIFS(Metas!J:J,Metas!A:A,A22,Metas!B:B,B22,Metas!D:D,D22) = 0,K22,K22 * (1-_xlfn.MAXIFS(Metas!J:J,Metas!A:A,A22,Metas!B:B,B22,Metas!D:D,D22))) -> 0 | O22: =IF(_xlfn.MAXIFS(Metas!J:J,Metas!A:A,A22,Metas!B:B,B22,Metas!D:D,D22) = 0,N22,N22 * (1-_xlfn.MAXIFS(Metas!J:J,Metas!A:A,A22,Metas!B:B,B22,Metas!D:D,D22))) -> 0 | P22: 0.75 | Q22: 1.15 | R22: 0.9 | S22: 1.25
A23: 2026 | B23: 1 | C23: André Cardoso | D23: andre.cardoso@altoqi.com.br | E23: GD | F23: Gestor | G23: 0.7 | H23: 3200 | I23: =IF(_xlfn.MAXIFS(Metas!J:J,Metas!A:A,A23,Metas!B:B,B23,Metas!D:D,D23) = 0,H23,H23 * (1-_xlfn.MAXIFS(Metas!J:J,Metas!A:A,A23,Metas!B:B,B23,Metas!D:D,D23))) -> 3200 | L23: =IF(_xlfn.MAXIFS(Metas!J:J,Metas!A:A,A23,Metas!B:B,B23,Metas!D:D,D23) = 0,K23,K23 * (1-_xlfn.MAXIFS(Metas!J:J,Metas!A:A,A23,Metas!B:B,B23,Metas!D:D,D23))) -> 0 | O23: =IF(_xlfn.MAXIFS(Metas!J:J,Metas!A:A,A23,Metas!B:B,B23,Metas!D:D,D23) = 0,N23,N23 * (1-_xlfn.MAXIFS(Metas!J:J,Metas!A:A,A23,Metas!B:B,B23,Metas!D:D,D23))) -> 0 | P23: 0.9 | Q23: 1.15 | R23: 1 | S23: 1.25
A24: 2026 | B24: 1 | C24: Arthur Treivisol | D24: arthur.trevisiol@altoqi.com.br | E24: GD | F24: Consultor | G24: 0.7 | H24: 1500 | I24: =IF(_xlfn.MAXIFS(Metas!J:J,Metas!A:A,A24,Metas!B:B,B24,Metas!D:D,D24) = 0,H24,H24 * (1-_xlfn.MAXIFS(Metas!J:J,Metas!A:A,A24,Metas!B:B,B24,Metas!D:D,D24))) -> 1500 | L24: =IF(_xlfn.MAXIFS(Metas!J:J,Metas!A:A,A24,Metas!B:B,B24,Metas!D:D,D24) = 0,K24,K24 * (1-_xlfn.MAXIFS(Metas!J:J,Metas!A:A,A24,Metas!B:B,B24,Metas!D:D,D24))) -> 0 | O24: =IF(_xlfn.MAXIFS(Metas!J:J,Metas!A:A,A24,Metas!B:B,B24,Metas!D:D,D24) = 0,N24,N24 * (1-_xlfn.MAXIFS(Metas!J:J,Metas!A:A,A24,Metas!B:B,B24,Metas!D:D,D24))) -> 0 | P24: 0.9 | Q24: 1.15 | R24: 1 | S24: 1.25
A25: 2026 | B25: 1 | C25: Elisa Nickel Costa | D25: elisa.costa@altoqi.com.br | E25: GD | F25: Consultor | G25: 0.7 | H25: 1500 | I25: =IF(_xlfn.MAXIFS(Metas!J:J,Metas!A:A,A25,Metas!B:B,B25,Metas!D:D,D25) = 0,H25,H25 * (1-_xlfn.MAXIFS(Metas!J:J,Metas!A:A,A25,Metas!B:B,B25,Metas!D:D,D25))) -> 1500 | L25: =IF(_xlfn.MAXIFS(Metas!J:J,Metas!A:A,A25,Metas!B:B,B25,Metas!D:D,D25) = 0,K25,K25 * (1-_xlfn.MAXIFS(Metas!J:J,Metas!A:A,A25,Metas!B:B,B25,Metas!D:D,D25))) -> 0 | O25: =IF(_xlfn.MAXIFS(Metas!J:J,Metas!A:A,A25,Metas!B:B,B25,Metas!D:D,D25) = 0,N25,N25 * (1-_xlfn.MAXIFS(Metas!J:J,Metas!A:A,A25,Metas!B:B,B25,Metas!D:D,D25))) -> 0 | P25: 0.9 | Q25: 1.15 | R25: 1 | S25: 1.25
A26: 2026 | B26: 1 | C26: Luiz Arthur Falcão Senna | D26: luiz.senna@altoqi.com.br | E26: GD | F26: Consultor | G26: 0.7 | H26: 1800 | I26: =IF(_xlfn.MAXIFS(Metas!J:J,Metas!A:A,A26,Metas!B:B,B26,Metas!D:D,D26) = 0,H26,H26 * (1-_xlfn.MAXIFS(Metas!J:J,Metas!A:A,A26,Metas!B:B,B26,Metas!D:D,D26))) -> 1800 | L26: =IF(_xlfn.MAXIFS(Metas!J:J,Metas!A:A,A26,Metas!B:B,B26,Metas!D:D,D26) = 0,K26,K26 * (1-_xlfn.MAXIFS(Metas!J:J,Metas!A:A,A26,Metas!B:B,B26,Metas!D:D,D26))) -> 0 | O26: =IF(_xlfn.MAXIFS(Metas!J:J,Metas!A:A,A26,Metas!B:B,B26,Metas!D:D,D26) = 0,N26,N26 * (1-_xlfn.MAXIFS(Metas!J:J,Metas!A:A,A26,Metas!B:B,B26,Metas!D:D,D26))) -> 0 | P26: 0.9 | Q26: 1.15 | R26: 1 | S26: 1.25
A27: 2026 | B27: 1 | C27: Matheus Fiebig | D27: matheus.lima@altoqi.com.br | E27: GD | F27: Consultor | G27: 0.7 | H27: 1500 | I27: =IF(_xlfn.MAXIFS(Metas!J:J,Metas!A:A,A27,Metas!B:B,B27,Metas!D:D,D27) = 0,H27,H27 * (1-_xlfn.MAXIFS(Metas!J:J,Metas!A:A,A27,Metas!B:B,B27,Metas!D:D,D27))) -> 1500 | L27: =IF(_xlfn.MAXIFS(Metas!J:J,Metas!A:A,A27,Metas!B:B,B27,Metas!D:D,D27) = 0,K27,K27 * (1-_xlfn.MAXIFS(Metas!J:J,Metas!A:A,A27,Metas!B:B,B27,Metas!D:D,D27))) -> 0 | O27: =IF(_xlfn.MAXIFS(Metas!J:J,Metas!A:A,A27,Metas!B:B,B27,Metas!D:D,D27) = 0,N27,N27 * (1-_xlfn.MAXIFS(Metas!J:J,Metas!A:A,A27,Metas!B:B,B27,Metas!D:D,D27))) -> 0 | P27: 0.9 | Q27: 1.15 | R27: 1 | S27: 1.25
A28: 2026 | B28: 1 | C28: Renata Scheffer | D28: renata.scheffer@altoqi.com.br | E28: GD | F28: Consultor | G28: 0.7 | H28: 1500 | I28: =IF(_xlfn.MAXIFS(Metas!J:J,Metas!A:A,A28,Metas!B:B,B28,Metas!D:D,D28,Metas!E:E,E28) = 0,H28,H28 * (1-_xlfn.MAXIFS(Metas!J:J,Metas!A:A,A28,Metas!B:B,B28,Metas!D:D,D28,Metas!E:E,E28))) -> 630 | L28: =IF(_xlfn.MAXIFS(Metas!J:J,Metas!A:A,A28,Metas!B:B,B28,Metas!D:D,D28) = 0,K28,K28 * (1-_xlfn.MAXIFS(Metas!J:J,Metas!A:A,A28,Metas!B:B,B28,Metas!D:D,D28))) -> 0 | O28: =IF(_xlfn.MAXIFS(Metas!J:J,Metas!A:A,A28,Metas!B:B,B28,Metas!D:D,D28) = 0,N28,N28 * (1-_xlfn.MAXIFS(Metas!J:J,Metas!A:A,A28,Metas!B:B,B28,Metas!D:D,D28))) -> 0 | P28: 0.9 | Q28: 1.15 | R28: 1 | S28: 1.25
A29: 2026 | B29: 1 | C29: Sarai Daniela | D29: daniela.cabrera@altoqi.com.br | E29: GD | F29: Consultor | G29: 0.5 | H29: 1800 | I29: =IF(_xlfn.MAXIFS(Metas!J:J,Metas!A:A,A29,Metas!B:B,B29,Metas!D:D,D29) = 0,H29,H29 * (1-_xlfn.MAXIFS(Metas!J:J,Metas!A:A,A29,Metas!B:B,B29,Metas!D:D,D29))) -> 1800 | L29: =IF(_xlfn.MAXIFS(Metas!J:J,Metas!A:A,A29,Metas!B:B,B29,Metas!D:D,D29) = 0,K29,K29 * (1-_xlfn.MAXIFS(Metas!J:J,Metas!A:A,A29,Metas!B:B,B29,Metas!D:D,D29))) -> 0 | O29: =IF(_xlfn.MAXIFS(Metas!J:J,Metas!A:A,A29,Metas!B:B,B29,Metas!D:D,D29) = 0,N29,N29 * (1-_xlfn.MAXIFS(Metas!J:J,Metas!A:A,A29,Metas!B:B,B29,Metas!D:D,D29))) -> 0 | P29: 0.75 | Q29: 1.15 | R29: 0.9 | S29: 1.25
A30: 2026 | B30: 1 | C30: Angélica da Silva Steinbach | D30: angelica.steinbach@altoqi.com.br | E30: Governo | F30: Consultor | G30: 0.5 | H30: 8000 | I30: =IF(_xlfn.MAXIFS(Metas!J:J,Metas!A:A,A30,Metas!B:B,B30,Metas!D:D,D30) = 0,H30,H30 * (1-_xlfn.MAXIFS(Metas!J:J,Metas!A:A,A30,Metas!B:B,B30,Metas!D:D,D30))) -> 8000 | L30: =IF(_xlfn.MAXIFS(Metas!J:J,Metas!A:A,A30,Metas!B:B,B30,Metas!D:D,D30) = 0,K30,K30 * (1-_xlfn.MAXIFS(Metas!J:J,Metas!A:A,A30,Metas!B:B,B30,Metas!D:D,D30))) -> 0 | O30: =IF(_xlfn.MAXIFS(Metas!J:J,Metas!A:A,A30,Metas!B:B,B30,Metas!D:D,D30) = 0,N30,N30 * (1-_xlfn.MAXIFS(Metas!J:J,Metas!A:A,A30,Metas!B:B,B30,Metas!D:D,D30))) -> 0 | P30: 0.75 | Q30: 1.15 | R30: 0.9 | S30: 1.25
A31: 2026 | B31: 1 | C31: Carla Araujo | D31: carla.araujo@altoqi.com.br | E31: Governo | F31: Consultor | G31: 0.5 | H31: 6800 | I31: =IF(_xlfn.MAXIFS(Metas!J:J,Metas!A:A,A31,Metas!B:B,B31,Metas!D:D,D31) = 0,H31,H31 * (1-_xlfn.MAXIFS(Metas!J:J,Metas!A:A,A31,Metas!B:B,B31,Metas!D:D,D31))) -> 6800 | L31: =IF(_xlfn.MAXIFS(Metas!J:J,Metas!A:A,A31,Metas!B:B,B31,Metas!D:D,D31) = 0,K31,K31 * (1-_xlfn.MAXIFS(Metas!J:J,Metas!A:A,A31,Metas!B:B,B31,Metas!D:D,D31))) -> 0 | O31: =IF(_xlfn.MAXIFS(Metas!J:J,Metas!A:A,A31,Metas!B:B,B31,Metas!D:D,D31) = 0,N31,N31 * (1-_xlfn.MAXIFS(Metas!J:J,Metas!A:A,A31,Metas!B:B,B31,Metas!D:D,D31))) -> 0 | P31: 0.75 | Q31: 1.15 | R31: 0.9 | S31: 1.25
A32: 2026 | B32: 1 | C32: Deize Marla Rudek | D32: deize.rudek@altoqi.com.br | E32: Governo | F32: Consultor | G32: 0.5 | H32: 5600 | I32: =IF(_xlfn.MAXIFS(Metas!J:J,Metas!A:A,A32,Metas!B:B,B32,Metas!D:D,D32) = 0,H32,H32 * (1-_xlfn.MAXIFS(Metas!J:J,Metas!A:A,A32,Metas!B:B,B32,Metas!D:D,D32))) -> 5600 | L32: =IF(_xlfn.MAXIFS(Metas!J:J,Metas!A:A,A32,Metas!B:B,B32,Metas!D:D,D32) = 0,K32,K32 * (1-_xlfn.MAXIFS(Metas!J:J,Metas!A:A,A32,Metas!B:B,B32,Metas!D:D,D32))) -> 0 | O32: =IF(_xlfn.MAXIFS(Metas!J:J,Metas!A:A,A32,Metas!B:B,B32,Metas!D:D,D32) = 0,N32,N32 * (1-_xlfn.MAXIFS(Metas!J:J,Metas!A:A,A32,Metas!B:B,B32,Metas!D:D,D32))) -> 0 | P32: 0.75 | Q32: 1.15 | R32: 0.9 | S32: 1.25
A33: 2026 | B33: 1 | C33: Fernanda Cristina Barbosa | D33: fernanda.barbosa@altoqi.com.br | E33: Governo | F33: Consultor | G33: 0.5 | H33: 5600 | I33: =IF(_xlfn.MAXIFS(Metas!J:J,Metas!A:A,A33,Metas!B:B,B33,Metas!D:D,D33) = 0,H33,H33 * (1-_xlfn.MAXIFS(Metas!J:J,Metas!A:A,A33,Metas!B:B,B33,Metas!D:D,D33))) -> 5600 | L33: =IF(_xlfn.MAXIFS(Metas!J:J,Metas!A:A,A33,Metas!B:B,B33,Metas!D:D,D33) = 0,K33,K33 * (1-_xlfn.MAXIFS(Metas!J:J,Metas!A:A,A33,Metas!B:B,B33,Metas!D:D,D33))) -> 0 | O33: =IF(_xlfn.MAXIFS(Metas!J:J,Metas!A:A,A33,Metas!B:B,B33,Metas!D:D,D33) = 0,N33,N33 * (1-_xlfn.MAXIFS(Metas!J:J,Metas!A:A,A33,Metas!B:B,B33,Metas!D:D,D33))) -> 0 | P33: 0.75 | Q33: 1.15 | R33: 0.9 | S33: 1.25
A34: 2026 | B34: 1 | C34: Henry Carlos Petersen | D34: henry.petersen@altoqi.com.br | E34: Governo | F34: Consultor | G34: 0.5 | H34: 10000 | I34: =IF(_xlfn.MAXIFS(Metas!J:J,Metas!A:A,A34,Metas!B:B,B34,Metas!D:D,D34) = 0,H34,H34 * (1-_xlfn.MAXIFS(Metas!J:J,Metas!A:A,A34,Metas!B:B,B34,Metas!D:D,D34))) -> 10000 | L34: =IF(_xlfn.MAXIFS(Metas!J:J,Metas!A:A,A34,Metas!B:B,B34,Metas!D:D,D34) = 0,K34,K34 * (1-_xlfn.MAXIFS(Metas!J:J,Metas!A:A,A34,Metas!B:B,B34,Metas!D:D,D34))) -> 0 | O34: =IF(_xlfn.MAXIFS(Metas!J:J,Metas!A:A,A34,Metas!B:B,B34,Metas!D:D,D34) = 0,N34,N34 * (1-_xlfn.MAXIFS(Metas!J:J,Metas!A:A,A34,Metas!B:B,B34,Metas!D:D,D34))) -> 0 | P34: 0.75 | Q34: 1.15 | R34: 0.9 | S34: 1.25
A35: 2026 | B35: 1 | C35: Jenifer das Dores Soares | D35: jenifer.soares@altoqi.com.br | E35: Governo | F35: Consultor | G35: 0.5 | H35: 3456 | I35: =IF(_xlfn.MAXIFS(Metas!J:J,Metas!A:A,A35,Metas!B:B,B35,Metas!D:D,D35) = 0,H35,H35 * (1-_xlfn.MAXIFS(Metas!J:J,Metas!A:A,A35,Metas!B:B,B35,Metas!D:D,D35))) -> 3456 | L35: =IF(_xlfn.MAXIFS(Metas!J:J,Metas!A:A,A35,Metas!B:B,B35,Metas!D:D,D35) = 0,K35,K35 * (1-_xlfn.MAXIFS(Metas!J:J,Metas!A:A,A35,Metas!B:B,B35,Metas!D:D,D35))) -> 0 | O35: =IF(_xlfn.MAXIFS(Metas!J:J,Metas!A:A,A35,Metas!B:B,B35,Metas!D:D,D35) = 0,N35,N35 * (1-_xlfn.MAXIFS(Metas!J:J,Metas!A:A,A35,Metas!B:B,B35,Metas!D:D,D35))) -> 0 | P35: 0.75 | Q35: 1.15 | R35: 0.9 | S35: 1.25
A36: 2026 | B36: 1 | C36: Jordayn Almeida | D36: jordayn.almeida@altoqi.com.br | E36: Governo | F36: Consultor | G36: 0.5 | H36: 10000 | I36: =IF(_xlfn.MAXIFS(Metas!J:J,Metas!A:A,A36,Metas!B:B,B36,Metas!D:D,D36) = 0,H36,H36 * (1-_xlfn.MAXIFS(Metas!J:J,Metas!A:A,A36,Metas!B:B,B36,Metas!D:D,D36))) -> 10000 | L36: =IF(_xlfn.MAXIFS(Metas!J:J,Metas!A:A,A36,Metas!B:B,B36,Metas!D:D,D36) = 0,K36,K36 * (1-_xlfn.MAXIFS(Metas!J:J,Metas!A:A,A36,Metas!B:B,B36,Metas!D:D,D36))) -> 0 | O36: =IF(_xlfn.MAXIFS(Metas!J:J,Metas!A:A,A36,Metas!B:B,B36,Metas!D:D,D36) = 0,N36,N36 * (1-_xlfn.MAXIFS(Metas!J:J,Metas!A:A,A36,Metas!B:B,B36,Metas!D:D,D36))) -> 0 | P36: 0.75 | Q36: 1.15 | R36: 0.9 | S36: 1.25
A37: 2026 | B37: 1 | C37: Leandro Fontana da Silva | D37: leandro.fontana@altoqi.com.br | E37: Governo | F37: Consultor | G37: 0.5 | H37: 8000 | I37: =IF(_xlfn.MAXIFS(Metas!J:J,Metas!A:A,A37,Metas!B:B,B37,Metas!D:D,D37) = 0,H37,H37 * (1-_xlfn.MAXIFS(Metas!J:J,Metas!A:A,A37,Metas!B:B,B37,Metas!D:D,D37))) -> 8000 | L37: =IF(_xlfn.MAXIFS(Metas!J:J,Metas!A:A,A37,Metas!B:B,B37,Metas!D:D,D37) = 0,K37,K37 * (1-_xlfn.MAXIFS(Metas!J:J,Metas!A:A,A37,Metas!B:B,B37,Metas!D:D,D37))) -> 0 | O37: =IF(_xlfn.MAXIFS(Metas!J:J,Metas!A:A,A37,Metas!B:B,B37,Metas!D:D,D37) = 0,N37,N37 * (1-_xlfn.MAXIFS(Metas!J:J,Metas!A:A,A37,Metas!B:B,B37,Metas!D:D,D37))) -> 0 | P37: 0.75 | Q37: 1.15 | R37: 0.9 | S37: 1.25
A38: 2026 | B38: 1 | C38: Marcelo Maestro | D38: marcelo.maestro@altoqi.com.br | E38: Governo | F38: Gestor | G38: 0.39 | H38: 11500 | I38: =IF(_xlfn.MAXIFS(Metas!J:J,Metas!A:A,A38,Metas!B:B,B38,Metas!D:D,D38) = 0,H38,H38 * (1-_xlfn.MAXIFS(Metas!J:J,Metas!A:A,A38,Metas!B:B,B38,Metas!D:D,D38))) -> 11500 | L38: =IF(_xlfn.MAXIFS(Metas!J:J,Metas!A:A,A38,Metas!B:B,B38,Metas!D:D,D38) = 0,K38,K38 * (1-_xlfn.MAXIFS(Metas!J:J,Metas!A:A,A38,Metas!B:B,B38,Metas!D:D,D38))) -> 0 | O38: =IF(_xlfn.MAXIFS(Metas!J:J,Metas!A:A,A38,Metas!B:B,B38,Metas!D:D,D38) = 0,N38,N38 * (1-_xlfn.MAXIFS(Metas!J:J,Metas!A:A,A38,Metas!B:B,B38,Metas!D:D,D38))) -> 0 | P38: 0.75 | Q38: 1.15 | R38: 0.9 | S38: 1.25
A39: 2026 | B39: 1 | C39: Nathan Alves | D39: nathan.alves@altoqi.com.br | E39: Governo | F39: Consultor | G39: 0.5 | H39: 6800 | I39: =IF(_xlfn.MAXIFS(Metas!J:J,Metas!A:A,A39,Metas!B:B,B39,Metas!D:D,D39) = 0,H39,H39 * (1-_xlfn.MAXIFS(Metas!J:J,Metas!A:A,A39,Metas!B:B,B39,Metas!D:D,D39))) -> 6800 | L39: =IF(_xlfn.MAXIFS(Metas!J:J,Metas!A:A,A39,Metas!B:B,B39,Metas!D:D,D39) = 0,K39,K39 * (1-_xlfn.MAXIFS(Metas!J:J,Metas!A:A,A39,Metas!B:B,B39,Metas!D:D,D39))) -> 0 | O39: =IF(_xlfn.MAXIFS(Metas!J:J,Metas!A:A,A39,Metas!B:B,B39,Metas!D:D,D39) = 0,N39,N39 * (1-_xlfn.MAXIFS(Metas!J:J,Metas!A:A,A39,Metas!B:B,B39,Metas!D:D,D39))) -> 0 | P39: 0.75 | Q39: 1.15 | R39: 0.9 | S39: 1.25
A40: 2026 | B40: 1 | C40: Soraia Fronchetti | D40: soraia@altoqi.com.br | E40: Governo | F40: Consultor | G40: 0.5 | H40: 9200 | I40: =IF(_xlfn.MAXIFS(Metas!J:J,Metas!A:A,A40,Metas!B:B,B40,Metas!D:D,D40) = 0,H40,H40 * (1-_xlfn.MAXIFS(Metas!J:J,Metas!A:A,A40,Metas!B:B,B40,Metas!D:D,D40))) -> 9200 | L40: =IF(_xlfn.MAXIFS(Metas!J:J,Metas!A:A,A40,Metas!B:B,B40,Metas!D:D,D40) = 0,K40,K40 * (1-_xlfn.MAXIFS(Metas!J:J,Metas!A:A,A40,Metas!B:B,B40,Metas!D:D,D40))) -> 0 | O40: =IF(_xlfn.MAXIFS(Metas!J:J,Metas!A:A,A40,Metas!B:B,B40,Metas!D:D,D40) = 0,N40,N40 * (1-_xlfn.MAXIFS(Metas!J:J,Metas!A:A,A40,Metas!B:B,B40,Metas!D:D,D40))) -> 0 | P40: 0.75 | Q40: 1.15 | R40: 0.9 | S40: 1.25
A41: 2026 | B41: 1 | C41: Tabata Couto | D41: tabata.couto@altoqi.com.br | E41: Governo | F41: Consultor | G41: 0.5 | H41: 5600 | I41: =IF(_xlfn.MAXIFS(Metas!J:J,Metas!A:A,A41,Metas!B:B,B41,Metas!D:D,D41) = 0,H41,H41 * (1-_xlfn.MAXIFS(Metas!J:J,Metas!A:A,A41,Metas!B:B,B41,Metas!D:D,D41))) -> 5600 | L41: =IF(_xlfn.MAXIFS(Metas!J:J,Metas!A:A,A41,Metas!B:B,B41,Metas!D:D,D41) = 0,K41,K41 * (1-_xlfn.MAXIFS(Metas!J:J,Metas!A:A,A41,Metas!B:B,B41,Metas!D:D,D41))) -> 0 | O41: =IF(_xlfn.MAXIFS(Metas!J:J,Metas!A:A,A41,Metas!B:B,B41,Metas!D:D,D41) = 0,N41,N41 * (1-_xlfn.MAXIFS(Metas!J:J,Metas!A:A,A41,Metas!B:B,B41,Metas!D:D,D41))) -> 0 | P41: 0.75 | Q41: 1.15 | R41: 0.9 | S41: 1.25
A42: 2026 | B42: 1 | C42: Beatriz Nau | D42: beatriz@altoqi.com.br | E42: Saving | F42: Gestor | G42: 0.6 | H42: 2400 | I42: =IF(_xlfn.MAXIFS(Metas!J:J,Metas!A:A,A42,Metas!B:B,B42,Metas!D:D,D42) = 0,H42,H42 * (1-_xlfn.MAXIFS(Metas!J:J,Metas!A:A,A42,Metas!B:B,B42,Metas!D:D,D42))) -> 2400 | J42: 0.75 | K42: 9600 | L42: =IF(_xlfn.MAXIFS(Metas!J:J,Metas!A:A,A42,Metas!B:B,B42,Metas!D:D,D42) = 0,K42,K42 * (1-_xlfn.MAXIFS(Metas!J:J,Metas!A:A,A42,Metas!B:B,B42,Metas!D:D,D42))) -> 9600 | M42: 1 | N42: 12000 | O42: =IF(_xlfn.MAXIFS(Metas!J:J,Metas!A:A,A42,Metas!B:B,B42,Metas!D:D,D42) = 0,N42,N42 * (1-_xlfn.MAXIFS(Metas!J:J,Metas!A:A,A42,Metas!B:B,B42,Metas!D:D,D42))) -> 12000 | P42: 1 | Q42: 1.05 | R42: 1.1 | S42: 1.1 | V42: =J42 -> 0.75 | W42: 0.01
A43: 2026 | B43: 1 | C43: Cintia Faraco | D43: cintia@altoqi.com.br | E43: Saving | F43: Consultor | G43: 0.6 | H43: 1620 | I43: =IF(_xlfn.MAXIFS(Metas!J:J,Metas!A:A,A43,Metas!B:B,B43,Metas!D:D,D43) = 0,H43,H43 * (1-_xlfn.MAXIFS(Metas!J:J,Metas!A:A,A43,Metas!B:B,B43,Metas!D:D,D43))) -> 1620 | J43: 0.75 | K43: 6480 | L43: =IF(_xlfn.MAXIFS(Metas!J:J,Metas!A:A,A43,Metas!B:B,B43,Metas!D:D,D43) = 0,K43,K43 * (1-_xlfn.MAXIFS(Metas!J:J,Metas!A:A,A43,Metas!B:B,B43,Metas!D:D,D43))) -> 6480 | M43: 1 | N43: 8100 | O43: =IF(_xlfn.MAXIFS(Metas!J:J,Metas!A:A,A43,Metas!B:B,B43,Metas!D:D,D43) = 0,N43,N43 * (1-_xlfn.MAXIFS(Metas!J:J,Metas!A:A,A43,Metas!B:B,B43,Metas!D:D,D43))) -> 8100 | P43: 1 | Q43: 1.05 | R43: 1.1 | S43: 1.1 | V43: =J43 -> 0.75 | W43: 0.01
A44: 2026 | B44: 1 | C44: Francyellen Batista | D44: francyellen@altoqi.com.br | E44: Saving | F44: Consultor | G44: 0.6 | H44: 1080 | I44: =IF(_xlfn.MAXIFS(Metas!J:J,Metas!A:A,A44,Metas!B:B,B44,Metas!D:D,D44) = 0,H44,H44 * (1-_xlfn.MAXIFS(Metas!J:J,Metas!A:A,A44,Metas!B:B,B44,Metas!D:D,D44))) -> 1080 | J44: 0.75 | K44: 4320 | L44: =IF(_xlfn.MAXIFS(Metas!J:J,Metas!A:A,A44,Metas!B:B,B44,Metas!D:D,D44) = 0,K44,K44 * (1-_xlfn.MAXIFS(Metas!J:J,Metas!A:A,A44,Metas!B:B,B44,Metas!D:D,D44))) -> 4320 | M44: 1 | N44: 5400 | O44: =IF(_xlfn.MAXIFS(Metas!J:J,Metas!A:A,A44,Metas!B:B,B44,Metas!D:D,D44) = 0,N44,N44 * (1-_xlfn.MAXIFS(Metas!J:J,Metas!A:A,A44,Metas!B:B,B44,Metas!D:D,D44))) -> 5400 | P44: 1 | Q44: 1.05 | R44: 1.1 | S44: 1.1 | V44: =J44 -> 0.75 | W44: 0.01
A45: 2026 | B45: 1 | C45: Jaqueline Correa | D45: jaqueline.correa@altoqi.com.br | E45: Saving | F45: Consultor | G45: 0.6 | H45: 1080 | I45: =IF(_xlfn.MAXIFS(Metas!J:J,Metas!A:A,A45,Metas!B:B,B45,Metas!D:D,D45) = 0,H45,H45 * (1-_xlfn.MAXIFS(Metas!J:J,Metas!A:A,A45,Metas!B:B,B45,Metas!D:D,D45))) -> 1080 | J45: 0.75 | K45: 4320 | L45: =IF(_xlfn.MAXIFS(Metas!J:J,Metas!A:A,A45,Metas!B:B,B45,Metas!D:D,D45) = 0,K45,K45 * (1-_xlfn.MAXIFS(Metas!J:J,Metas!A:A,A45,Metas!B:B,B45,Metas!D:D,D45))) -> 4320 | M45: 1 | N45: 5400 | O45: =IF(_xlfn.MAXIFS(Metas!J:J,Metas!A:A,A45,Metas!B:B,B45,Metas!D:D,D45) = 0,N45,N45 * (1-_xlfn.MAXIFS(Metas!J:J,Metas!A:A,A45,Metas!B:B,B45,Metas!D:D,D45))) -> 5400 | P45: 1 | Q45: 1.05 | R45: 1.1 | S45: 1.1 | V45: =J45 -> 0.75 | W45: 0.01
A46: 2026 | B46: 1 | C46: Marcela Accacio | D46: marcela@altoqi.com.br | E46: Saving | F46: Consultor | G46: 0.6 | H46: 1620 | I46: =IF(_xlfn.MAXIFS(Metas!J:J,Metas!A:A,A46,Metas!B:B,B46,Metas!D:D,D46) = 0,H46,H46 * (1-_xlfn.MAXIFS(Metas!J:J,Metas!A:A,A46,Metas!B:B,B46,Metas!D:D,D46))) -> 1620 | J46: 0.75 | K46: 6480 | L46: =IF(_xlfn.MAXIFS(Metas!J:J,Metas!A:A,A46,Metas!B:B,B46,Metas!D:D,D46) = 0,K46,K46 * (1-_xlfn.MAXIFS(Metas!J:J,Metas!A:A,A46,Metas!B:B,B46,Metas!D:D,D46))) -> 6480 | M46: 1 | N46: 8100 | O46: =IF(_xlfn.MAXIFS(Metas!J:J,Metas!A:A,A46,Metas!B:B,B46,Metas!D:D,D46) = 0,N46,N46 * (1-_xlfn.MAXIFS(Metas!J:J,Metas!A:A,A46,Metas!B:B,B46,Metas!D:D,D46))) -> 8100 | P46: 1 | Q46: 1.05 | R46: 1.1 | S46: 1.1 | V46: =J46 -> 0.75 | W46: 0.01
A47: 2026 | B47: 1 | C47: Rosana Machado | D47: rosana@altoqi.com.br | E47: Saving | F47: Consultor | G47: 0.6 | H47: 1080 | I47: =IF(_xlfn.MAXIFS(Metas!J:J,Metas!A:A,A47,Metas!B:B,B47,Metas!D:D,D47) = 0,H47,H47 * (1-_xlfn.MAXIFS(Metas!J:J,Metas!A:A,A47,Metas!B:B,B47,Metas!D:D,D47))) -> 1080 | J47: 0.75 | K47: 4320 | L47: =IF(_xlfn.MAXIFS(Metas!J:J,Metas!A:A,A47,Metas!B:B,B47,Metas!D:D,D47) = 0,K47,K47 * (1-_xlfn.MAXIFS(Metas!J:J,Metas!A:A,A47,Metas!B:B,B47,Metas!D:D,D47))) -> 4320 | M47: 1 | N47: 5400 | O47: =IF(_xlfn.MAXIFS(Metas!J:J,Metas!A:A,A47,Metas!B:B,B47,Metas!D:D,D47) = 0,N47,N47 * (1-_xlfn.MAXIFS(Metas!J:J,Metas!A:A,A47,Metas!B:B,B47,Metas!D:D,D47))) -> 5400 | P47: 1 | Q47: 1.05 | R47: 1.1 | S47: 1.1 | V47: =J47 -> 0.75 | W47: 0.01
A48: 2026 | B48: 1 | C48: Rubia Estipe | D48: rubia.estipe@altoqi.com.br | E48: Saving | F48: Consultor | G48: 0.6 | H48: 1620 | I48: =IF(_xlfn.MAXIFS(Metas!J:J,Metas!A:A,A48,Metas!B:B,B48,Metas!D:D,D48) = 0,H48,H48 * (1-_xlfn.MAXIFS(Metas!J:J,Metas!A:A,A48,Metas!B:B,B48,Metas!D:D,D48))) -> 1620 | J48: 0.75 | K48: 6480 | L48: =IF(_xlfn.MAXIFS(Metas!J:J,Metas!A:A,A48,Metas!B:B,B48,Metas!D:D,D48) = 0,K48,K48 * (1-_xlfn.MAXIFS(Metas!J:J,Metas!A:A,A48,Metas!B:B,B48,Metas!D:D,D48))) -> 6480 | M48: 1 | N48: 8100 | O48: =IF(_xlfn.MAXIFS(Metas!J:J,Metas!A:A,A48,Metas!B:B,B48,Metas!D:D,D48) = 0,N48,N48 * (1-_xlfn.MAXIFS(Metas!J:J,Metas!A:A,A48,Metas!B:B,B48,Metas!D:D,D48))) -> 8100 | P48: 1 | Q48: 1.05 | R48: 1.1 | S48: 1.1 | V48: =J48 -> 0.75 | W48: 0.01
A49: 2026 | B49: 1 | C49: Silvia Estipe | D49: silvia.estipe@altoqi.com.br | E49: Saving | F49: Consultor | G49: 0.6 | H49: 1080 | I49: =IF(_xlfn.MAXIFS(Metas!J:J,Metas!A:A,A49,Metas!B:B,B49,Metas!D:D,D49) = 0,H49,H49 * (1-_xlfn.MAXIFS(Metas!J:J,Metas!A:A,A49,Metas!B:B,B49,Metas!D:D,D49))) -> 1080 | J49: 0.75 | K49: 4320 | L49: =IF(_xlfn.MAXIFS(Metas!J:J,Metas!A:A,A49,Metas!B:B,B49,Metas!D:D,D49) = 0,K49,K49 * (1-_xlfn.MAXIFS(Metas!J:J,Metas!A:A,A49,Metas!B:B,B49,Metas!D:D,D49))) -> 4320 | M49: 1 | N49: 5400 | O49: =IF(_xlfn.MAXIFS(Metas!J:J,Metas!A:A,A49,Metas!B:B,B49,Metas!D:D,D49) = 0,N49,N49 * (1-_xlfn.MAXIFS(Metas!J:J,Metas!A:A,A49,Metas!B:B,B49,Metas!D:D,D49))) -> 5400 | P49: 1 | Q49: 1.05 | R49: 1.1 | S49: 1.1 | V49: =J49 -> 0.75 | W49: 0.01
A50: 2026 | B50: 1 | C50: Sonia Maria Zielinski Pockszevnicki | D50: sonia.zielinski@altoqi.com.br | E50: Sonia | F50: Gestor | G50: 0.55 | H50: 8976 | I50: =IF(_xlfn.MAXIFS(Metas!J:J,Metas!A:A,A50,Metas!B:B,B50,Metas!D:D,D50) = 0,H50,H50 * (1-_xlfn.MAXIFS(Metas!J:J,Metas!A:A,A50,Metas!B:B,B50,Metas!D:D,D50))) -> 8976 | L50: =IF(_xlfn.MAXIFS(Metas!J:J,Metas!A:A,A50,Metas!B:B,B50,Metas!D:D,D50) = 0,K50,K50 * (1-_xlfn.MAXIFS(Metas!J:J,Metas!A:A,A50,Metas!B:B,B50,Metas!D:D,D50))) -> 0 | O50: =IF(_xlfn.MAXIFS(Metas!J:J,Metas!A:A,A50,Metas!B:B,B50,Metas!D:D,D50) = 0,N50,N50 * (1-_xlfn.MAXIFS(Metas!J:J,Metas!A:A,A50,Metas!B:B,B50,Metas!D:D,D50))) -> 0 | P50: 0.95 | Q50: 1.15 | R50: 1.05 | S50: 1.25 | V50: =G50 -> 0.55 | W50: 0.005
A51: 2026 | B51: 2 | C51: Anderson Ortiz | D51: anderson.ortiz@altoqi.com.br | E51: Ares | F51: Consultor | G51: 0.55 | H51: 3960 | I51: =IF(_xlfn.MAXIFS(Metas!J:J,Metas!A:A,A51,Metas!B:B,B51,Metas!D:D,D51) = 0,H51,H51 * (1-_xlfn.MAXIFS(Metas!J:J,Metas!A:A,A51,Metas!B:B,B51,Metas!D:D,D51))) -> 3960 | L51: =IF(_xlfn.MAXIFS(Metas!J:J,Metas!A:A,A51,Metas!B:B,B51,Metas!D:D,D51) = 0,K51,K51 * (1-_xlfn.MAXIFS(Metas!J:J,Metas!A:A,A51,Metas!B:B,B51,Metas!D:D,D51))) -> 0 | O51: =IF(_xlfn.MAXIFS(Metas!J:J,Metas!A:A,A51,Metas!B:B,B51,Metas!D:D,D51) = 0,N51,N51 * (1-_xlfn.MAXIFS(Metas!J:J,Metas!A:A,A51,Metas!B:B,B51,Metas!D:D,D51))) -> 0 | P51: 0.95 | Q51: 1.15 | R51: 1.05 | S51: 1.25 | V51: =G51 -> 0.55 | W51: 0.02
A52: 2026 | B52: 2 | C52: Francisco Guilherme Junior | D52: francisco.junior@altoqi.com.br | E52: Ares | F52: Consultor | G52: 0.55 | H52: 4176 | I52: =IF(_xlfn.MAXIFS(Metas!J:J,Metas!A:A,A52,Metas!B:B,B52,Metas!D:D,D52) = 0,H52,H52 * (1-_xlfn.MAXIFS(Metas!J:J,Metas!A:A,A52,Metas!B:B,B52,Metas!D:D,D52))) -> 2088 | L52: =IF(_xlfn.MAXIFS(Metas!J:J,Metas!A:A,A52,Metas!B:B,B52,Metas!D:D,D52) = 0,K52,K52 * (1-_xlfn.MAXIFS(Metas!J:J,Metas!A:A,A52,Metas!B:B,B52,Metas!D:D,D52))) -> 0 | O52: =IF(_xlfn.MAXIFS(Metas!J:J,Metas!A:A,A52,Metas!B:B,B52,Metas!D:D,D52) = 0,N52,N52 * (1-_xlfn.MAXIFS(Metas!J:J,Metas!A:A,A52,Metas!B:B,B52,Metas!D:D,D52))) -> 0 | P52: 0.95 | Q52: 1.15 | R52: 1.05 | S52: 1.25 | V52: =G52 -> 0.55 | W52: 0.02
A53: 2026 | B53: 2 | C53: Rodrigo da Rosa Lima | D53: rodrigo.lima@altoqi.com.br | E53: Ares | F53: Consultor | G53: 0.55 | H53: 3564 | I53: =IF(_xlfn.MAXIFS(Metas!J:J,Metas!A:A,A53,Metas!B:B,B53,Metas!D:D,D53) = 0,H53,H53 * (1-_xlfn.MAXIFS(Metas!J:J,Metas!A:A,A53,Metas!B:B,B53,Metas!D:D,D53))) -> 3564 | L53: =IF(_xlfn.MAXIFS(Metas!J:J,Metas!A:A,A53,Metas!B:B,B53,Metas!D:D,D53) = 0,K53,K53 * (1-_xlfn.MAXIFS(Metas!J:J,Metas!A:A,A53,Metas!B:B,B53,Metas!D:D,D53))) -> 0 | O53: =IF(_xlfn.MAXIFS(Metas!J:J,Metas!A:A,A53,Metas!B:B,B53,Metas!D:D,D53) = 0,N53,N53 * (1-_xlfn.MAXIFS(Metas!J:J,Metas!A:A,A53,Metas!B:B,B53,Metas!D:D,D53))) -> 0 | P53: 0.95 | Q53: 1.15 | R53: 1.05 | S53: 1.25 | V53: =G53 -> 0.55 | W53: 0.02
A54: 2026 | B54: 2 | C54: Denis Melo Silva | D54: denis.silva@altoqi.com.br | E54: B2B Construtora | F54: Consultor | G54: 0.55 | H54: 4176 | I54: =IF(_xlfn.MAXIFS(Metas!J:J,Metas!A:A,A54,Metas!B:B,B54,Metas!D:D,D54) = 0,H54,H54 * (1-_xlfn.MAXIFS(Metas!J:J,Metas!A:A,A54,Metas!B:B,B54,Metas!D:D,D54))) -> 1252.8 | L54: =IF(_xlfn.MAXIFS(Metas!J:J,Metas!A:A,A54,Metas!B:B,B54,Metas!D:D,D54) = 0,K54,K54 * (1-_xlfn.MAXIFS(Metas!J:J,Metas!A:A,A54,Metas!B:B,B54,Metas!D:D,D54))) -> 0 | O54: =IF(_xlfn.MAXIFS(Metas!J:J,Metas!A:A,A54,Metas!B:B,B54,Metas!D:D,D54) = 0,N54,N54 * (1-_xlfn.MAXIFS(Metas!J:J,Metas!A:A,A54,Metas!B:B,B54,Metas!D:D,D54))) -> 0 | P54: 0.95 | Q54: 1.15 | R54: 1.05 | S54: 1.25 | V54: =G54 -> 0.55 | W54: 0.02
A55: 2026 | B55: 2 | C55: Eloyse Silveira | D55: eloyse.silveira@altoqi.com.br | E55: B2B Construtora | F55: Consultor | G55: 0.55 | H55: 4176 | I55: =IF(_xlfn.MAXIFS(Metas!J:J,Metas!A:A,A55,Metas!B:B,B55,Metas!D:D,D55) = 0,H55,H55 * (1-_xlfn.MAXIFS(Metas!J:J,Metas!A:A,A55,Metas!B:B,B55,Metas!D:D,D55))) -> 4176 | L55: =IF(_xlfn.MAXIFS(Metas!J:J,Metas!A:A,A55,Metas!B:B,B55,Metas!D:D,D55) = 0,K55,K55 * (1-_xlfn.MAXIFS(Metas!J:J,Metas!A:A,A55,Metas!B:B,B55,Metas!D:D,D55))) -> 0 | O55: =IF(_xlfn.MAXIFS(Metas!J:J,Metas!A:A,A55,Metas!B:B,B55,Metas!D:D,D55) = 0,N55,N55 * (1-_xlfn.MAXIFS(Metas!J:J,Metas!A:A,A55,Metas!B:B,B55,Metas!D:D,D55))) -> 0 | P55: 0.95 | Q55: 1.15 | R55: 1.05 | S55: 1.25 | V55: =G55 -> 0.55 | W55: 0.02
A56: 2026 | B56: 2 | C56: Henrique Teixeira Silva | D56: henrique.silva@altoqi.com.br | E56: B2B Construtora | F56: Consultor | G56: 0.55 | H56: 4176 | I56: =IF(_xlfn.MAXIFS(Metas!J:J,Metas!A:A,A56,Metas!B:B,B56,Metas!D:D,D56) = 0,H56,H56 * (1-_xlfn.MAXIFS(Metas!J:J,Metas!A:A,A56,Metas!B:B,B56,Metas!D:D,D56))) -> 4176 | L56: =IF(_xlfn.MAXIFS(Metas!J:J,Metas!A:A,A56,Metas!B:B,B56,Metas!D:D,D56) = 0,K56,K56 * (1-_xlfn.MAXIFS(Metas!J:J,Metas!A:A,A56,Metas!B:B,B56,Metas!D:D,D56))) -> 0 | O56: =IF(_xlfn.MAXIFS(Metas!J:J,Metas!A:A,A56,Metas!B:B,B56,Metas!D:D,D56) = 0,N56,N56 * (1-_xlfn.MAXIFS(Metas!J:J,Metas!A:A,A56,Metas!B:B,B56,Metas!D:D,D56))) -> 0 | P56: 0.95 | Q56: 1.15 | R56: 1.05 | S56: 1.25 | V56: =G56 -> 0.55 | W56: 0.02
A57: 2026 | B57: 2 | C57: Rafael Acencio | D57: rafael.acencio@altoqi.com.br | E57: B2B Construtora | F57: Consultor | G57: 0.55 | H57: 5297 | I57: =IF(_xlfn.MAXIFS(Metas!J:J,Metas!A:A,A57,Metas!B:B,B57,Metas!D:D,D57) = 0,H57,H57 * (1-_xlfn.MAXIFS(Metas!J:J,Metas!A:A,A57,Metas!B:B,B57,Metas!D:D,D57))) -> 3496.02 | L57: =IF(_xlfn.MAXIFS(Metas!J:J,Metas!A:A,A57,Metas!B:B,B57,Metas!D:D,D57) = 0,K57,K57 * (1-_xlfn.MAXIFS(Metas!J:J,Metas!A:A,A57,Metas!B:B,B57,Metas!D:D,D57))) -> 0 | O57: =IF(_xlfn.MAXIFS(Metas!J:J,Metas!A:A,A57,Metas!B:B,B57,Metas!D:D,D57) = 0,N57,N57 * (1-_xlfn.MAXIFS(Metas!J:J,Metas!A:A,A57,Metas!B:B,B57,Metas!D:D,D57))) -> 0 | P57: 0.95 | Q57: 1.15 | R57: 1.05 | S57: 1.25 | V57: =G57 -> 0.55 | W57: 0.02
A58: 2026 | B58: 2 | C58: Fernanda da Silva Fertonani | D58: fernanda.fertonani@altoqi.com.br | E58: B2B Escritório | F58: Consultor | G58: 0.55 | H58: 4176 | I58: =IF(_xlfn.MAXIFS(Metas!J:J,Metas!A:A,A58,Metas!B:B,B58,Metas!D:D,D58) = 0,H58,H58 * (1-_xlfn.MAXIFS(Metas!J:J,Metas!A:A,A58,Metas!B:B,B58,Metas!D:D,D58))) -> 4176 | L58: =IF(_xlfn.MAXIFS(Metas!J:J,Metas!A:A,A58,Metas!B:B,B58,Metas!D:D,D58) = 0,K58,K58 * (1-_xlfn.MAXIFS(Metas!J:J,Metas!A:A,A58,Metas!B:B,B58,Metas!D:D,D58))) -> 0 | O58: =IF(_xlfn.MAXIFS(Metas!J:J,Metas!A:A,A58,Metas!B:B,B58,Metas!D:D,D58) = 0,N58,N58 * (1-_xlfn.MAXIFS(Metas!J:J,Metas!A:A,A58,Metas!B:B,B58,Metas!D:D,D58))) -> 0 | P58: 0.95 | Q58: 1.15 | R58: 1.05 | S58: 1.25 | V58: =G58 -> 0.55 | W58: 0.02
A59: 2026 | B59: 2 | C59: Paola Oliveira | D59: paola.oliveira@altoqi.com.br | E59: B2B Escritório | F59: Consultor | G59: 0.55 | H59: 4176 | I59: =IF(_xlfn.MAXIFS(Metas!J:J,Metas!A:A,A59,Metas!B:B,B59,Metas!D:D,D59) = 0,H59,H59 * (1-_xlfn.MAXIFS(Metas!J:J,Metas!A:A,A59,Metas!B:B,B59,Metas!D:D,D59))) -> 2088 | L59: =IF(_xlfn.MAXIFS(Metas!J:J,Metas!A:A,A59,Metas!B:B,B59,Metas!D:D,D59) = 0,K59,K59 * (1-_xlfn.MAXIFS(Metas!J:J,Metas!A:A,A59,Metas!B:B,B59,Metas!D:D,D59))) -> 0 | O59: =IF(_xlfn.MAXIFS(Metas!J:J,Metas!A:A,A59,Metas!B:B,B59,Metas!D:D,D59) = 0,N59,N59 * (1-_xlfn.MAXIFS(Metas!J:J,Metas!A:A,A59,Metas!B:B,B59,Metas!D:D,D59))) -> 0 | P59: 0.95 | Q59: 1.15 | R59: 1.05 | S59: 1.25 | V59: =G59 -> 0.55 | W59: 0.02
A60: 2026 | B60: 2 | C60: Aline Castilho Pureza | D60: aline.pureza@altoqi.com.br | E60: Farmer | F60: Consultor | G60: 0.55 | H60: 3240 | I60: =IF(_xlfn.MAXIFS(Metas!J:J,Metas!A:A,A60,Metas!B:B,B60,Metas!D:D,D60) = 0,H60,H60 * (1-_xlfn.MAXIFS(Metas!J:J,Metas!A:A,A60,Metas!B:B,B60,Metas!D:D,D60))) -> 1944 | L60: =IF(_xlfn.MAXIFS(Metas!J:J,Metas!A:A,A60,Metas!B:B,B60,Metas!D:D,D60) = 0,K60,K60 * (1-_xlfn.MAXIFS(Metas!J:J,Metas!A:A,A60,Metas!B:B,B60,Metas!D:D,D60))) -> 0 | O60: =IF(_xlfn.MAXIFS(Metas!J:J,Metas!A:A,A60,Metas!B:B,B60,Metas!D:D,D60) = 0,N60,N60 * (1-_xlfn.MAXIFS(Metas!J:J,Metas!A:A,A60,Metas!B:B,B60,Metas!D:D,D60))) -> 0 | P60: 0.95 | Q60: 1.15 | R60: 1.05 | S60: 1.25 | V60: =G60 -> 0.55 | W60: 0.02
A61: 2026 | B61: 2 | C61: Clidiani Costa | D61: clidiani@altoqi.com.br | E61: Farmer | F61: Consultor | G61: 0.55 | H61: 6480 | I61: =IF(_xlfn.MAXIFS(Metas!J:J,Metas!A:A,A61,Metas!B:B,B61,Metas!D:D,D61) = 0,H61,H61 * (1-_xlfn.MAXIFS(Metas!J:J,Metas!A:A,A61,Metas!B:B,B61,Metas!D:D,D61))) -> 5054.4 | J61: 1 | K61: 8100 | L61: =IF(_xlfn.MAXIFS(Metas!J:J,Metas!A:A,A61,Metas!B:B,B61,Metas!D:D,D61) = 0,K61,K61 * (1-_xlfn.MAXIFS(Metas!J:J,Metas!A:A,A61,Metas!B:B,B61,Metas!D:D,D61))) -> 6318 | O61: =IF(_xlfn.MAXIFS(Metas!J:J,Metas!A:A,A61,Metas!B:B,B61,Metas!D:D,D61) = 0,N61,N61 * (1-_xlfn.MAXIFS(Metas!J:J,Metas!A:A,A61,Metas!B:B,B61,Metas!D:D,D61))) -> 0 | P61: 0.95 | Q61: 1.15 | R61: 1.05 | S61: 1.25 | V61: =G61 -> 0.55 | W61: 0.02
A62: 2026 | B62: 2 | C62: Debora Vieira | D62: debora.vieira@altoqi.com.br | E62: Farmer | F62: Consultor | G62: 0.55 | H62: 3240 | I62: =IF(_xlfn.MAXIFS(Metas!J:J,Metas!A:A,A62,Metas!B:B,B62,Metas!D:D,D62) = 0,H62,H62 * (1-_xlfn.MAXIFS(Metas!J:J,Metas!A:A,A62,Metas!B:B,B62,Metas!D:D,D62))) -> 3240 | L62: =IF(_xlfn.MAXIFS(Metas!J:J,Metas!A:A,A62,Metas!B:B,B62,Metas!D:D,D62) = 0,K62,K62 * (1-_xlfn.MAXIFS(Metas!J:J,Metas!A:A,A62,Metas!B:B,B62,Metas!D:D,D62))) -> 0 | O62: =IF(_xlfn.MAXIFS(Metas!J:J,Metas!A:A,A62,Metas!B:B,B62,Metas!D:D,D62) = 0,N62,N62 * (1-_xlfn.MAXIFS(Metas!J:J,Metas!A:A,A62,Metas!B:B,B62,Metas!D:D,D62))) -> 0 | P62: 0.95 | Q62: 1.15 | R62: 1.05 | S62: 1.25 | V62: =G62 -> 0.55 | W62: 0.02
A63: 2026 | B63: 2 | C63: Mariana Rachadel | D63: mariana@altoqi.com.br | E63: Farmer | F63: Consultor | G63: 0.55 | H63: 9200 | I63: =IF(_xlfn.MAXIFS(Metas!J:J,Metas!A:A,A63,Metas!B:B,B63,Metas!D:D,D63) = 0,H63,H63 * (1-_xlfn.MAXIFS(Metas!J:J,Metas!A:A,A63,Metas!B:B,B63,Metas!D:D,D63))) -> 5796 | J63: 1 | K63: 11500 | L63: =IF(_xlfn.MAXIFS(Metas!J:J,Metas!A:A,A63,Metas!B:B,B63,Metas!D:D,D63) = 0,K63,K63 * (1-_xlfn.MAXIFS(Metas!J:J,Metas!A:A,A63,Metas!B:B,B63,Metas!D:D,D63))) -> 7245 | O63: =IF(_xlfn.MAXIFS(Metas!J:J,Metas!A:A,A63,Metas!B:B,B63,Metas!D:D,D63) = 0,N63,N63 * (1-_xlfn.MAXIFS(Metas!J:J,Metas!A:A,A63,Metas!B:B,B63,Metas!D:D,D63))) -> 0 | P63: 0.95 | Q63: 1.15 | R63: 1.05 | S63: 1.25 | V63: =G63 -> 0.55 | W63: 0.02
A64: 2026 | B64: 2 | C64: Renata Parizotto | D64: renata.parizotto@altoqi.com.br | E64: Farmer | F64: Consultor | G64: 0.55 | H64: 4176 | I64: =IF(_xlfn.MAXIFS(Metas!J:J,Metas!A:A,A64,Metas!B:B,B64,Metas!D:D,D64) = 0,H64,H64 * (1-_xlfn.MAXIFS(Metas!J:J,Metas!A:A,A64,Metas!B:B,B64,Metas!D:D,D64))) -> 2046.24 | L64: =IF(_xlfn.MAXIFS(Metas!J:J,Metas!A:A,A64,Metas!B:B,B64,Metas!D:D,D64) = 0,K64,K64 * (1-_xlfn.MAXIFS(Metas!J:J,Metas!A:A,A64,Metas!B:B,B64,Metas!D:D,D64))) -> 0 | O64: =IF(_xlfn.MAXIFS(Metas!J:J,Metas!A:A,A64,Metas!B:B,B64,Metas!D:D,D64) = 0,N64,N64 * (1-_xlfn.MAXIFS(Metas!J:J,Metas!A:A,A64,Metas!B:B,B64,Metas!D:D,D64))) -> 0 | P64: 0.95 | Q64: 1.15 | R64: 1.05 | S64: 1.25 | V64: =G64 -> 0.55 | W64: 0.02
A65: 2026 | B65: 2 | C65: Thales Mariante De Sá | D65: thales.sa@altoqi.com.br | E65: Farmer | F65: Consultor | G65: 0.55 | H65: 3240 | I65: =IF(_xlfn.MAXIFS(Metas!J:J,Metas!A:A,A65,Metas!B:B,B65,Metas!D:D,D65) = 0,H65,H65 * (1-_xlfn.MAXIFS(Metas!J:J,Metas!A:A,A65,Metas!B:B,B65,Metas!D:D,D65))) -> 3240 | L65: =IF(_xlfn.MAXIFS(Metas!J:J,Metas!A:A,A65,Metas!B:B,B65,Metas!D:D,D65) = 0,K65,K65 * (1-_xlfn.MAXIFS(Metas!J:J,Metas!A:A,A65,Metas!B:B,B65,Metas!D:D,D65))) -> 0 | O65: =IF(_xlfn.MAXIFS(Metas!J:J,Metas!A:A,A65,Metas!B:B,B65,Metas!D:D,D65) = 0,N65,N65 * (1-_xlfn.MAXIFS(Metas!J:J,Metas!A:A,A65,Metas!B:B,B65,Metas!D:D,D65))) -> 0 | P65: 0.95 | Q65: 1.15 | R65: 1.05 | S65: 1.25 | V65: =G65 -> 0.55 | W65: 0.02
A66: 2026 | B66: 2 | C66: Anderson Ortiz | D66: anderson.ortiz@altoqi.com.br | E66: FSB | F66: Gestor | G66: 0.6 | H66: 4879 | I66: =IF(_xlfn.MAXIFS(Metas!J:J,Metas!A:A,A66,Metas!B:B,B66,Metas!D:D,D66,Metas!E:E,E66) = 0,H66,H66 * (1-_xlfn.MAXIFS(Metas!J:J,Metas!A:A,A66,Metas!B:B,B66,Metas!D:D,D66,Metas!E:E,E66))) -> 4879 | L66: =IF(_xlfn.MAXIFS(Metas!J:J,Metas!A:A,A66,Metas!B:B,B66,Metas!D:D,D66) = 0,K66,K66 * (1-_xlfn.MAXIFS(Metas!J:J,Metas!A:A,A66,Metas!B:B,B66,Metas!D:D,D66))) -> 0 | O66: =IF(_xlfn.MAXIFS(Metas!J:J,Metas!A:A,A66,Metas!B:B,B66,Metas!D:D,D66) = 0,N66,N66 * (1-_xlfn.MAXIFS(Metas!J:J,Metas!A:A,A66,Metas!B:B,B66,Metas!D:D,D66))) -> 0 | P66: 0.95 | Q66: 1.15 | R66: 1.05 | S66: 1.25 | V66: =G66 -> 0.6 | W66: 0.02
A67: 2026 | B67: 2 | C67: Artur Machado | D67: artur.francisco@altoqi.com.br | E67: FSB | F67: Consultor | G67: 0.6 | H67: 3240 | I67: =IF(_xlfn.MAXIFS(Metas!J:J,Metas!A:A,A67,Metas!B:B,B67,Metas!D:D,D67) = 0,H67,H67 * (1-_xlfn.MAXIFS(Metas!J:J,Metas!A:A,A67,Metas!B:B,B67,Metas!D:D,D67))) -> 1620 | L67: =IF(_xlfn.MAXIFS(Metas!J:J,Metas!A:A,A67,Metas!B:B,B67,Metas!D:D,D67) = 0,K67,K67 * (1-_xlfn.MAXIFS(Metas!J:J,Metas!A:A,A67,Metas!B:B,B67,Metas!D:D,D67))) -> 0 | O67: =IF(_xlfn.MAXIFS(Metas!J:J,Metas!A:A,A67,Metas!B:B,B67,Metas!D:D,D67) = 0,N67,N67 * (1-_xlfn.MAXIFS(Metas!J:J,Metas!A:A,A67,Metas!B:B,B67,Metas!D:D,D67))) -> 0 | P67: 0.95 | Q67: 1.15 | R67: 1.05 | S67: 1.25 | V67: =G67 -> 0.6 | W67: 0.02
A68: 2026 | B68: 2 | C68: Eliane Guinther | D68: eliane.guinther@altoqi.com.br | E68: FSB | F68: Consultor | G68: 0.6 | H68: 3240 | I68: =IF(_xlfn.MAXIFS(Metas!J:J,Metas!A:A,A68,Metas!B:B,B68,Metas!D:D,D68) = 0,H68,H68 * (1-_xlfn.MAXIFS(Metas!J:J,Metas!A:A,A68,Metas!B:B,B68,Metas!D:D,D68))) -> 3240 | L68: =IF(_xlfn.MAXIFS(Metas!J:J,Metas!A:A,A68,Metas!B:B,B68,Metas!D:D,D68) = 0,K68,K68 * (1-_xlfn.MAXIFS(Metas!J:J,Metas!A:A,A68,Metas!B:B,B68,Metas!D:D,D68))) -> 0 | O68: =IF(_xlfn.MAXIFS(Metas!J:J,Metas!A:A,A68,Metas!B:B,B68,Metas!D:D,D68) = 0,N68,N68 * (1-_xlfn.MAXIFS(Metas!J:J,Metas!A:A,A68,Metas!B:B,B68,Metas!D:D,D68))) -> 0 | P68: 0.95 | Q68: 1.15 | R68: 1.05 | S68: 1.25 | V68: =G68 -> 0.6 | W68: 0.02
A69: 2026 | B69: 2 | C69: Renata Scheffer | D69: renata.scheffer@altoqi.com.br | E69: FSB | F69: Consultor | G69: 0.6 | H69: 3240 | I69: =IF(_xlfn.MAXIFS(Metas!J:J,Metas!A:A,A69,Metas!B:B,B69,Metas!D:D,D69,Metas!E:E,E69) = 0,H69,H69 * (1-_xlfn.MAXIFS(Metas!J:J,Metas!A:A,A69,Metas!B:B,B69,Metas!D:D,D69,Metas!E:E,E69))) -> 1620 | L69: =IF(_xlfn.MAXIFS(Metas!J:J,Metas!A:A,A69,Metas!B:B,B69,Metas!D:D,D69) = 0,K69,K69 * (1-_xlfn.MAXIFS(Metas!J:J,Metas!A:A,A69,Metas!B:B,B69,Metas!D:D,D69))) -> 0 | O69: =IF(_xlfn.MAXIFS(Metas!J:J,Metas!A:A,A69,Metas!B:B,B69,Metas!D:D,D69) = 0,N69,N69 * (1-_xlfn.MAXIFS(Metas!J:J,Metas!A:A,A69,Metas!B:B,B69,Metas!D:D,D69))) -> 0 | P69: 0.95 | Q69: 1.15 | R69: 1.05 | S69: 1.25 | V69: =G69 -> 0.6 | W69: 0.02
A70: 2026 | B70: 2 | C70: Susana Alves Becker | D70: susana.becker@altoqi.com.br | E70: FSB | F70: Consultor | G70: 0.6 | H70: 3960 | I70: =IF(_xlfn.MAXIFS(Metas!J:J,Metas!A:A,A70,Metas!B:B,B70,Metas!D:D,D70) = 0,H70,H70 * (1-_xlfn.MAXIFS(Metas!J:J,Metas!A:A,A70,Metas!B:B,B70,Metas!D:D,D70))) -> 3960 | L70: =IF(_xlfn.MAXIFS(Metas!J:J,Metas!A:A,A70,Metas!B:B,B70,Metas!D:D,D70) = 0,K70,K70 * (1-_xlfn.MAXIFS(Metas!J:J,Metas!A:A,A70,Metas!B:B,B70,Metas!D:D,D70))) -> 0 | O70: =IF(_xlfn.MAXIFS(Metas!J:J,Metas!A:A,A70,Metas!B:B,B70,Metas!D:D,D70) = 0,N70,N70 * (1-_xlfn.MAXIFS(Metas!J:J,Metas!A:A,A70,Metas!B:B,B70,Metas!D:D,D70))) -> 0 | P70: 0.95 | Q70: 1.15 | R70: 1.05 | S70: 1.25 | V70: =G70 -> 0.6 | W70: 0.02
A71: 2026 | B71: 2 | C71: Ana Camargo | D71: ana.camargo@altoqi.com.br | E71: GD | F71: Consultor | G71: 0.7 | H71: 1500 | I71: =IF(_xlfn.MAXIFS(Metas!J:J,Metas!A:A,A71,Metas!B:B,B71,Metas!D:D,D71) = 0,H71,H71 * (1-_xlfn.MAXIFS(Metas!J:J,Metas!A:A,A71,Metas!B:B,B71,Metas!D:D,D71))) -> 1500 | L71: =IF(_xlfn.MAXIFS(Metas!J:J,Metas!A:A,A71,Metas!B:B,B71,Metas!D:D,D71) = 0,K71,K71 * (1-_xlfn.MAXIFS(Metas!J:J,Metas!A:A,A71,Metas!B:B,B71,Metas!D:D,D71))) -> 0 | O71: =IF(_xlfn.MAXIFS(Metas!J:J,Metas!A:A,A71,Metas!B:B,B71,Metas!D:D,D71) = 0,N71,N71 * (1-_xlfn.MAXIFS(Metas!J:J,Metas!A:A,A71,Metas!B:B,B71,Metas!D:D,D71))) -> 0 | P71: 0.95 | Q71: 1.15 | R71: 1.05 | S71: 1.25
A72: 2026 | B72: 2 | C72: Anand Freitas Figueiredo | D72: anand.figueiredo@altoqi.com.br | E72: GD | F72: Consultor | G72: 0.5 | H72: 1800 | I72: =IF(_xlfn.MAXIFS(Metas!J:J,Metas!A:A,A72,Metas!B:B,B72,Metas!D:D,D72) = 0,H72,H72 * (1-_xlfn.MAXIFS(Metas!J:J,Metas!A:A,A72,Metas!B:B,B72,Metas!D:D,D72))) -> 1800 | L72: =IF(_xlfn.MAXIFS(Metas!J:J,Metas!A:A,A72,Metas!B:B,B72,Metas!D:D,D72) = 0,K72,K72 * (1-_xlfn.MAXIFS(Metas!J:J,Metas!A:A,A72,Metas!B:B,B72,Metas!D:D,D72))) -> 0 | O72: =IF(_xlfn.MAXIFS(Metas!J:J,Metas!A:A,A72,Metas!B:B,B72,Metas!D:D,D72) = 0,N72,N72 * (1-_xlfn.MAXIFS(Metas!J:J,Metas!A:A,A72,Metas!B:B,B72,Metas!D:D,D72))) -> 0 | P72: 0.75 | Q72: 1.15 | R72: 0.9 | S72: 1.25
A73: 2026 | B73: 2 | C73: André Cardoso | D73: andre.cardoso@altoqi.com.br | E73: GD | F73: Gestor | G73: 0.7 | H73: 3200 | I73: =IF(_xlfn.MAXIFS(Metas!J:J,Metas!A:A,A73,Metas!B:B,B73,Metas!D:D,D73) = 0,H73,H73 * (1-_xlfn.MAXIFS(Metas!J:J,Metas!A:A,A73,Metas!B:B,B73,Metas!D:D,D73))) -> 3200 | L73: =IF(_xlfn.MAXIFS(Metas!J:J,Metas!A:A,A73,Metas!B:B,B73,Metas!D:D,D73) = 0,K73,K73 * (1-_xlfn.MAXIFS(Metas!J:J,Metas!A:A,A73,Metas!B:B,B73,Metas!D:D,D73))) -> 0 | O73: =IF(_xlfn.MAXIFS(Metas!J:J,Metas!A:A,A73,Metas!B:B,B73,Metas!D:D,D73) = 0,N73,N73 * (1-_xlfn.MAXIFS(Metas!J:J,Metas!A:A,A73,Metas!B:B,B73,Metas!D:D,D73))) -> 0 | P73: 0.95 | Q73: 1.15 | R73: 1.05 | S73: 1.25
A74: 2026 | B74: 2 | C74: Arthur Treivisol | D74: arthur.trevisiol@altoqi.com.br | E74: GD | F74: Consultor | G74: 0.7 | H74: 1500 | I74: =IF(_xlfn.MAXIFS(Metas!J:J,Metas!A:A,A74,Metas!B:B,B74,Metas!D:D,D74) = 0,H74,H74 * (1-_xlfn.MAXIFS(Metas!J:J,Metas!A:A,A74,Metas!B:B,B74,Metas!D:D,D74))) -> 1500 | L74: =IF(_xlfn.MAXIFS(Metas!J:J,Metas!A:A,A74,Metas!B:B,B74,Metas!D:D,D74) = 0,K74,K74 * (1-_xlfn.MAXIFS(Metas!J:J,Metas!A:A,A74,Metas!B:B,B74,Metas!D:D,D74))) -> 0 | O74: =IF(_xlfn.MAXIFS(Metas!J:J,Metas!A:A,A74,Metas!B:B,B74,Metas!D:D,D74) = 0,N74,N74 * (1-_xlfn.MAXIFS(Metas!J:J,Metas!A:A,A74,Metas!B:B,B74,Metas!D:D,D74))) -> 0 | P74: 0.95 | Q74: 1.15 | R74: 1.05 | S74: 1.25
A75: 2026 | B75: 2 | C75: Elisa Nickel Costa | D75: elisa.costa@altoqi.com.br | E75: GD | F75: Consultor | G75: 0.7 | H75: 1500 | I75: =IF(_xlfn.MAXIFS(Metas!J:J,Metas!A:A,A75,Metas!B:B,B75,Metas!D:D,D75) = 0,H75,H75 * (1-_xlfn.MAXIFS(Metas!J:J,Metas!A:A,A75,Metas!B:B,B75,Metas!D:D,D75))) -> 1500 | L75: =IF(_xlfn.MAXIFS(Metas!J:J,Metas!A:A,A75,Metas!B:B,B75,Metas!D:D,D75) = 0,K75,K75 * (1-_xlfn.MAXIFS(Metas!J:J,Metas!A:A,A75,Metas!B:B,B75,Metas!D:D,D75))) -> 0 | O75: =IF(_xlfn.MAXIFS(Metas!J:J,Metas!A:A,A75,Metas!B:B,B75,Metas!D:D,D75) = 0,N75,N75 * (1-_xlfn.MAXIFS(Metas!J:J,Metas!A:A,A75,Metas!B:B,B75,Metas!D:D,D75))) -> 0 | P75: 0.95 | Q75: 1.15 | R75: 1.05 | S75: 1.25
A76: 2026 | B76: 2 | C76: Luiz Arthur Falcão Senna | D76: luiz.senna@altoqi.com.br | E76: GD | F76: Consultor | G76: 0.7 | H76: 1800 | I76: =IF(_xlfn.MAXIFS(Metas!J:J,Metas!A:A,A76,Metas!B:B,B76,Metas!D:D,D76) = 0,H76,H76 * (1-_xlfn.MAXIFS(Metas!J:J,Metas!A:A,A76,Metas!B:B,B76,Metas!D:D,D76))) -> 1800 | L76: =IF(_xlfn.MAXIFS(Metas!J:J,Metas!A:A,A76,Metas!B:B,B76,Metas!D:D,D76) = 0,K76,K76 * (1-_xlfn.MAXIFS(Metas!J:J,Metas!A:A,A76,Metas!B:B,B76,Metas!D:D,D76))) -> 0 | O76: =IF(_xlfn.MAXIFS(Metas!J:J,Metas!A:A,A76,Metas!B:B,B76,Metas!D:D,D76) = 0,N76,N76 * (1-_xlfn.MAXIFS(Metas!J:J,Metas!A:A,A76,Metas!B:B,B76,Metas!D:D,D76))) -> 0 | P76: 0.95 | Q76: 1.15 | R76: 1.05 | S76: 1.25
A77: 2026 | B77: 2 | C77: Maria Eduarda Barbosa | D77: maria.eduarda@altoqi.com.br | E77: GD | F77: Consultor | G77: 0.7 | H77: 1500 | I77: =IF(_xlfn.MAXIFS(Metas!J:J,Metas!A:A,A77,Metas!B:B,B77,Metas!D:D,D77) = 0,H77,H77 * (1-_xlfn.MAXIFS(Metas!J:J,Metas!A:A,A77,Metas!B:B,B77,Metas!D:D,D77))) -> 495 | L77: =IF(_xlfn.MAXIFS(Metas!J:J,Metas!A:A,A77,Metas!B:B,B77,Metas!D:D,D77) = 0,K77,K77 * (1-_xlfn.MAXIFS(Metas!J:J,Metas!A:A,A77,Metas!B:B,B77,Metas!D:D,D77))) -> 0 | O77: =IF(_xlfn.MAXIFS(Metas!J:J,Metas!A:A,A77,Metas!B:B,B77,Metas!D:D,D77) = 0,N77,N77 * (1-_xlfn.MAXIFS(Metas!J:J,Metas!A:A,A77,Metas!B:B,B77,Metas!D:D,D77))) -> 0 | P77: 0.95 | Q77: 1.15 | R77: 1.05 | S77: 1.25
A78: 2026 | B78: 2 | C78: Matheus Fiebig | D78: matheus.lima@altoqi.com.br | E78: GD | F78: Consultor | G78: 0.7 | H78: 1500 | I78: =IF(_xlfn.MAXIFS(Metas!J:J,Metas!A:A,A78,Metas!B:B,B78,Metas!D:D,D78) = 0,H78,H78 * (1-_xlfn.MAXIFS(Metas!J:J,Metas!A:A,A78,Metas!B:B,B78,Metas!D:D,D78))) -> 1500 | L78: =IF(_xlfn.MAXIFS(Metas!J:J,Metas!A:A,A78,Metas!B:B,B78,Metas!D:D,D78) = 0,K78,K78 * (1-_xlfn.MAXIFS(Metas!J:J,Metas!A:A,A78,Metas!B:B,B78,Metas!D:D,D78))) -> 0 | O78: =IF(_xlfn.MAXIFS(Metas!J:J,Metas!A:A,A78,Metas!B:B,B78,Metas!D:D,D78) = 0,N78,N78 * (1-_xlfn.MAXIFS(Metas!J:J,Metas!A:A,A78,Metas!B:B,B78,Metas!D:D,D78))) -> 0 | P78: 0.95 | Q78: 1.15 | R78: 1.05 | S78: 1.25
A79: 2026 | B79: 2 | C79: Sarai Daniela | D79: daniela.cabrera@altoqi.com.br | E79: GD | F79: Consultor | G79: 0.5 | H79: 1800 | I79: =IF(_xlfn.MAXIFS(Metas!J:J,Metas!A:A,A79,Metas!B:B,B79,Metas!D:D,D79) = 0,H79,H79 * (1-_xlfn.MAXIFS(Metas!J:J,Metas!A:A,A79,Metas!B:B,B79,Metas!D:D,D79))) -> 1800 | L79: =IF(_xlfn.MAXIFS(Metas!J:J,Metas!A:A,A79,Metas!B:B,B79,Metas!D:D,D79) = 0,K79,K79 * (1-_xlfn.MAXIFS(Metas!J:J,Metas!A:A,A79,Metas!B:B,B79,Metas!D:D,D79))) -> 0 | O79: =IF(_xlfn.MAXIFS(Metas!J:J,Metas!A:A,A79,Metas!B:B,B79,Metas!D:D,D79) = 0,N79,N79 * (1-_xlfn.MAXIFS(Metas!J:J,Metas!A:A,A79,Metas!B:B,B79,Metas!D:D,D79))) -> 0 | P79: 0.75 | Q79: 1.15 | R79: 0.9 | S79: 1.25
A80: 2026 | B80: 2 | C80: Angélica da Silva Steinbach | D80: angelica.steinbach@altoqi.com.br | E80: Governo | F80: Consultor | G80: 0.5 | H80: 8000 | I80: =IF(_xlfn.MAXIFS(Metas!J:J,Metas!A:A,A80,Metas!B:B,B80,Metas!D:D,D80) = 0,H80,H80 * (1-_xlfn.MAXIFS(Metas!J:J,Metas!A:A,A80,Metas!B:B,B80,Metas!D:D,D80))) -> 8000 | L80: =IF(_xlfn.MAXIFS(Metas!J:J,Metas!A:A,A80,Metas!B:B,B80,Metas!D:D,D80) = 0,K80,K80 * (1-_xlfn.MAXIFS(Metas!J:J,Metas!A:A,A80,Metas!B:B,B80,Metas!D:D,D80))) -> 0 | O80: =IF(_xlfn.MAXIFS(Metas!J:J,Metas!A:A,A80,Metas!B:B,B80,Metas!D:D,D80) = 0,N80,N80 * (1-_xlfn.MAXIFS(Metas!J:J,Metas!A:A,A80,Metas!B:B,B80,Metas!D:D,D80))) -> 0 | P80: 0.75 | Q80: 1.15 | R80: 0.9 | S80: 1.25
A81: 2026 | B81: 2 | C81: Carla Araujo | D81: carla.araujo@altoqi.com.br | E81: Governo | F81: Consultor | G81: 0.5 | H81: 6800 | I81: =IF(_xlfn.MAXIFS(Metas!J:J,Metas!A:A,A81,Metas!B:B,B81,Metas!D:D,D81) = 0,H81,H81 * (1-_xlfn.MAXIFS(Metas!J:J,Metas!A:A,A81,Metas!B:B,B81,Metas!D:D,D81))) -> 6800 | L81: =IF(_xlfn.MAXIFS(Metas!J:J,Metas!A:A,A81,Metas!B:B,B81,Metas!D:D,D81) = 0,K81,K81 * (1-_xlfn.MAXIFS(Metas!J:J,Metas!A:A,A81,Metas!B:B,B81,Metas!D:D,D81))) -> 0 | O81: =IF(_xlfn.MAXIFS(Metas!J:J,Metas!A:A,A81,Metas!B:B,B81,Metas!D:D,D81) = 0,N81,N81 * (1-_xlfn.MAXIFS(Metas!J:J,Metas!A:A,A81,Metas!B:B,B81,Metas!D:D,D81))) -> 0 | P81: 0.75 | Q81: 1.15 | R81: 0.9 | S81: 1.25
A82: 2026 | B82: 2 | C82: Deize Marla Rudek | D82: deize.rudek@altoqi.com.br | E82: Governo | F82: Consultor | G82: 0.5 | H82: 5600 | I82: =IF(_xlfn.MAXIFS(Metas!J:J,Metas!A:A,A82,Metas!B:B,B82,Metas!D:D,D82) = 0,H82,H82 * (1-_xlfn.MAXIFS(Metas!J:J,Metas!A:A,A82,Metas!B:B,B82,Metas!D:D,D82))) -> 5600 | L82: =IF(_xlfn.MAXIFS(Metas!J:J,Metas!A:A,A82,Metas!B:B,B82,Metas!D:D,D82) = 0,K82,K82 * (1-_xlfn.MAXIFS(Metas!J:J,Metas!A:A,A82,Metas!B:B,B82,Metas!D:D,D82))) -> 0 | O82: =IF(_xlfn.MAXIFS(Metas!J:J,Metas!A:A,A82,Metas!B:B,B82,Metas!D:D,D82) = 0,N82,N82 * (1-_xlfn.MAXIFS(Metas!J:J,Metas!A:A,A82,Metas!B:B,B82,Metas!D:D,D82))) -> 0 | P82: 0.75 | Q82: 1.15 | R82: 0.9 | S82: 1.25
... A91: 2026 | B91: 2 | C91: Tabata Couto | D91: tabata.couto@altoqi.com.br | E91: Governo | F91: Consultor | G91: 0.5 | H91: 5600 | I91: =IF(_xlfn.MAXIFS(Metas!J:J,Metas!A:A,A91,Metas!B:B,B91,Metas!D:D,D91) = 0,H91,H91 * (1-_xlfn.MAXIFS(Metas!J:J,Metas!A:A,A91,Metas!B:B,B91,Metas!D:D,D91))) -> 5600 | L91: =IF(_xlfn.MAXIFS(Metas!J:J,Metas!A:A,A91,Metas!B:B,B91,Metas!D:D,D91) = 0,K91,K91 * (1-_xlfn.MAXIFS(Metas!J:J,Metas!A:A,A91,Metas!B:B,B91,Metas!D:D,D91))) -> 0 | O91: =IF(_xlfn.MAXIFS(Metas!J:J,Metas!A:A,A91,Metas!B:B,B91,Metas!D:D,D91) = 0,N91,N91 * (1-_xlfn.MAXIFS(Metas!J:J,Metas!A:A,A91,Metas!B:B,B91,Metas!D:D,D91))) -> 0 | P91: 0.75 | Q91: 1.15 | R91: 0.9 | S91: 1.25
A92: 2026 | B92: 2 | C92: Beatriz Nau | D92: beatriz@altoqi.com.br | E92: Saving | F92: Gestor | G92: 0.6 | H92: 2400 | I92: =IF(_xlfn.MAXIFS(Metas!J:J,Metas!A:A,A92,Metas!B:B,B92,Metas!D:D,D92) = 0,H92,H92 * (1-_xlfn.MAXIFS(Metas!J:J,Metas!A:A,A92,Metas!B:B,B92,Metas!D:D,D92))) -> 2400 | J92: 0.75 | K92: 9600 | L92: =IF(_xlfn.MAXIFS(Metas!J:J,Metas!A:A,A92,Metas!B:B,B92,Metas!D:D,D92) = 0,K92,K92 * (1-_xlfn.MAXIFS(Metas!J:J,Metas!A:A,A92,Metas!B:B,B92,Metas!D:D,D92))) -> 9600 | M92: 1 | N92: 12000 | O92: =IF(_xlfn.MAXIFS(Metas!J:J,Metas!A:A,A92,Metas!B:B,B92,Metas!D:D,D92) = 0,N92,N92 * (1-_xlfn.MAXIFS(Metas!J:J,Metas!A:A,A92,Metas!B:B,B92,Metas!D:D,D92))) -> 12000 | P92: 1 | Q92: 1.05 | R92: 1.1 | S92: 1.1 | V92: =J92 -> 0.75 | W92: 0.01
A93: 2026 | B93: 2 | C93: Cintia Faraco | D93: cintia@altoqi.com.br | E93: Saving | F93: Consultor | G93: 0.6 | H93: 1620 | I93: =IF(_xlfn.MAXIFS(Metas!J:J,Metas!A:A,A93,Metas!B:B,B93,Metas!D:D,D93) = 0,H93,H93 * (1-_xlfn.MAXIFS(Metas!J:J,Metas!A:A,A93,Metas!B:B,B93,Metas!D:D,D93))) -> 1620 | J93: 0.75 | K93: 6480 | L93: =IF(_xlfn.MAXIFS(Metas!J:J,Metas!A:A,A93,Metas!B:B,B93,Metas!D:D,D93) = 0,K93,K93 * (1-_xlfn.MAXIFS(Metas!J:J,Metas!A:A,A93,Metas!B:B,B93,Metas!D:D,D93))) -> 6480 | M93: 1 | N93: 8100 | O93: =IF(_xlfn.MAXIFS(Metas!J:J,Metas!A:A,A93,Metas!B:B,B93,Metas!D:D,D93) = 0,N93,N93 * (1-_xlfn.MAXIFS(Metas!J:J,Metas!A:A,A93,Metas!B:B,B93,Metas!D:D,D93))) -> 8100 | P93: 1 | Q93: 1.05 | R93: 1.1 | S93: 1.1 | V93: =J93 -> 0.75 | W93: 0.01
A94: 2026 | B94: 2 | C94: Francyellen Batista | D94: francyellen@altoqi.com.br | E94: Saving | F94: Consultor | G94: 0.6 | H94: 1080 | I94: =IF(_xlfn.MAXIFS(Metas!J:J,Metas!A:A,A94,Metas!B:B,B94,Metas!D:D,D94) = 0,H94,H94 * (1-_xlfn.MAXIFS(Metas!J:J,Metas!A:A,A94,Metas!B:B,B94,Metas!D:D,D94))) -> 1080 | J94: 0.75 | K94: 4320 | L94: =IF(_xlfn.MAXIFS(Metas!J:J,Metas!A:A,A94,Metas!B:B,B94,Metas!D:D,D94) = 0,K94,K94 * (1-_xlfn.MAXIFS(Metas!J:J,Metas!A:A,A94,Metas!B:B,B94,Metas!D:D,D94))) -> 4320 | M94: 1 | N94: 5400 | O94: =IF(_xlfn.MAXIFS(Metas!J:J,Metas!A:A,A94,Metas!B:B,B94,Metas!D:D,D94) = 0,N94,N94 * (1-_xlfn.MAXIFS(Metas!J:J,Metas!A:A,A94,Metas!B:B,B94,Metas!D:D,D94))) -> 5400 | P94: 1 | Q94: 1.05 | R94: 1.1 | S94: 1.1 | V94: =J94 -> 0.75 | W94: 0.01
A95: 2026 | B95: 2 | C95: Jaqueline Correa | D95: jaqueline.correa@altoqi.com.br | E95: Saving | F95: Consultor | G95: 0.6 | H95: 1080 | I95: =IF(_xlfn.MAXIFS(Metas!J:J,Metas!A:A,A95,Metas!B:B,B95,Metas!D:D,D95) = 0,H95,H95 * (1-_xlfn.MAXIFS(Metas!J:J,Metas!A:A,A95,Metas!B:B,B95,Metas!D:D,D95))) -> 1080 | J95: 0.75 | K95: 4320 | L95: =IF(_xlfn.MAXIFS(Metas!J:J,Metas!A:A,A95,Metas!B:B,B95,Metas!D:D,D95) = 0,K95,K95 * (1-_xlfn.MAXIFS(Metas!J:J,Metas!A:A,A95,Metas!B:B,B95,Metas!D:D,D95))) -> 4320 | M95: 1 | N95: 5400 | O95: =IF(_xlfn.MAXIFS(Metas!J:J,Metas!A:A,A95,Metas!B:B,B95,Metas!D:D,D95) = 0,N95,N95 * (1-_xlfn.MAXIFS(Metas!J:J,Metas!A:A,A95,Metas!B:B,B95,Metas!D:D,D95))) -> 5400 | P95: 1 | Q95: 1.05 | R95: 1.1 | S95: 1.1 | V95: =J95 -> 0.75 | W95: 0.01
A96: 2026 | B96: 2 | C96: Marcela Accacio | D96: marcela@altoqi.com.br | E96: Saving | F96: Consultor | G96: 0.6 | H96: 1620 | I96: =IF(_xlfn.MAXIFS(Metas!J:J,Metas!A:A,A96,Metas!B:B,B96,Metas!D:D,D96) = 0,H96,H96 * (1-_xlfn.MAXIFS(Metas!J:J,Metas!A:A,A96,Metas!B:B,B96,Metas!D:D,D96))) -> 1620 | J96: 0.75 | K96: 6480 | L96: =IF(_xlfn.MAXIFS(Metas!J:J,Metas!A:A,A96,Metas!B:B,B96,Metas!D:D,D96) = 0,K96,K96 * (1-_xlfn.MAXIFS(Metas!J:J,Metas!A:A,A96,Metas!B:B,B96,Metas!D:D,D96))) -> 6480 | M96: 1 | N96: 8100 | O96: =IF(_xlfn.MAXIFS(Metas!J:J,Metas!A:A,A96,Metas!B:B,B96,Metas!D:D,D96) = 0,N96,N96 * (1-_xlfn.MAXIFS(Metas!J:J,Metas!A:A,A96,Metas!B:B,B96,Metas!D:D,D96))) -> 8100 | P96: 1 | Q96: 1.05 | R96: 1.1 | S96: 1.1 | V96: =J96 -> 0.75 | W96: 0.01
A97: 2026 | B97: 2 | C97: Rosana Machado | D97: rosana@altoqi.com.br | E97: Saving | F97: Consultor | G97: 0.6 | H97: 1080 | I97: =IF(_xlfn.MAXIFS(Metas!J:J,Metas!A:A,A97,Metas!B:B,B97,Metas!D:D,D97) = 0,H97,H97 * (1-_xlfn.MAXIFS(Metas!J:J,Metas!A:A,A97,Metas!B:B,B97,Metas!D:D,D97))) -> 1080 | J97: 0.75 | K97: 4320 | L97: =IF(_xlfn.MAXIFS(Metas!J:J,Metas!A:A,A97,Metas!B:B,B97,Metas!D:D,D97) = 0,K97,K97 * (1-_xlfn.MAXIFS(Metas!J:J,Metas!A:A,A97,Metas!B:B,B97,Metas!D:D,D97))) -> 4320 | M97: 1 | N97: 5400 | O97: =IF(_xlfn.MAXIFS(Metas!J:J,Metas!A:A,A97,Metas!B:B,B97,Metas!D:D,D97) = 0,N97,N97 * (1-_xlfn.MAXIFS(Metas!J:J,Metas!A:A,A97,Metas!B:B,B97,Metas!D:D,D97))) -> 5400 | P97: 1 | Q97: 1.05 | R97: 1.1 | S97: 1.1 | V97: =J97 -> 0.75 | W97: 0.01
A98: 2026 | B98: 2 | C98: Rubia Estipe | D98: rubia.estipe@altoqi.com.br | E98: Saving | F98: Consultor | G98: 0.6 | H98: 1620 | I98: =IF(_xlfn.MAXIFS(Metas!J:J,Metas!A:A,A98,Metas!B:B,B98,Metas!D:D,D98) = 0,H98,H98 * (1-_xlfn.MAXIFS(Metas!J:J,Metas!A:A,A98,Metas!B:B,B98,Metas!D:D,D98))) -> 1620 | J98: 0.75 | K98: 6480 | L98: =IF(_xlfn.MAXIFS(Metas!J:J,Metas!A:A,A98,Metas!B:B,B98,Metas!D:D,D98) = 0,K98,K98 * (1-_xlfn.MAXIFS(Metas!J:J,Metas!A:A,A98,Metas!B:B,B98,Metas!D:D,D98))) -> 6480 | M98: 1 | N98: 8100 | O98: =IF(_xlfn.MAXIFS(Metas!J:J,Metas!A:A,A98,Metas!B:B,B98,Metas!D:D,D98) = 0,N98,N98 * (1-_xlfn.MAXIFS(Metas!J:J,Metas!A:A,A98,Metas!B:B,B98,Metas!D:D,D98))) -> 8100 | P98: 1 | Q98: 1.05 | R98: 1.1 | S98: 1.1 | V98: =J98 -> 0.75 | W98: 0.01
A99: 2026 | B99: 2 | C99: Silvia Estipe | D99: silvia.estipe@altoqi.com.br | E99: Saving | F99: Consultor | G99: 0.6 | H99: 1080 | I99: =IF(_xlfn.MAXIFS(Metas!J:J,Metas!A:A,A99,Metas!B:B,B99,Metas!D:D,D99) = 0,H99,H99 * (1-_xlfn.MAXIFS(Metas!J:J,Metas!A:A,A99,Metas!B:B,B99,Metas!D:D,D99))) -> 1080 | J99: 0.75 | K99: 4320 | L99: =IF(_xlfn.MAXIFS(Metas!J:J,Metas!A:A,A99,Metas!B:B,B99,Metas!D:D,D99) = 0,K99,K99 * (1-_xlfn.MAXIFS(Metas!J:J,Metas!A:A,A99,Metas!B:B,B99,Metas!D:D,D99))) -> 4320 | M99: 1 | N99: 5400 | O99: =IF(_xlfn.MAXIFS(Metas!J:J,Metas!A:A,A99,Metas!B:B,B99,Metas!D:D,D99) = 0,N99,N99 * (1-_xlfn.MAXIFS(Metas!J:J,Metas!A:A,A99,Metas!B:B,B99,Metas!D:D,D99))) -> 5400 | P99: 1 | Q99: 1.05 | R99: 1.1 | S99: 1.1 | V99: =J99 -> 0.75 | W99: 0.01
A100: 2026 | B100: 2 | C100: Sonia Maria Zielinski Pockszevnicki | D100: sonia.zielinski@altoqi.com.br | E100: Sonia | F100: Gestor | G100: 0.55 | H100: 8976 | I100: =IF(_xlfn.MAXIFS(Metas!J:J,Metas!A:A,A100,Metas!B:B,B100,Metas!D:D,D100) = 0,H100,H100 * (1-_xlfn.MAXIFS(Metas!J:J,Metas!A:A,A100,Metas!B:B,B100,Metas!D:D,D100))) -> 8976 | L100: =IF(_xlfn.MAXIFS(Metas!J:J,Metas!A:A,A100,Metas!B:B,B100,Metas!D:D,D100) = 0,K100,K100 * (1-_xlfn.MAXIFS(Metas!J:J,Metas!A:A,A100,Metas!B:B,B100,Metas!D:D,D100))) -> 0 | O100: =IF(_xlfn.MAXIFS(Metas!J:J,Metas!A:A,A100,Metas!B:B,B100,Metas!D:D,D100) = 0,N100,N100 * (1-_xlfn.MAXIFS(Metas!J:J,Metas!A:A,A100,Metas!B:B,B100,Metas!D:D,D100))) -> 0 | P100: 0.95 | Q100: 1.15 | R100: 1.05 | S100: 1.25 | V100: =G100 -> 0.55 | W100: 0.005
A101: 2026 | B101: 3 | C101: Anderson Ortiz | D101: anderson.ortiz@altoqi.com.br | E101: Ares | F101: Consultor | G101: 0.55 | H101: 3960 | I101: =IF(_xlfn.MAXIFS(Metas!J:J,Metas!A:A,A101,Metas!B:B,B101,Metas!D:D,D101) = 0,H101,H101 * (1-_xlfn.MAXIFS(Metas!J:J,Metas!A:A,A101,Metas!B:B,B101,Metas!D:D,D101))) -> 3960 | L101: =IF(_xlfn.MAXIFS(Metas!J:J,Metas!A:A,A101,Metas!B:B,B101,Metas!D:D,D101) = 0,K101,K101 * (1-_xlfn.MAXIFS(Metas!J:J,Metas!A:A,A101,Metas!B:B,B101,Metas!D:D,D101))) -> 0 | O101: =IF(_xlfn.MAXIFS(Metas!J:J,Metas!A:A,A101,Metas!B:B,B101,Metas!D:D,D101) = 0,N101,N101 * (1-_xlfn.MAXIFS(Metas!J:J,Metas!A:A,A101,Metas!B:B,B101,Metas!D:D,D101))) -> 0 | P101: 0.95 | Q101: 1.15 | R101: 1.05 | S101: 1.25 | V101: =G101 -> 0.55 | W101: 0.02
A102: 2026 | B102: 3 | C102: Francisco Guilherme Junior | D102: francisco.junior@altoqi.com.br | E102: Ares | F102: Consultor | G102: 0.55 | H102: 4176 | I102: =IF(_xlfn.MAXIFS(Metas!J:J,Metas!A:A,A102,Metas!B:B,B102,Metas!D:D,D102) = 0,H102,H102 * (1-_xlfn.MAXIFS(Metas!J:J,Metas!A:A,A102,Metas!B:B,B102,Metas!D:D,D102))) -> 4176 | L102: =IF(_xlfn.MAXIFS(Metas!J:J,Metas!A:A,A102,Metas!B:B,B102,Metas!D:D,D102) = 0,K102,K102 * (1-_xlfn.MAXIFS(Metas!J:J,Metas!A:A,A102,Metas!B:B,B102,Metas!D:D,D102))) -> 0 | O102: =IF(_xlfn.MAXIFS(Metas!J:J,Metas!A:A,A102,Metas!B:B,B102,Metas!D:D,D102) = 0,N102,N102 * (1-_xlfn.MAXIFS(Metas!J:J,Metas!A:A,A102,Metas!B:B,B102,Metas!D:D,D102))) -> 0 | P102: 0.95 | Q102: 1.15 | R102: 1.05 | S102: 1.25 | V102: =G102 -> 0.55 | W102: 0.02
A103: 2026 | B103: 3 | C103: Rodrigo da Rosa Lima | D103: rodrigo.lima@altoqi.com.br | E103: Ares | F103: Consultor | G103: 0.55 | H103: 3564 | I103: =IF(_xlfn.MAXIFS(Metas!J:J,Metas!A:A,A103,Metas!B:B,B103,Metas!D:D,D103) = 0,H103,H103 * (1-_xlfn.MAXIFS(Metas!J:J,Metas!A:A,A103,Metas!B:B,B103,Metas!D:D,D103))) -> 3564 | L103: =IF(_xlfn.MAXIFS(Metas!J:J,Metas!A:A,A103,Metas!B:B,B103,Metas!D:D,D103) = 0,K103,K103 * (1-_xlfn.MAXIFS(Metas!J:J,Metas!A:A,A103,Metas!B:B,B103,Metas!D:D,D103))) -> 0 | O103: =IF(_xlfn.MAXIFS(Metas!J:J,Metas!A:A,A103,Metas!B:B,B103,Metas!D:D,D103) = 0,N103,N103 * (1-_xlfn.MAXIFS(Metas!J:J,Metas!A:A,A103,Metas!B:B,B103,Metas!D:D,D103))) -> 0 | P103: 0.95 | Q103: 1.15 | R103: 1.05 | S103: 1.25 | V103: =G103 -> 0.55 | W103: 0.02
A104: 2026 | B104: 3 | C104: Eloyse Silveira | D104: eloyse.silveira@altoqi.com.br | E104: B2B Construtora | F104: Consultor | G104: 0.55 | H104: 4176 | I104: =IF(_xlfn.MAXIFS(Metas!J:J,Metas!A:A,A104,Metas!B:B,B104,Metas!D:D,D104) = 0,H104,H104 * (1-_xlfn.MAXIFS(Metas!J:J,Metas!A:A,A104,Metas!B:B,B104,Metas!D:D,D104))) -> 2088 | L104: =IF(_xlfn.MAXIFS(Metas!J:J,Metas!A:A,A104,Metas!B:B,B104,Metas!D:D,D104) = 0,K104,K104 * (1-_xlfn.MAXIFS(Metas!J:J,Metas!A:A,A104,Metas!B:B,B104,Metas!D:D,D104))) -> 0 | O104: =IF(_xlfn.MAXIFS(Metas!J:J,Metas!A:A,A104,Metas!B:B,B104,Metas!D:D,D104) = 0,N104,N104 * (1-_xlfn.MAXIFS(Metas!J:J,Metas!A:A,A104,Metas!B:B,B104,Metas!D:D,D104))) -> 0 | P104: 0.95 | Q104: 1.15 | R104: 1.05 | S104: 1.25 | V104: =G104 -> 0.55 | W104: 0.02
A105: 2026 | B105: 3 | C105: Henrique Teixeira Silva | D105: henrique.silva@altoqi.com.br | E105: B2B Construtora | F105: Consultor | G105: 0.55 | H105: 4176 | I105: =IF(_xlfn.MAXIFS(Metas!J:J,Metas!A:A,A105,Metas!B:B,B105,Metas!D:D,D105) = 0,H105,H105 * (1-_xlfn.MAXIFS(Metas!J:J,Metas!A:A,A105,Metas!B:B,B105,Metas!D:D,D105))) -> 4176 | L105: =IF(_xlfn.MAXIFS(Metas!J:J,Metas!A:A,A105,Metas!B:B,B105,Metas!D:D,D105) = 0,K105,K105 * (1-_xlfn.MAXIFS(Metas!J:J,Metas!A:A,A105,Metas!B:B,B105,Metas!D:D,D105))) -> 0 | O105: =IF(_xlfn.MAXIFS(Metas!J:J,Metas!A:A,A105,Metas!B:B,B105,Metas!D:D,D105) = 0,N105,N105 * (1-_xlfn.MAXIFS(Metas!J:J,Metas!A:A,A105,Metas!B:B,B105,Metas!D:D,D105))) -> 0 | P105: 0.95 | Q105: 1.15 | R105: 1.05 | S105: 1.25 | V105: =G105 -> 0.55 | W105: 0.02
A106: 2026 | B106: 3 | C106: Rafael Acencio | D106: rafael.acencio@altoqi.com.br | E106: B2B Construtora | F106: Consultor | G106: 0.55 | H106: 5297 | I106: =IF(_xlfn.MAXIFS(Metas!J:J,Metas!A:A,A106,Metas!B:B,B106,Metas!D:D,D106) = 0,H106,H106 * (1-_xlfn.MAXIFS(Metas!J:J,Metas!A:A,A106,Metas!B:B,B106,Metas!D:D,D106))) -> 5297 | L106: =IF(_xlfn.MAXIFS(Metas!J:J,Metas!A:A,A106,Metas!B:B,B106,Metas!D:D,D106) = 0,K106,K106 * (1-_xlfn.MAXIFS(Metas!J:J,Metas!A:A,A106,Metas!B:B,B106,Metas!D:D,D106))) -> 0 | O106: =IF(_xlfn.MAXIFS(Metas!J:J,Metas!A:A,A106,Metas!B:B,B106,Metas!D:D,D106) = 0,N106,N106 * (1-_xlfn.MAXIFS(Metas!J:J,Metas!A:A,A106,Metas!B:B,B106,Metas!D:D,D106))) -> 0 | P106: 0.95 | Q106: 1.15 | R106: 1.05 | S106: 1.25 | V106: =G106 -> 0.55 | W106: 0.02
A107: 2026 | B107: 3 | C107: Fernanda da Silva Fertonani | D107: fernanda.fertonani@altoqi.com.br | E107: B2B Escritório | F107: Consultor | G107: 0.55 | H107: 4176 | I107: =IF(_xlfn.MAXIFS(Metas!J:J,Metas!A:A,A107,Metas!B:B,B107,Metas!D:D,D107) = 0,H107,H107 * (1-_xlfn.MAXIFS(Metas!J:J,Metas!A:A,A107,Metas!B:B,B107,Metas!D:D,D107))) -> 4176 | L107: =IF(_xlfn.MAXIFS(Metas!J:J,Metas!A:A,A107,Metas!B:B,B107,Metas!D:D,D107) = 0,K107,K107 * (1-_xlfn.MAXIFS(Metas!J:J,Metas!A:A,A107,Metas!B:B,B107,Metas!D:D,D107))) -> 0 | O107: =IF(_xlfn.MAXIFS(Metas!J:J,Metas!A:A,A107,Metas!B:B,B107,Metas!D:D,D107) = 0,N107,N107 * (1-_xlfn.MAXIFS(Metas!J:J,Metas!A:A,A107,Metas!B:B,B107,Metas!D:D,D107))) -> 0 | P107: 0.95 | Q107: 1.15 | R107: 1.05 | S107: 1.25 | V107: =G107 -> 0.55 | W107: 0.02
A108: 2026 | B108: 3 | C108: Rafael Marquez Motta | D108: rafael.motta@altoqi.com.br | E108: B2B Escritório | F108: Gestor | G108: 0.55 | H108: 6600 | I108: =IF(_xlfn.MAXIFS(Metas!J:J,Metas!A:A,A108,Metas!B:B,B108,Metas!D:D,D108,Metas!E:E,E108) = 0,H108,H108 * (1-_xlfn.MAXIFS(Metas!J:J,Metas!A:A,A108,Metas!B:B,B108,Metas!D:D,D108,Metas!E:E,E108))) -> 5100 | L108: =IF(_xlfn.MAXIFS(Metas!J:J,Metas!A:A,A108,Metas!B:B,B108,Metas!D:D,D108) = 0,K108,K108 * (1-_xlfn.MAXIFS(Metas!J:J,Metas!A:A,A108,Metas!B:B,B108,Metas!D:D,D108))) -> 0 | O108: =IF(_xlfn.MAXIFS(Metas!J:J,Metas!A:A,A108,Metas!B:B,B108,Metas!D:D,D108) = 0,N108,N108 * (1-_xlfn.MAXIFS(Metas!J:J,Metas!A:A,A108,Metas!B:B,B108,Metas!D:D,D108))) -> 0 | P108: 0.95 | Q108: 1.15 | R108: 1.05 | S108: 1.25 | V108: =G108 -> 0.55 | W108: 0.02
...

Sheet Acel Form Pag
A1: Ano | B1: Mês | C1: Pipeline | D1: À Vista | E1: CC Até 3x | F1: CC Até 12x | G1: Recorrente
A2: 2026 | B2: 1 | C2: Ares | D2: 1.3 | E2: 1.2 | F2: 1.15 | G2: 1
A3: 2026 | B3: 1 | C3: B2B | D3: 1.3 | E3: 1.2 | F3: 1.15 | G3: 1
A4: 2026 | B4: 1 | C4: B2B Construtora | D4: 1.3 | E4: 1.2 | F4: 1.15 | G4: 1
A5: 2026 | B5: 1 | C5: B2B Escritório | D5: 1.3 | E5: 1.2 | F5: 1.15 | G5: 1
A6: 2026 | B6: 1 | C6: B2E | D6: 1.3 | E6: 1.2 | F6: 1.15 | G6: 1
A7: 2026 | B7: 1 | C7: Farmer | D7: 1.5 | E7: 1.4 | F7: 1.25 | G7: 1
A8: 2026 | B8: 1 | C8: FSB | D8: 1.3 | E8: 1.2 | F8: 1.15 | G8: 0.9
A9: 2026 | B9: 1 | C9: Renovação | D9: 1.3 | E9: 1.2 | F9: 1.15 | G9: 0.9
A10: 2026 | B10: 1 | C10: Saving | D10: 1.2 | E10: 1.15 | F10: 1.1 | G10: 1
A11: 2026 | B11: 1 | C11: Sonia | D11: 1.4 | E11: 1.3 | F11: 1.2 | G11: 1
A12: 2026 | B12: 2 | C12: Ares | D12: 1.3 | E12: 1.2 | F12: 1.15 | G12: 1
A13: 2026 | B13: 2 | C13: B2B | D13: 1.3 | E13: 1.2 | F13: 1.15 | G13: 1
... A36: 2026 | B36: 4 | C36: FSB | D36: 1.3 | E36: 1.15 | F36: 1.15 | G36: 1
A37: 2026 | B37: 4 | C37: Saving
A38: 2026 | B38: 4 | C38: Sonia | D38: 1.4 | E38: 1.3 | F38: 1.2 | G38: 1
A39: 2026 | B39: 5 | C39: Ares | D39: 1.3 | E39: 1.15 | F39: 1.15 | G39: 1
A40: 2026 | B40: 5 | C40: B2B Construtora | D40: 1.3 | E40: 1.15 | F40: 1.15 | G40: 1
A41: 2026 | B41: 5 | C41: B2B Escritório | D41: 1.3 | E41: 1.15 | F41: 1.15 | G41: 1
A42: 2026 | B42: 5 | C42: Farmer | D42: 1.5 | E42: 1.25 | F42: 1.25 | G42: 1
A43: 2026 | B43: 5 | C43: FSB | D43: 1.3 | E43: 1.15 | F43: 1.15 | G43: 1
A44: 2026 | B44: 5 | C44: Saving
A45: 2026 | B45: 5 | C45: Sonia | D45: 1.4 | E45: 1.3 | F45: 1.2 | G45: 1

Sheet Patamares Saving
A1: Ano | B1: Mês | C1: Patamar | D1: %
A2: 2026 | B2: 4 | C2: 0.6 | D2: 0.55
A3: 2026 | B3: 4 | C3: 0.7 | D3: 0.7
A4: 2026 | B4: 4 | C4: 0.8 | D4: 0.85
A5: 2026 | B5: 4 | C5: 0.9 | D5: 0.95
A6: 2026 | B6: 4 | C6: 1 | D6: 1.05
A7: 2026 | B7: 4 | C7: 1.1 | D7: 1.1
A8: 2026 | B8: 5 | C8: 0.6 | D8: 0.55
A9: 2026 | B9: 5 | C9: 0.7 | D9: 0.7
A10: 2026 | B10: 5 | C10: 0.8 | D10: 0.85
A11: 2026 | B11: 5 | C11: 0.9 | D11: 0.95
A12: 2026 | B12: 5 | C12: 1 | D12: 1.05
A13: 2026 | B13: 5 | C13: 1.1 | D13: 1.1

Sheet Recuperação de Canc e Divs
A1: Recuperação de Dívidas | F1: Recuperação de Cancelamentos
A2: Ano | B2: Mês | C2: Consultora | D2: Valor | F2: Ano | G2: Mês | H2: Consultora | I2: Link | J2: Contrato | K2: Fechamento | L2: Data de Início | M2: Data de Renovação | N2: Valor Original | O2: Valor Ajustado | P2: Comissão
A3: 2026 | B3: 1 | C3: cintia@altoqi.com.br | D3: 0 | F3: 2026 | G3: 1 | H3: raquel.zanatta@altoqi.com.br | I3: https://app.hubspot.com/contacts/44552714/record/0-3/51931137662/ | J3: 317770 | K3: 46030 | L3: 45455 | M3: 46558 | N3: 10161.15 | O3: =(M3-K3) * N3 / (M3-L3) -> 4864.0863 | P3: =O3*0.02 -> 97.281726 | Q3: =(M3-K3)/30.44 -> 17.345598 | R3: =O3/Q3 -> 280.42195
A4: 2026 | B4: 1 | C4: francyellen@altoqi.com.br | D4: 2661.2 | F4: 2026 | G4: 1 | H4: raquel.zanatta@altoqi.com.br | I4: https://app.hubspot.com/contacts/44552714/record/0-3/54286871438/ | J4: 326499 | K4: 46051 | L4: 46019 | M4: 46384 | N4: 9354 | O4: =(M4-K4) * N4 / (M4-L4) -> 8533.9233 | P4: =O4*0.02 -> 170.67847 | Q4: =(M4-K4)/30.44 -> 10.939553 | R4: =O4/Q4 -> 780.09797
A5: 2026 | B5: 1 | C5: jaqueline.correa@altoqi.com.br | D5: 7393.31 | F5: 2026 | G5: 1 | H5: raquel.zanatta@altoqi.com.br | I5: https://app.hubspot.com/contacts/44552714/record/0-3/54347298840/ | J5: 327694 | K5: 46050 | L5: 46008 | M5: 46373 | N5: 9354 | O5: =(M5-K5) * N5 / (M5-L5) -> 8277.6493 | P5: =O5*0.02 -> 165.55299 | Q5: =(M5-K5)/30.44 -> 10.611038 | R5: =O5/Q5 -> 780.09797
A6: 2026 | B6: 1 | C6: marcela@altoqi.com.br | D6: 2102.28 | F6: 2026 | G6: 1 | H6: raquel.zanatta@altoqi.com.br | I6: https://app.hubspot.com/contacts/44552714/record/0-3/52580585476/ | J6: 502829 | K6: 46030 | L6: 45983 | M6: 46348 | N6: 8418.6 | O6: =(M6-K6) * N6 / (M6-L6) -> 7334.5611 | P6: =O6*0.02 -> 146.69122 | Q6: =(M6-K6)/30.44 -> 10.446781 | R6: =O6/Q6 -> 702.08818
A7: 2026 | B7: 1 | C7: rosana@altoqi.com.br | D7: 3626.1 | F7: 2026 | G7: 1 | H7: raquel.zanatta@altoqi.com.br | I7: https://app.hubspot.com/contacts/44552714/record/0-3/53676149284/ | J7: 520856 | K7: 46043 | L7: 45586 | M7: 46681 | N7: 17751.6 | O7: =(M7-K7) * N7 / (M7-L7) -> 10342.941 | P7: =O7*0.02 -> 206.85883 | Q7: =(M7-K7)/30.44 -> 20.959264 | R7: =O7/Q7 -> 493.47827
A8: 2026 | B8: 2 | C8: aline.pureza@altoqi.com.br | D8: 1228.65 | F8: 2026 | G8: 1 | H8: barbara.oliveira@altoqi.com.br | I8: https://app.hubspot.com/contacts/44552714/record/0-3/53746796930/ | J8: 539718 | K8: 46035 | L8: 45481 | M8: 46941 | N8: 18956.83 | O8: =(M8-K8) * N8 / (M8-L8) -> 11763.622 | P8: =O8*0.02 -> 235.27244 | Q8: =(M8-K8)/30.44 -> 29.763469 | R8: =O8/Q8 -> 395.23692
A9: 2026 | B9: 2 | C9: cintia@altoqi.com.br | D9: 3072.03 | F9: 2026 | G9: 1 | H9: barbara.oliveira@altoqi.com.br | I9: https://app.hubspot.com/contacts/44552714/record/0-3/52875501423/ | J9: 547738 | K9: 46045 | L9: 45936 | M9: 46301 | N9: 2294.4 | O9: =(M9-K9) * N9 / (M9-L9) -> 1609.223 | P9: =O9*0.02 -> 32.18446 | Q9: =(M9-K9)/30.44 -> 8.4099869 | R9: =O9/Q9 -> 191.34667
A10: 2026 | B10: 2 | C10: francyellen@altoqi.com.br | D10: 12113.1 | F10: 2026 | G10: 1 | H10: raquel.zanatta@altoqi.com.br | I10: https://app.hubspot.com/contacts/44552714/record/0-3/53395107509/ | J10: 620833 | K10: 46042 | L10: 45913 | M10: 46278 | N10: 4892.4 | O10: =(M10-K10) * N10 / (M10-L10) -> 3163.3052 | P10: =O10*0.02 -> 63.266104 | Q10: =(M10-K10)/30.44 -> 7.7529566 | R10: =O10/Q10 -> 408.01276
A11: 2026 | B11: 2 | C11: jaqueline.correa@altoqi.com.br | D11: 1502.19 | F11: 2026 | G11: 1 | H11: raquel.zanatta@altoqi.com.br | I11: https://app.hubspot.com/contacts/44552714/record/0-3/52590399574/ | J11: 623478 | K11: 46031 | L11: 45968 | M11: 46333 | N11: 5627.16 | O11: =(M11-K11) * N11 / (M11-L11) -> 4655.8968 | P11: =O11*0.02 -> 93.117935 | Q11: =(M11-K11)/30.44 -> 9.9211564 | R11: =O11/Q11 -> 469.28973
A12: 2026 | B12: 2 | C12: marcela@altoqi.com.br | D12: 14394.09 | F12: 2026 | G12: 1 | H12: barbara.oliveira@altoqi.com.br | I12: https://app.hubspot.com/contacts/44552714/record/0-3/53502195048/ | J12: 624022 | K12: 46053 | L12: 45618 | M12: 46713 | N12: 10506.6 | O12: =(M12-K12) * N12 / (M12-L12) -> 6332.7452 | P12: =O12*0.02 -> 126.6549 | Q12: =(M12-K12)/30.44 -> 21.681997 | R12: =O12/Q12 -> 292.07388
A13: 2026 | B13: 2 | C13: rosana@altoqi.com.br | D13: 6187.98 | F13: 2026 | G13: 1 | H13: raquel.zanatta@altoqi.com.br | I13: https://app.hubspot.com/contacts/44552714/record/0-3/51940525129/ | J13: 628533 | K13: 46030 | L13: 45758 | M13: 46854 | N13: 11145.6 | O13: =(M13-K13) * N13 / (M13-L13) -> 8379.5387 | P13: =O13*0.02 -> 167.59077 | Q13: =(M13-K13)/30.44 -> 27.069645 | R13: =O13/Q13 -> 309.5548
A14: 2026 | B14: 2 | C14: rubia.estipe@altoqi.com.br | D14: 0 | F14: 2026 | G14: 1 | H14: raquel.zanatta@altoqi.com.br | I14: https://app.hubspot.com/contacts/44552714/record/0-3/52252501884/ | J14: 633657 | K14: 46030 | L14: 45957 | M14: 46322 | N14: 10166.4 | O14: =(M14-K14) * N14 / (M14-L14) -> 8133.12 | P14: =O14*0.02 -> 162.6624 | Q14: =(M14-K14)/30.44 -> 9.5926413 | R14: =O14/Q14 -> 847.84991
... A36: 2026 | B36: 5 | C36: silvia.estipe@altoqi.com.br | D36: 7830.6 | F36: 2026 | G36: 3 | H36: raquel.zanatta@altoqi.com.br | I36: https://app.hubspot.com/contacts/44552714/record/0-3/52218593300 | J36: 620950 | K36: 46097 | L36: 45918 | M36: 46283 | N36: 5436 | O36: =(M36-K36) * N36 / (M36-L36) -> 2770.126 | P36: =O36*0.02 -> 55.402521 | Q36: =(M36-K36)/30.44 -> 6.1103811 | R36: =O36/Q36 -> 453.34751
F37: 2026 | G37: 3 | H37: raquel.zanatta@altoqi.com.br | I37: https://app.hubspot.com/contacts/44552714/record/0-3/53700973447 | J37: 624990 | K37: 46097 | L37: 45643 | M37: 46738 | N37: 5592.6 | O37: =(M37-K37) * N37 / (M37-L37) -> 3273.8416 | P37: =O37*0.02 -> 65.476833 | Q37: =(M37-K37)/30.44 -> 21.057819 | R37: =O37/Q37 -> 155.46917
F38: 2026 | G38: 3 | H38: raquel.zanatta@altoqi.com.br | I38: https://app.hubspot.com/contacts/44552714/record/0-3/54019420841 | J38: 625119 | K38: 46084 | L38: 45649 | M38: 46744 | N38: 16502.4 | O38: =(M38-K38) * N38 / (M38-L38) -> 9946.6521 | P38: =O38*0.02 -> 198.93304 | Q38: =(M38-K38)/30.44 -> 21.681997 | R38: =O38/Q38 -> 458.75165
F39: 2026 | G39: 3 | H39: raquel.zanatta@altoqi.com.br | I39: https://app.hubspot.com/contacts/44552714/record/0-3/58208753066 | J39: 626540 | K39: 46107 | L39: 46066 | M39: 46431 | N39: 4074 | O39: =(M39-K39) * N39 / (M39-L39) -> 3616.3726 | P39: =O39*0.02 -> 72.327452 | Q39: =(M39-K39)/30.44 -> 10.64389 | R39: =O39/Q39 -> 339.76044
F40: 2026 | G40: 3 | H40: raquel.zanatta@altoqi.com.br | I40: https://app.hubspot.com/contacts/44552714/record/0-3/54983983992 | J40: 627943 | K40: 46099 | L40: 46108 | M40: 46473 | N40: 4530.6 | O40: =(M40-K40) * N40 / (M40-L40) -> 4642.3134 | P40: =O40*0.02 -> 92.846268 | Q40: =(M40-K40)/30.44 -> 12.286465 | R40: =O40/Q40 -> 377.83963
F41: 2026 | G41: 3 | H41: raquel.zanatta@altoqi.com.br | I41: https://app.hubspot.com/contacts/44552714/record/0-3/53700973447 | J41: 628474 | K41: 46097 | L41: 45757 | M41: 46122 | N41: 2682 | O41: =(M41-K41) * N41 / (M41-L41) -> 183.69863 | P41: =O41*0.02 -> 3.6739726 | Q41: =(M41-K41)/30.44 -> 0.82128778 | R41: =O41/Q41 -> 223.67145
F42: 2026 | G42: 3 | H42: raquel.zanatta@altoqi.com.br | I42: https://app.hubspot.com/contacts/44552714/record/0-3/53269722885 | J42: 629046 | K42: 46094 | L42: 45776 | M42: 46141 | N42: 11976 | O42: =(M42-K42) * N42 / (M42-L42) -> 1542.1151 | P42: =O42*0.02 -> 30.842301 | Q42: =(M42-K42)/30.44 -> 1.544021 | R42: =O42/Q42 -> 998.76559
F43: 2026 | G43: 3 | H43: raquel.zanatta@altoqi.com.br | I43: https://app.hubspot.com/contacts/44552714/record/0-3/52920040752 | J43: 630551 | K43: 46097 | L43: 45838 | M43: 46203 | N43: 2638.56 | O43: =(M43-K43) * N43 / (M43-L43) -> 766.26674 | P43: =O43*0.02 -> 15.325335 | Q43: =(M43-K43)/30.44 -> 3.4822602 | R43: =O43/Q43 -> 220.04868
F44: 2026 | G44: 3 | H44: raquel.zanatta@altoqi.com.br | I44: https://app.hubspot.com/contacts/44552714/record/0-3/55803239863 | J44: 630846 | K44: 46087 | L44: 45847 | M44: 46212 | N44: 4983.24 | O44: =(M44-K44) * N44 / (M44-L44) -> 1706.589 | P44: =O44*0.02 -> 34.131781 | Q44: =(M44-K44)/30.44 -> 4.1064389 | R44: =O44/Q44 -> 415.58856
F45: 2026 | G45: 3 | H45: raquel.zanatta@altoqi.com.br | I45: https://app.hubspot.com/contacts/44552714/record/0-3/52218593300 | J45: 631377 | K45: 46097 | L45: 45866 | M45: 46231 | N45: 3483 | O45: =(M45-K45) * N45 / (M45-L45) -> 1278.6904 | P45: =O45*0.02 -> 25.573808 | Q45: =(M45-K45)/30.44 -> 4.4021025 | R45: =O45/Q45 -> 290.47266
F46: 2026 | G46: 3 | H46: raquel.zanatta@altoqi.com.br | I46: https://app.hubspot.com/contacts/44552714/record/0-3/53874574998 | J46: 633093 | K46: 46097 | L46: 45930 | M46: 46295 | N46: 2868 | O46: =(M46-K46) * N46 / (M46-L46) -> 1555.7918 | P46: =O46*0.02 -> 31.115836 | Q46: =(M46-K46)/30.44 -> 6.5045992 | R46: =O46/Q46 -> 239.18334
F47: 2026 | G47: 3 | H47: raquel.zanatta@altoqi.com.br | I47: https://app.hubspot.com/contacts/44552714/record/0-3/54394608466 | J47: 633147 | K47: 46097 | L47: 45932 | M47: 46297 | N47: 2868 | O47: =(M47-K47) * N47 / (M47-L47) -> 1571.5068 | P47: =O47*0.02 -> 31.430137 | Q47: =(M47-K47)/30.44 -> 6.5703022 | R47: =O47/Q47 -> 239.18334
F48: 2026 | G48: 3 | H48: raquel.zanatta@altoqi.com.br | I48: https://app.hubspot.com/contacts/44552714/record/0-3/56989700430 | J48: 636080 | K48: 46107 | L48: 46065 | M48: 46430 | N48: 2874 | O48: =(M48-K48) * N48 / (M48-L48) -> 2543.2932 | P48: =O48*0.02 -> 50.865863 | Q48: =(M48-K48)/30.44 -> 10.611038 | R48: =O48/Q48 -> 239.68373
... F74: 2026 | G74: 4 | H74: barbara.oliveira@altoqi.com.br | I74: https://app.hubspot.com/contacts/44552714/record/0-3/59094203532 | J74: 635568 | K74: 46129 | L74: 46036 | M74: 46766 | N74: 52140.48 | O74: =(M74-K74) * N74 / (M74-L74) -> 45497.926 | P74: =O74*0.02 -> 909.95851 | Q74: =(M74-K74)/30.44 -> 20.926413 | R74: =O74/Q74 -> 2174.1866
F75: 2026 | G75: 5 | H75: Jessica.Souza@altoqi.com.br | I75: https://app.hubspot.com/contacts/44552714/record/0-3/60152450650 | J75: 315064 | K75: 46167.573 | L75: 45425 | M75: 46519 | N75: 10983.6 | O75: =(M75-K75) * N75 / (M75-L75) -> 3528.2765 | P75: =O75*0.02 -> 70.56553
F76: 2026 | G76: 5 | H76: raquel.zanatta@altoqi.com.br | I76: https://app.hubspot.com/contacts/44552714/record/0-3/54215388308 | J76: 318311 | K76: 46167.643 | L76: 45839 | M76: 46204 | N76: 18590.27 | O76: =(M76-K76) * N76 / (M76-L76) -> 1851.7409 | P76: =O76*0.02 -> 37.034817
F77: 2026 | G77: 5 | H77: raquel.zanatta@altoqi.com.br | I77: https://app.hubspot.com/contacts/44552714/record/0-3/59571141954 | J77: 522488 | K77: 46164.709 | L77: 45626 | M77: 46356 | N77: 22128.24 | O77: =(M77-K77) * N77 / (M77-L77) -> 5798.5377 | P77: =O77*0.02 -> 115.97075
F78: 2026 | G78: 5 | H78: raquel.zanatta@altoqi.com.br | I78: https://app.hubspot.com/contacts/44552714/record/0-3/58938837935 | J78: 540971 | K78: 46167.507 | L78: 45866 | M78: 46231 | N78: 4375.8 | O78: =(M78-K78) * N78 / (M78-L78) -> 761.18606 | P78: =O78*0.02 -> 15.223721
F79: 2026 | G79: 5 | H79: raquel.zanatta@altoqi.com.br | I79: https://app.hubspot.com/contacts/44552714/record/0-3/59148474778 | J79: 541570 | K79: 46168.524 | L79: 45492 | M79: 46595 | N79: 46951.8 | O79: =(M79-K79) * N79 / (M79-L79) -> 18153.975 | P79: =O79*0.02 -> 363.07949
F80: 2026 | G80: 5 | H80: raquel.zanatta@altoqi.com.br | I80: https://app.hubspot.com/contacts/44552714/record/0-3/57481967726 | J80: 546856 | K80: 46154.655 | L80: 45928 | M80: 46293 | N80: 13338.48 | O80: =(M80-K80) * N80 / (M80-L80) -> 5055.6544 | P80: =O80*0.02 -> 101.11309
F81: 2026 | G81: 5 | H81: raquel.zanatta@altoqi.com.br | I81: https://app.hubspot.com/contacts/44552714/record/0-3/57406379309 | J81: 608259 | K81: 46146.608 | L81: 46053 | M81: 46418 | N81: 2874 | O81: =(M81-K81) * N81 / (M81-L81) -> 2136.9305 | P81: =O81*0.02 -> 42.738611
F82: 2026 | G82: 5 | H82: raquel.zanatta@altoqi.com.br | I82: https://app.hubspot.com/contacts/44552714/record/0-3/55932340077 | J82: 620533 | K82: 46162.744 | L82: 45905 | M82: 46270 | N82: 22441.2 | O82: =(M82-K82) * N82 / (M82-L82) -> 6594.4081 | P82: =O82*0.02 -> 131.88816
F83: 2026 | G83: 5 | H83: raquel.zanatta@altoqi.com.br | I83: https://app.hubspot.com/contacts/44552714/record/0-3/60006796888 | J83: 621611 | K83: 46163.742 | L83: 45565 | M83: 46295 | N83: 14400 | O83: =(M83-K83) * N83 / (M83-L83) -> 2589.2055 | P83: =O83*0.02 -> 51.78411
F84: 2026 | G84: 5 | H84: raquel.zanatta@altoqi.com.br | I84: https://app.hubspot.com/contacts/44552714/record/0-3/59026335258 | J84: 624847 | K84: 46163.736 | L84: 45638 | M84: 46368 | N84: 5736 | O84: =(M84-K84) * N84 / (M84-L84) -> 1605.0105 | P84: =O84*0.02 -> 32.10021
F85: 2026 | G85: 5 | H85: raquel.zanatta@altoqi.com.br | I85: https://app.hubspot.com/contacts/44552714/record/0-3/60141334881 | J85: 625343 | K85: 46169.483 | L85: 45666 | M85: 46761 | N85: 16354.8 | O85: =(M85-K85) * N85 / (M85-L85) -> 8834.8385 | P85: =O85*0.02 -> 176.69677
F86: 2026 | G86: 5 | H86: raquel.zanatta@altoqi.com.br | I86: https://app.hubspot.com/contacts/44552714/record/0-3/58999706165 | J86: 631056 | K86: 46168.374 | L86: 45855 | M86: 46220 | N86: 4785.24 | O86: =(M86-K86) * N86 / (M86-L86) -> 676.83469 | P86: =O86*0.02 -> 13.536694
... F89: 2026 | G89: 5 | H89: raquel.zanatta@altoqi.com.br | I89: https://app.hubspot.com/contacts/44552714/record/0-3/59980855100 | J89: 637033 | K89: 46169.423 | L89: 46122 | M89: 46487 | N89: 4411.2 | O89: =(M89-K89) * N89 / (M89-L89) -> 3838.0713 | P89: =O89*0.02 -> 76.761426

Sheet Comissões
A1: {=_xlfn._xlws.FILTER(Metas!A:H,(Metas!A:A>2025)*(Metas!E:E<>"Governo")*(Metas!E:E<>"GD")*(((Metas!E:E<>"Saving")+(Metas!A:A<2026)+(Metas!B:B<5))>0))} -> Ano | B1: Mês | C1: Consultor | D1: Email | E1: Equipe | F1: Cargo | G1: Gestor | H1: Tipo | I1: Realizado | J1: Meta | K1: % Atingido | L1: Cliff | M1: Parte da verda | N1: % À Vista | O1: Mult | P1: Parte da verda | Q1: % CC até 3x | R1: Mult | S1: Parte da verda | T1: % CC até 12x | U1: Mult | V1: Parte da verda | W1: % Recorrente | X1: Mult | Y1: OTE Base | Z1: Acelerador OTE | AA1: OTE Ajustado | AB1: OTE Variável | AC1: Bookings Extras | AD1: Comissão Bookings Extras | AE1: Dívidas Pagas | AF1: Comissão Sobre Dívidas Pagas | AG1: Realizado Trimestral Individual | AH1: Meta Trimestral Individual | AI1: % Trimestral Individual | AJ1: Realizado Trimestral Equipe | AK1: Meta Trimestral Equipe | AL1: % Trimestral Equipe | AM1: Comissão Trimestral Individual | AN1: Comissão Trimestral Equipe
A2: 2026 | B2: 1 | C2: Anderson Ortiz | D2: anderson.ortiz@altoqi.com.br | E2: Ares | F2: Consultor | G2: sonia.zielinski@altoqi.com.br | H2: MRR | I2: =IF(AND(F2="Consultor",H2="MRR"),SUMIFS(Negócios!L:L,Negócios!A:A,A2,Negócios!B:B,B2,Negócios!P:P,D2), IF(AND(F2="Consultor",H2="Opps"),SUMIFS('Realizado GD'!D:D,'Realizado GD'!A:A,A2,'Realizado GD'!B:B,B2,'Realizado GD'!C:C,D2), IF(AND(F2="Gestor",H2="MRR"),SUMIFS(I:I,A:A,A2,B:B,B2,G:G,D2)))) -> 2260.05 | J2: =SUMIFS(Metas!K:K,Metas!A:A,A2,Metas!B:B,B2,Metas!D:D,D2,Metas!H:H,H2) -> 5000 | K2: =IFERROR(I2/J2,0) -> 0.45201 | L2: {=_xlfn.LET( _xlpm.g,_xlfn.MAXIFS(Parâmetros!G:G,Parâmetros!A:A,A2,Parâmetros!B:B,B2,Parâmetros!D:D,D2,Parâmetros!E:E,E2), _xlpm.j,_xlfn.MAXIFS(Parâmetros!J:J,Parâmetros!A:A,A2,Parâmetros!B:B,B2,Parâmetros!D:D,D2,Parâmetros!E:E,E2), _xlpm.m,_xlfn.MAXIFS(Parâmetros!M:M,Parâmetros!A:A,A2,Parâmetros!B:B,B2,Parâmetros!D:D,D2,Parâmetros!E:E,E2), IF(_xlpm.g=0,"",TEXT(_xlpm.g,"0,00%")) & IF(AND(_xlpm.g<>0,_xlpm.j<>0)," | ","") & IF(_xlpm.j=0,"",TEXT(_xlpm.j,"0,00%")) & IF(AND(OR(_xlpm.g<>0,_xlpm.j<>0),_xlpm.m<>0)," | ","") & IF(_xlpm.m=0,"",TEXT(_xlpm.m,"0,00%")) )} -> 55,00% | M2: =IF(AND(F2="Gestor",H2="MRR"),SUMIFS(M:M,A:A,A2,B:B,B2,G:G,D2), SUMIFS(Negócios!L:L,Negócios!A:A,A2,Negócios!B:B,B2,Negócios!P:P,D2,Negócios!AG:AG,"À Vista",Negócios!Q:Q,E2)) -> 1059.21 | N2: =IFERROR(M2/$I2,0) -> 0.46866662 | O2: =SUMIFS('Acel Form Pag'!D:D,'Acel Form Pag'!A:A,A2,'Acel Form Pag'!B:B,B2,'Acel Form Pag'!C:C,E2) -> 1.3 | P2: =IF(AND(F2="Gestor",H2="MRR"),SUMIFS(P:P,A:A,A2,B:B,B2,G:G,D2), SUMIFS(Negócios!L:L,Negócios!A:A,A2,Negócios!B:B,B2,Negócios!P:P,D2,Negócios!AG:AG,"CC 3x",Negócios!Q:Q,E2)) -> 0 | Q2: =IFERROR(P2/$I2,0) -> 0 | R2: =SUMIFS('Acel Form Pag'!E:E,'Acel Form Pag'!A:A,A2,'Acel Form Pag'!B:B,B2,'Acel Form Pag'!C:C,E2) -> 1.2 | S2: =IF(AND(F2="Gestor",H2="MRR"),SUMIFS(S:S,A:A,A2,B:B,B2,G:G,D2), SUMIFS(Negócios!L:L,Negócios!A:A,A2,Negócios!B:B,B2,Negócios!P:P,D2,Negócios!AG:AG,"CC 12x",Negócios!Q:Q,E2)) -> 929.24 | T2: =IFERROR(S2/$I2,0) -> 0.41115905 | U2: =SUMIFS('Acel Form Pag'!F:F,'Acel Form Pag'!A:A,A2,'Acel Form Pag'!B:B,B2,'Acel Form Pag'!C:C,E2) -> 1.15 | V2: =IF(AND(F2="Gestor",H2="MRR"),SUMIFS(V:V,A:A,A2,B:B,B2,G:G,D2), SUMIFS(Negócios!L:L,Negócios!A:A,A2,Negócios!B:B,B2,Negócios!P:P,D2,Negócios!AG:AG,"Recorrente",Negócios!Q:Q,E2)) -> 271.6 | W2: =IFERROR(V2/$I2,0) -> 0.12017433 | X2: =SUMIFS('Acel Form Pag'!G:G,'Acel Form Pag'!A:A,A2,'Acel Form Pag'!B:B,B2,'Acel Form Pag'!C:C,E2) -> 1 | Y2: =MAX(_xlfn.MAXIFS(Parâmetros!O:O,Parâmetros!A:A,A2,Parâmetros!B:B,B2,Parâmetros!D:D,D2,Parâmetros!M:M,"<="&K2),_xlfn.MAXIFS(Parâmetros!L:L,Parâmetros!A:A,A2,Parâmetros!B:B,B2,Parâmetros!D:D,D2,Parâmetros!J:J,"<="&K2),_xlfn.MAXIFS(Parâmetros!I:I,Parâmetros!A:A,A2,Parâmetros!B:B,B2,Parâmetros!D:D,D2)) -> 1980 | Z2: =MAX(_xlfn.MAXIFS(Parâmetros!Q:Q,Parâmetros!A:A,A2,Parâmetros!B:B,B2,Parâmetros!D:D,D2,Parâmetros!E:E,E2,Parâmetros!P:P,"<="&K2), _xlfn.MAXIFS(Parâmetros!S:S,Parâmetros!A:A,A2,Parâmetros!B:B,B2,Parâmetros!D:D,D2,Parâmetros!E:E,E2,Parâmetros!R:R,"<="&K2), _xlfn.MAXIFS(Parâmetros!U:U,Parâmetros!A:A,A2,Parâmetros!B:B,B2,Parâmetros!D:D,D2,Parâmetros!E:E,E2,Parâmetros!T:T,"<="&K2),1) * IF(K2 >= SUMIFS(Parâmetros!G:G,Parâmetros!A:A,A2,Parâmetros!B:B,B2,Parâmetros!D:D,D2,Parâmetros!E:E,E2),1,0) -> 0 | AA2: =Y2*Z2*K2 -> 0 | AB2: =(AA2*N2*O2) + (AA2*Q2*R2) + (AA2*T2*U2) + (AA2*W2*X2) -> 0 | AC2: =IF(F2="Gestor",SUMIFS(AC:AC,A:A,A2,B:B,B2,G:G,D2), IF(E2="Saving",SUMIFS(Negócios!I:I,Negócios!A:A,A2,Negócios!B:B,B2,Negócios!P:P,D2,Negócios!H:H,"Curso") + SUMIFS(Negócios!I:I,Negócios!A:A,A2,Negócios!B:B,B2,Negócios!P:P,D2,Negócios!H:H,"Serviço") + SUMIFS(Negócios!I:I,Negócios!A:A,A2,Negócios!B:B,B2,Negócios!P:P,D2,Negócios!H:H,"Implementação"),SUMIFS(Negócios!I:I,Negócios!A:A,A2,Negócios!B:B,B2,Negócios!P:P,D2,Negócios!H:H,"Implementação"))) -> 0 | AD2: =SUMIFS(Parâmetros!W:W,Parâmetros!A:A,A2,Parâmetros!B:B,B2,Parâmetros!D:D,D2) * AC2 * IF(K2 >= SUMIFS(Parâmetros!V:V,Parâmetros!A:A,A2,Parâmetros!B:B,B2,Parâmetros!D:D,D2),1,0) -> 0 | AE2: =SUMIFS('Recuperação de Canc e Divs'!D:D,'Recuperação de Canc e Divs'!A:A,A2,'Recuperação de Canc e Divs'!B:B,B2,'Recuperação de Canc e Divs'!C:C,D2) -> 0 | AF2: =IF(K2>=SUMIFS(Parâmetros!J:J,Parâmetros!A:A,A2,Parâmetros!B:B,B2,Parâmetros!D:D,D2),AE2*0.025,0) -> 0 | AG2: =IF(OR(B2=3,B2=6,B2=9,B2=12), SUMIFS(I:I,$A:$A,$A2,$B:$B,">="&(B2-2),$B:$B,"<="&B2,$D:$D,$D2),"") | AH2: =IF(OR(B2=3,B2=6,B2=9,B2=12), SUMIFS(J:J,$A:$A,$A2,$B:$B,">="&(B2-2),$B:$B,"<="&B2,$D:$D,$D2),"") | AI2: =IFERROR(AG2/AH2,0) -> 0 | AJ2: =IF(F2="Gestor","", IF(OR(B2=3,B2=6,B2=9,B2=12), SUMIFS(I:I,$A:$A,$A2,$B:$B,">="&(B2-2),$B:$B,"<="&B2,$E:$E,$E2,$F:$F,"<>Gestor"), "")) | AK2: =IF(F2="Gestor","", IF(OR(B2=3,B2=6,B2=9,B2=12), SUMIFS(J:J,$A:$A,$A2,$B:$B,">="&(B2-2),$B:$B,"<="&B2,$E:$E,$E2,$F:$F,"<>Gestor"), "")) | AL2: =IFERROR(AJ2/AK2,0) -> 0 | AM2: =IF(AND(OR(B2=3,B2=6,B2=9,B2=12),AI2>=1), IF(F2="Gestor",AI2*0.6,AI2*0.3),"") | AN2: =IF(OR(B2=3,B2=6,B2=9,B2=12), IF(AND(AK2>=1,AI2>=SUMIFS(Parâmetros!G:G,Parâmetros!A:A,Comissões!A2,Parâmetros!B:B,Comissões!B2,Parâmetros!D:D,Comissões!D2,Parâmetros!E:E,Comissões!E2)),AI2*0.3,""),"")
